Workbook
Name AFJPs: Listas!$O$3:$O$15
Name LG: "LG"
Name ListaBancos: Listas!$C$5:$C$90
Name ListaContratos: #REF!
Name ListaDias: Listas!$H$2:$H$33
Name ListaEmpleados: Empleados!$E$7:$E$57
Name ListaEstadoCivil: Listas!$M$2:$M$7
Name ListaLegajo: Empleados!$C$7:$C$57
Name ListaMes: Listas!$F$3:$F$15
Name ListaMeses: Listas!$A$3:$A$124
Name ListaSexo: Listas!$L$3:$L$4
Name MatrizAntiguedad: Listas!$E$24:$G$38
Name MatrizDatos: #REF!
Name Provincias: Listas!$J$2:$J$26
Name TablaEmpleados: Empleados!$C$6:$P$57
Name TablaNoRemunerativo: 'Ret. VAV y SAC'!$B$6:$V$56
Name TablaNoRemunerativo: 'Ret. y no Rem.'!$B$6:$AL$56
Name TablaRemuneracion: Remuneración!$B$7:$AP$58

Sheet Listas
A1: 1 | H1: Días | J1: Provincia | M1: Estado Civil | O1: AFJP
A2: Lista Meses | C2: Entidad Bancaria: falta traer datos del Central | F2: Mes
C3: ListaBancos | H3: 1 | J3: Buenos Aires | L3: F | M3: Casado | O3: Arauca Bit
A4: 37622 | F4: Enero | H4: 2 | J4: Capital Federal | L4: M | M4: Soltero/a | O4: Consolidar
A5: 37653 | C5: Abn Amro Bank N. V. | F5: Febrero | H5: 3 | J5: Catamarca | M5: Divorciado/a | O5: Futura
A6: 37681 | C6: American Express Bank Ltd. | F6: Marzo | H6: 4 | J6: Chaco | M6: Viudo/a | O6: Generar
A7: 37712 | C7: B.I. Creditanstalt | F7: Abril | H7: 5 | J7: Chubut | M7: Concubinos/as | O7: Máxima
A8: 37742 | C8: Bacs Banco de Credito Y Securitizacion S | F8: Mayo | H8: 6 | J8: Córdoba | O8: Met
A9: 37773 | C9: Banca Nazionale del Lavoro | F9: Junio | H9: 7 | J9: Corrientes | O9: Nacion
A10: 37803 | C10: Banco de Balcarce | F10: Julio | H10: 8 | J10: Entre Ríos | O10: Orígenes
A11: 37834 | C11: Banco de Corrientes | F11: Agosto | H11: 9 | J11: Formosa | O11: Previsol
A12: 37865 | C12: Banco de Entre Rios | F12: Septiembre | H12: 10 | J12: Jujuy | O12: Profesión + Auge
A13: 37895 | C13: Banco de Formosa | F13: Octubre | H13: 11 | J13: La Pampa | O13: Prorenta
A14: 37926 | C14: Banco de Inversion Y Comercio Exterior | F14: Noviembre | H14: 12 | J14: La Rioja | O14: Siembra
A15: 37956 | C15: Banco de la Edificadora de Olavarria | F15: Diciembre | H15: 13 | J15: Mendoza | O15: Unidos
A16: 37987 | C16: Banco de La Pampa | H16: 14 | J16: Misiones
A17: 38018 | C17: Banco de la Rep. Oriental del Uruguay | H17: 15 | J17: Neuquen
A18: 38047 | C18: Banco de San Juan | H18: 16 | J18: Río Negro
A19: 38078 | C19: Banco de Santa Cruz | H19: 17 | J19: Salta
A20: 38108 | C20: Banco de Santiago del Estero | H20: 18 | J20: San Juan
A21: 38139 | C21: Banco de Servicios Financieros | H21: 19 | J21: San Luis
A22: 38169 | C22: Banco de Valores | E22: Antigüedad | H22: 20 | J22: Santa Cruz
A23: 38200 | C23: Banco del Chubut | E23: Desde | F23: Hasta | G23: % | H23: 21 | J23: Santa Fe
A24: 38231 | C24: Banco del Sol | E24: 0 | F24: 1 | G24: 0 | H24: 22 | J24: Santiago del Estero
A25: 38261 | C25: Banco del Tucuman | E25: 1 | F25: 3 | G25: 0.01 | H25: 23 | J25: Tierra del Fuego
A26: 38292 | C26: Banco Do Brasil | E26: 3 | F26: 5 | G26: 0.02 | H26: 24 | J26: Tucumán
A27: 38322 | C27: Banco Do Estado de Sao Paulo | E27: 5 | F27: 7 | G27: 0.04 | H27: 25
A28: 38353 | C28: Banco Empresario de Tucuman | E28: 7 | F28: 9 | G28: 0.05 | H28: 26
A29: 38384 | C29: Banco Europeo Para America Latina | E29: 9 | F29: 11 | G29: 0.06 | H29: 27
A30: 38412 | C30: Banco Exterior de America | E30: 11 | F30: 13 | G30: 0.07 | H30: 28
A31: 38443 | C31: Banco Finansur | E31: 13 | F31: 15 | G31: 0.08 | H31: 29
A32: 38473 | C32: Banco General de Negocios | E32: 15 | F32: 17 | G32: 0.1 | H32: 30
A33: 38504 | C33: Banco Julio | E33: 17 | F33: 19 | G33: 0.12
A34: 38534 | C34: Banco Macro | E34: 19 | F34: 99 | G34: 0.14
A35: 38565 | C35: Banco Mariva | E35: 99 | F35: 0 | G35: 0
A36: 38596 | C36: Banco Mercurio | E36: 1000 | F36: 0 | G36: 0
A37: 38626 | C37: Banco Municipal de La Plata | E37: 1000 | F37: 0 | G37: 0
A38: 38657 | C38: Banco Municipal de Rosario | E38: 1000 | F38: 0 | G38: 0
A39: 38687 | C39: Banco Patagonia
A40: 38718 | C40: Banco Piano
A41: 38749 | C41: Banco Privado de Inversiones
A42: 38777 | C42: Banco Provincia de Tierra del Fuego
A43: 38808 | C43: Banco Regional de Cuyo
A44: 38838 | C44: Banco Rio de La Plata
A45: 38869 | C45: Banco Roela
A46: 38899 | C46: Banco Saenz
A47: 38930 | C47: Banco San Luis
A48: 38961 | C48: Banco San Miguel de Tucuman
A49: 38991 | C49: Banco Societe Generale
A50: 39022 | C50: Banco Sudameris Argentina
... A90: 40238 | C90: The Chase Manhattan Bank
A91: 40269
A92: 40299
A93: 40330
A94: 40360
A95: 40391
A96: 40422
A97: 40452
A98: 40483
A99: 40513
A100: 40544
A101: 40575
A102: 40603
... A124: 41275

Sheet Menú
C4: Liquidación de Sueldos Mensuales

Sheet Empleador
B2: Datos del Empleador
C6: Razón social | D6: CARETTA MARIA DEL CARMEN
C7: Cuit | D7: 27202918684
C8: Domicilio Legal | D8: CMTE RODRIGUEZ Nº 147
C9: Localidad | D9: MALARGUE
C10: Provincia | D10: Mendoza
C11: Código postal | D11: 5613
C12: Domicilio de pago | D12: Malargue, Mza

Sheet Empleados
C2: Nómina de Empleados
G5: Sueldo Base
C6: Nro. Legajo | D6: Fecha de Ingreso | E6: Apellido y Nombre | F6: CUIL | G6: Sueldo Básico | H6: Sueldo Básico Exacto | J6: Ad. No Rem. Exacto | K6: Dias trabajados | L6: Otro Exacto | M6: Nro.Caja de Ahorro | N6: Calificación Profesional | O6: Tarea Cumplida | P6: Nombre AFJP
C8: 1 | D8: 40848 | E8: ARANIBAR CLAUDIA CRISTINA | F8: 27-23067512-6 | N8: VENDEDOR | O8: Categ. B | P8: SIPA
C9: 2 | D9: 40910 | E9: QUIROGA VANINA LEONELA | F9: 27-34642729-4 | G9: =471.57+1571.95 -> 2043.52 | N9: VENDEDOR | O9: Categ. B | P9: SIPA
H11: =+G11*(30-Remuneración!AM11-Remuneración!J11-Remuneración!F11)/30 -> 0 | J11: =+I11*(30-Remuneración!AM11-Remuneración!J11-Remuneración!F11)/30 -> 0 | L11: =+K11*(30-Remuneración!AM11-Remuneración!J11-Remuneración!F11)/30 -> 0
H12: =+G12*(30-Remuneración!AM12-Remuneración!J12-Remuneración!F12)/30 -> 0 | J12: =+I12*(30-Remuneración!AM12-Remuneración!J12-Remuneración!F12)/30 -> 0 | L12: =+K12*(30-Remuneración!AM12-Remuneración!J12-Remuneración!F12)/30 -> 0
H13: =+G13*(30-Remuneración!AM13-Remuneración!J13-Remuneración!F13)/30 -> 0 | J13: =+I13*(30-Remuneración!AM13-Remuneración!J13-Remuneración!F13)/30 -> 0 | L13: =+K13*(30-Remuneración!AM13-Remuneración!J13-Remuneración!F13)/30 -> 0
H14: =+G14*(30-Remuneración!AM14-Remuneración!J14-Remuneración!F14)/30 -> 0 | J14: =+I14*(30-Remuneración!AM14-Remuneración!J14-Remuneración!F14)/30 -> 0 | L14: =+K14*(30-Remuneración!AM14-Remuneración!J14-Remuneración!F14)/30 -> 0
H15: =+G15*(30-Remuneración!AM15-Remuneración!J15-Remuneración!F15)/30 -> 0 | J15: =+I15*(30-Remuneración!AM15-Remuneración!J15-Remuneración!F15)/30 -> 0 | L15: =+K15*(30-Remuneración!AM15-Remuneración!J15-Remuneración!F15)/30 -> 0
H16: =+G16*(30-Remuneración!AM16-Remuneración!J16-Remuneración!F16)/30 -> 0 | J16: =+I16*(30-Remuneración!AM16-Remuneración!J16-Remuneración!F16)/30 -> 0 | L16: =+K16*(30-Remuneración!AM16-Remuneración!J16-Remuneración!F16)/30 -> 0
H17: =+G17*(30-Remuneración!AM17-Remuneración!J17-Remuneración!F17)/30 -> 0 | J17: =+I17*(30-Remuneración!AM17-Remuneración!J17-Remuneración!F17)/30 -> 0 | L17: =+K17*(30-Remuneración!AM17-Remuneración!J17-Remuneración!F17)/30 -> 0
H18: =+G18*(30-Remuneración!AM18-Remuneración!J18-Remuneración!F18)/30 -> 0 | J18: =+I18*(30-Remuneración!AM18-Remuneración!J18-Remuneración!F18)/30 -> 0 | L18: =+K18*(30-Remuneración!AM18-Remuneración!J18-Remuneración!F18)/30 -> 0
H19: =+G19*(30-Remuneración!AM19-Remuneración!J19-Remuneración!F19)/30 -> 0 | J19: =+I19*(30-Remuneración!AM19-Remuneración!J19-Remuneración!F19)/30 -> 0 | L19: =+K19*(30-Remuneración!AM19-Remuneración!J19-Remuneración!F19)/30 -> 0
H20: =+G20*(30-Remuneración!AM20-Remuneración!J20-Remuneración!F20)/30 -> 0 | J20: =+I20*(30-Remuneración!AM20-Remuneración!J20-Remuneración!F20)/30 -> 0 | L20: =+K20*(30-Remuneración!AM20-Remuneración!J20-Remuneración!F20)/30 -> 0
H21: =+G21*(30-Remuneración!AM21-Remuneración!J21-Remuneración!F21)/30 -> 0 | J21: =+I21*(30-Remuneración!AM21-Remuneración!J21-Remuneración!F21)/30 -> 0 | L21: =+K21*(30-Remuneración!AM21-Remuneración!J21-Remuneración!F21)/30 -> 0
H22: =+G22*(30-Remuneración!AM22-Remuneración!J22-Remuneración!F22)/30 -> 0 | J22: =+I22*(30-Remuneración!AM22-Remuneración!J22-Remuneración!F22)/30 -> 0 | L22: =+K22*(30-Remuneración!AM22-Remuneración!J22-Remuneración!F22)/30 -> 0
... H56: =+G56*(30-Remuneración!AM56-Remuneración!J56-Remuneración!F56)/30 -> 0 | J56: =+I56*(30-Remuneración!AM56-Remuneración!J56-Remuneración!F56)/30 -> 0 | L56: =+K56*(30-Remuneración!AM56-Remuneración!J56-Remuneración!F56)/30 -> 0
H57: =+G57*(30-Remuneración!AM58-Remuneración!J58-Remuneración!F58)/30 -> 0 | J57: =+I57*(30-Remuneración!AM58-Remuneración!J58-Remuneración!F58)/30 -> 0 | L57: =+K57*(30-Remuneración!AM58-Remuneración!J58-Remuneración!F58)/30 -> 0

Sheet Remuneración
B2: Carga de Datos
B4: Período | C4: 41000
F6: Feriados Trabajados | H6: Ausentismo | J6: Licencia p/enfermedad | L6: Antigüedad | N6: Comp. Serv. Art. 11.6 | P6: Adic. Alimentación | R6: Presentismo | T6: Falla Caja | V6: Adic. Rem. % 5 | X6: Adic. Rem. % 6 | AF6: Horas Extras. 50% | AI6: Horas Extras 100% | AL6: Liquidación
B7: Nro. Legajo | C7: Apellido y Nombre | D7: Sueldo Base | E7: Sueldo Exacto | F7: Cant. Días | G7: Basico Dias Normales | H7: Cant. Días | I7: Ausentismo | J7: Cant. Días | K7: Importe | L7: % | M7: Importe | N7: % | O7: Importe | P7: % | Q7: Importe | R7: % | S7: Importe | U7: Importe | V7: % | W7: Importe | X7: % | Y7: Importe | Z7: Acuerdo Salarial 2008 | AA7: Acuerdo Salarial 2009 | AB7: Acuerdo Salarial 2010 | AC7: Presentismo Acuerdos No Rem. | AD7: Adic. Fijo 5 | AE7: Adic. Fijo 6 | AF7: hs | AG7: $/hora | AH7: Hs Extras 50% | AI7: hs | AJ7: $/hora | AK7: Hs Extras 100% | AL7: SAC 1° SEMES 12 PROP. | AM7: Cant. Días | AN7: Vacaciones 2008 | AO7: días lab | AP7: Sueldo Bruto sin SAC ni VAC
B8: =IF(Empleados!C8="","",Empleados!C8) -> 1 | C8: =IF(Empleados!E8="","",Empleados!E8) -> ARANIBAR CLAUDIA CRISTINA | D8: | | E8: =D8*(30-H8-AM8)/30 -> #VALUE! | G8: =IF(F8="",0,IF(ISERROR(F8*D8/30),0,F8*D8/30)) -> 0 | I8: =IF(H8="",0,IF(ISERROR(H8*$D8/30),0,H8*$D8/30)) -> 0 | K8: =IF(J8="",0,IF(ISERROR(J8*$D8/25),0,J8*$D8/25)) -> 0 | M8: =IF(AND($D8="",L8=""),0,L8*$E8) -> #VALUE! | O8: =IF(AND($D8="",N8=""),0,N8*$E8) -> #VALUE! | Q8: =IF(AND($D8="",P8=""),0,P8*$E8) -> #VALUE! | R8: 0.0833 | S8: =IF(AND($D8="",R8=""),0,R8*$E8) -> #VALUE! | U8: =IF(AND($D8="",T8=""),0,T8*$E8) -> #VALUE! | W8: =IF(AND($D8="",V8=""),0,V8*$E8) -> #VALUE! | Y8: =IF(AND($D8="",X8=""),0,X8*$E8) -> #VALUE! | AH8: =IF(AG8="",0,AF8*AG8) -> 0 | AK8: =IF(AJ8="",0,AI8*AJ8) -> 0 | AO8: =30-AM8-J8-F8-H8 -> 30 | AP8: =E8+M8+O8+Q8+S8+U8+W8+Y8+SUM(Z8:AE8)+AH8+AK8+G8+K8 -> #VALUE!
B9: =IF(Empleados!C9="","",Empleados!C9) -> 2 | C9: =IF(Empleados!E9="","",Empleados!E9) -> QUIROGA VANINA LEONELA | D9: =Empleados!G9+Empleados!I9+Empleados!K9 -> 2043.52 | E9: =D9*(30-H9-AM9)/30 -> 2043.52 | G9: =IF(F9="",0,IF(ISERROR(F9*D9/30),0,F9*D9/30)) -> 0 | I9: =IF(H9="",0,IF(ISERROR(H9*$D9/30),0,H9*$D9/30)) -> 0 | K9: =IF(J9="",0,IF(ISERROR(J9*$D9/30),0,J9*$D9/30)) -> 0 | M9: =IF(AND($D9="",L9=""),0,L9*$E9) -> 0 | O9: =IF(AND($D9="",N9=""),0,N9*$E9) -> 0 | Q9: =IF(AND($D9="",P9=""),0,P9*$E9) -> 0 | R9: 0.0833 | S9: =IF(AND($D9="",R9=""),0,R9*$E9) -> 170.22522 | U9: =IF(AND($D9="",T9=""),0,T9*$E9) -> 0 | W9: =IF(AND($D9="",V9=""),0,V9*$E9) -> 0 | Y9: =IF(AND($D9="",X9=""),0,X9*$E9) -> 0 | AH9: =IF(AG9="",0,AF9*AG9) -> 0 | AK9: =IF(AJ9="",0,AI9*AJ9) -> 0 | AO9: =30-AM9-J9-F9-H9 -> 30 | AP9: =E9+M9+O9+Q9+S9+U9+W9+Y9+SUM(Z9:AE9)+AH9+AK9+G9 -> 2213.7452
B10: =IF(Empleados!C10="","",Empleados!C10) | C10: =IF(Empleados!E10="","",Empleados!E10) | D10: =Empleados!G10+Empleados!I10+Empleados!K10 -> 0 | E10: =D10*(30-H10-AM10)/30 -> 0 | G10: =IF(F10="",0,IF(ISERROR(F10*D10/30),0,F10*D10/30)) -> 0 | I10: =IF(H10="",0,IF(ISERROR(H10*$D10/30),0,H10*$D10/30)) -> 0 | K10: =IF(J10="",0,IF(ISERROR(J10*$D10/30),0,J10*$D10/30)) -> 0 | M10: =IF(AND($D10="",L10=""),0,L10*$E10) -> 0 | O10: =IF(AND($D10="",N10=""),0,N10*$E10) -> 0 | Q10: =IF(AND($D10="",P10=""),0,P10*$E10) -> 0 | S10: =IF(AND($D10="",R10=""),0,R10*$E10) -> 0 | U10: =IF(AND($D10="",T10=""),0,T10*$E10) -> 0 | W10: =IF(AND($D10="",V10=""),0,V10*$E10) -> 0 | Y10: =IF(AND($D10="",X10=""),0,X10*$E10) -> 0 | AH10: =IF(AG10="",0,AF10*AG10) -> 0 | AK10: =IF(AJ10="",0,AI10*AJ10) -> 0 | AO10: =30-AM10-J10-F10-H10 -> 30 | AP10: =E10+M10+O10+Q10+S10+U10+W10+Y10+SUM(Z10:AE10)+AH10+AK10+G10 -> 0
B11: =IF(Empleados!C11="","",Empleados!C11) | C11: =IF(Empleados!E11="","",Empleados!E11) | D11: =Empleados!G11+Empleados!I11+Empleados!K11 -> 0 | E11: =D11*(30-H11-AM11)/30 -> 0 | G11: =IF(F11="",0,IF(ISERROR(F11*D11/30),0,F11*D11/30)) -> 0 | I11: =IF(H11="",0,IF(ISERROR(H11*$D11/30),0,H11*$D11/30)) -> 0 | K11: =IF(J11="",0,IF(ISERROR(J11*$D11/30),0,J11*$D11/30)) -> 0 | M11: =IF(AND($D11="",L11=""),0,L11*$E11) -> 0 | O11: =IF(AND($D11="",N11=""),0,N11*$E11) -> 0 | Q11: =IF(AND($D11="",P11=""),0,P11*$E11) -> 0 | S11: =IF(AND($D11="",R11=""),0,R11*$E11) -> 0 | U11: =IF(AND($D11="",T11=""),0,T11*$E11) -> 0 | W11: =IF(AND($D11="",V11=""),0,V11*$E11) -> 0 | Y11: =IF(AND($D11="",X11=""),0,X11*$E11) -> 0 | AH11: =IF(AG11="",0,AF11*AG11) -> 0 | AK11: =IF(AJ11="",0,AI11*AJ11) -> 0 | AO11: =30-AM11-J11-F11-H11 -> 30 | AP11: =E11+M11+O11+Q11+S11+U11+W11+Y11+SUM(Z11:AE11)+AH11+AK11+G11 -> 0
B12: =IF(Empleados!C12="","",Empleados!C12) | C12: =IF(Empleados!E12="","",Empleados!E12) | D12: =Empleados!G12+Empleados!I12+Empleados!K12 -> 0 | E12: =D12*(30-H12-AM12)/30 -> 0 | G12: =IF(F12="",0,IF(ISERROR(F12*D12/30),0,F12*D12/30)) -> 0 | I12: =IF(H12="",0,IF(ISERROR(H12*$D12/30),0,H12*$D12/30)) -> 0 | K12: =IF(J12="",0,IF(ISERROR(J12*$D12/30),0,J12*$D12/30)) -> 0 | M12: =IF(AND($D12="",L12=""),0,L12*$E12) -> 0 | O12: =IF(AND($D12="",N12=""),0,N12*$E12) -> 0 | Q12: =IF(AND($D12="",P12=""),0,P12*$E12) -> 0 | S12: =IF(AND($D12="",R12=""),0,R12*$E12) -> 0 | U12: =IF(AND($D12="",T12=""),0,T12*$E12) -> 0 | W12: =IF(AND($D12="",V12=""),0,V12*$E12) -> 0 | Y12: =IF(AND($D12="",X12=""),0,X12*$E12) -> 0 | AH12: =IF(AG12="",0,AF12*AG12) -> 0 | AK12: =IF(AJ12="",0,AI12*AJ12) -> 0 | AO12: =30-AM12-J12-F12-H12 -> 30 | AP12: =E12+M12+O12+Q12+S12+U12+W12+Y12+SUM(Z12:AE12)+AH12+AK12+G12 -> 0
B13: =IF(Empleados!C13="","",Empleados!C13) | C13: =IF(Empleados!E13="","",Empleados!E13) | D13: =Empleados!G13+Empleados!I13+Empleados!K13 -> 0 | E13: =D13*(30-H13-AM13)/30 -> 0 | G13: =IF(F13="",0,IF(ISERROR(F13*D13/30),0,F13*D13/30)) -> 0 | I13: =IF(H13="",0,IF(ISERROR(H13*$D13/30),0,H13*$D13/30)) -> 0 | K13: =IF(J13="",0,IF(ISERROR(J13*$D13/30),0,J13*$D13/30)) -> 0 | M13: =IF(AND($D13="",L13=""),0,L13*$E13) -> 0 | O13: =IF(AND($D13="",N13=""),0,N13*$E13) -> 0 | Q13: =IF(AND($D13="",P13=""),0,P13*$E13) -> 0 | S13: =IF(AND($D13="",R13=""),0,R13*$E13) -> 0 | U13: =IF(AND($D13="",T13=""),0,T13*$E13) -> 0 | W13: =IF(AND($D13="",V13=""),0,V13*$E13) -> 0 | Y13: =IF(AND($D13="",X13=""),0,X13*$E13) -> 0 | AH13: =IF(AG13="",0,AF13*AG13) -> 0 | AK13: =IF(AJ13="",0,AI13*AJ13) -> 0 | AO13: =30-AM13-J13-F13-H13 -> 30 | AP13: =E13+M13+O13+Q13+S13+U13+W13+Y13+SUM(Z13:AE13)+AH13+AK13+G13 -> 0
B14: =IF(Empleados!C14="","",Empleados!C14) | C14: =IF(Empleados!E14="","",Empleados!E14) | D14: =Empleados!G14+Empleados!I14+Empleados!K14 -> 0 | E14: =D14*(30-H14-AM14)/30 -> 0 | G14: =IF(F14="",0,IF(ISERROR(F14*D14/30),0,F14*D14/30)) -> 0 | I14: =IF(H14="",0,IF(ISERROR(H14*$D14/30),0,H14*$D14/30)) -> 0 | K14: =IF(J14="",0,IF(ISERROR(J14*$D14/30),0,J14*$D14/30)) -> 0 | M14: =IF(AND($D14="",L14=""),0,L14*$E14) -> 0 | O14: =IF(AND($D14="",N14=""),0,N14*$E14) -> 0 | Q14: =IF(AND($D14="",P14=""),0,P14*$E14) -> 0 | S14: =IF(AND($D14="",R14=""),0,R14*$E14) -> 0 | U14: =IF(AND($D14="",T14=""),0,T14*$E14) -> 0 | W14: =IF(AND($D14="",V14=""),0,V14*$E14) -> 0 | Y14: =IF(AND($D14="",X14=""),0,X14*$E14) -> 0 | AH14: =IF(AG14="",0,AF14*AG14) -> 0 | AK14: =IF(AJ14="",0,AI14*AJ14) -> 0 | AO14: =30-AM14-J14-F14-H14 -> 30 | AP14: =E14+M14+O14+Q14+S14+U14+W14+Y14+SUM(Z14:AE14)+AH14+AK14+G14 -> 0
B15: =IF(Empleados!C15="","",Empleados!C15) | C15: =IF(Empleados!E15="","",Empleados!E15) | D15: =Empleados!G15+Empleados!I15+Empleados!K15 -> 0 | E15: =D15*(30-H15-AM15)/30 -> 0 | G15: =IF(F15="",0,IF(ISERROR(F15*D15/30),0,F15*D15/30)) -> 0 | I15: =IF(H15="",0,IF(ISERROR(H15*$D15/30),0,H15*$D15/30)) -> 0 | K15: =IF(J15="",0,IF(ISERROR(J15*$D15/30),0,J15*$D15/30)) -> 0 | M15: =IF(AND($D15="",L15=""),0,L15*$E15) -> 0 | O15: =IF(AND($D15="",N15=""),0,N15*$E15) -> 0 | Q15: =IF(AND($D15="",P15=""),0,P15*$E15) -> 0 | S15: =IF(AND($D15="",R15=""),0,R15*$E15) -> 0 | U15: =IF(AND($D15="",T15=""),0,T15*$E15) -> 0 | W15: =IF(AND($D15="",V15=""),0,V15*$E15) -> 0 | Y15: =IF(AND($D15="",X15=""),0,X15*$E15) -> 0 | AH15: =IF(AG15="",0,AF15*AG15) -> 0 | AK15: =IF(AJ15="",0,AI15*AJ15) -> 0 | AO15: =30-AM15-J15-F15-H15 -> 30 | AP15: =E15+M15+O15+Q15+S15+U15+W15+Y15+SUM(Z15:AE15)+AH15+AK15+G15 -> 0
B16: =IF(Empleados!C16="","",Empleados!C16) | C16: =IF(Empleados!E16="","",Empleados!E16) | D16: =((Empleados!G16+Empleados!I16+Empleados!K16)/30)*30 -> 0 | E16: =D16*(30-H16-AM16)/30 -> 0 | G16: =IF(F16="",0,IF(ISERROR(F16*D16/30),0,F16*D16/30)) -> 0 | I16: =IF(H16="",0,IF(ISERROR(H16*$D16/30),0,H16*$D16/30)) -> 0 | K16: =IF(J16="",0,IF(ISERROR(J16*$D16/30),0,J16*$D16/30)) -> 0 | M16: =IF(AND($D16="",L16=""),0,L16*$E16) -> 0 | O16: =IF(AND($D16="",N16=""),0,N16*$E16) -> 0 | Q16: =IF(AND($D16="",P16=""),0,P16*$E16) -> 0 | S16: =IF(AND($D16="",R16=""),0,R16*$E16) -> 0 | U16: =IF(AND($D16="",T16=""),0,T16*$E16) -> 0 | W16: =IF(AND($D16="",V16=""),0,V16*$E16) -> 0 | Y16: =IF(AND($D16="",X16=""),0,X16*$E16) -> 0 | AH16: =IF(AG16="",0,AF16*AG16) -> 0 | AK16: =IF(AJ16="",0,AI16*AJ16) -> 0 | AO16: =30-AM16-J16-F16-H16 -> 30 | AP16: =E16+M16+O16+Q16+S16+U16+W16+Y16+SUM(Z16:AE16)+AH16+AK16+G16 -> 0
B17: =IF(Empleados!C17="","",Empleados!C17) | C17: =IF(Empleados!E17="","",Empleados!E17) | D17: =Empleados!G17+Empleados!I17+Empleados!K17 -> 0 | E17: =D17*(30-H17-AM17)/30 -> 0 | G17: =IF(F17="",0,IF(ISERROR(F17*D17/30),0,F17*D17/30)) -> 0 | I17: =IF(H17="",0,IF(ISERROR(H17*$D17/30),0,H17*$D17/30)) -> 0 | K17: =IF(J17="",0,IF(ISERROR(J17*$D17/30),0,J17*$D17/30)) -> 0 | M17: =IF(AND($D17="",L17=""),0,L17*$E17) -> 0 | O17: =IF(AND($D17="",N17=""),0,N17*$E17) -> 0 | Q17: =IF(AND($D17="",P17=""),0,P17*$E17) -> 0 | S17: =IF(AND($D17="",R17=""),0,R17*$E17) -> 0 | U17: =IF(AND($D17="",T17=""),0,T17*$E17) -> 0 | W17: =IF(AND($D17="",V17=""),0,V17*$E17) -> 0 | Y17: =IF(AND($D17="",X17=""),0,X17*$E17) -> 0 | AH17: =IF(AG17="",0,AF17*AG17) -> 0 | AK17: =IF(AJ17="",0,AI17*AJ17) -> 0 | AO17: =30-AM17-J17-F17-H17 -> 30 | AP17: =E17+M17+O17+Q17+S17+U17+W17+Y17+SUM(Z17:AE17)+AH17+AK17+G17 -> 0
B18: =IF(Empleados!C18="","",Empleados!C18) | C18: =IF(Empleados!E18="","",Empleados!E18) | D18: =Empleados!G18+Empleados!I18+Empleados!K18 -> 0 | E18: =D18*(30-H18-AM18)/30 -> 0 | G18: =IF(F18="",0,IF(ISERROR(F18*D18/30),0,F18*D18/30)) -> 0 | I18: =IF(H18="",0,IF(ISERROR(H18*$D18/30),0,H18*$D18/30)) -> 0 | K18: =IF(J18="",0,IF(ISERROR(J18*$D18/30),0,J18*$D18/30)) -> 0 | M18: =IF(AND($D18="",L18=""),0,L18*$E18) -> 0 | O18: =IF(AND($D18="",N18=""),0,N18*$E18) -> 0 | Q18: =IF(AND($D18="",P18=""),0,P18*$E18) -> 0 | S18: =IF(AND($D18="",R18=""),0,R18*$E18) -> 0 | U18: =IF(AND($D18="",T18=""),0,T18*$E18) -> 0 | W18: =IF(AND($D18="",V18=""),0,V18*$E18) -> 0 | Y18: =IF(AND($D18="",X18=""),0,X18*$E18) -> 0 | AH18: =IF(AG18="",0,AF18*AG18) -> 0 | AK18: =IF(AJ18="",0,AI18*AJ18) -> 0 | AO18: =30-AM18-J18-F18-H18 -> 30 | AP18: =E18+M18+O18+Q18+S18+U18+W18+Y18+SUM(Z18:AE18)+AH18+AK18+G18 -> 0
B19: =IF(Empleados!C19="","",Empleados!C19) | C19: =IF(Empleados!E19="","",Empleados!E19) | D19: =Empleados!G19+Empleados!I19+Empleados!K19 -> 0 | E19: =D19*(30-H19-AM19)/30 -> 0 | G19: =IF(F19="",0,IF(ISERROR(F19*D19/30),0,F19*D19/30)) -> 0 | I19: =IF(H19="",0,IF(ISERROR(H19*$D19/30),0,H19*$D19/30)) -> 0 | K19: =IF(J19="",0,IF(ISERROR(J19*$D19/30),0,J19*$D19/30)) -> 0 | M19: =IF(AND($D19="",L19=""),0,L19*$E19) -> 0 | O19: =IF(AND($D19="",N19=""),0,N19*$E19) -> 0 | Q19: =IF(AND($D19="",P19=""),0,P19*$E19) -> 0 | S19: =IF(AND($D19="",R19=""),0,R19*$E19) -> 0 | U19: =IF(AND($D19="",T19=""),0,T19*$E19) -> 0 | W19: =IF(AND($D19="",V19=""),0,V19*$E19) -> 0 | Y19: =IF(AND($D19="",X19=""),0,X19*$E19) -> 0 | AH19: =IF(AG19="",0,AF19*AG19) -> 0 | AK19: =IF(AJ19="",0,AI19*AJ19) -> 0 | AO19: =30-AM19-J19-F19-H19 -> 30 | AP19: =E19+M19+O19+Q19+S19+U19+W19+Y19+SUM(Z19:AE19)+AH19+AK19+G19 -> 0
B20: =IF(Empleados!C20="","",Empleados!C20) | C20: =IF(Empleados!E20="","",Empleados!E20) | D20: =Empleados!G20+Empleados!I20+Empleados!K20 -> 0 | E20: =D20*(30-H20-AM20)/30 -> 0 | G20: =IF(F20="",0,IF(ISERROR(F20*D20/30),0,F20*D20/30)) -> 0 | I20: =IF(H20="",0,IF(ISERROR(H20*$D20/30),0,H20*$D20/30)) -> 0 | K20: =IF(J20="",0,IF(ISERROR(J20*$D20/30),0,J20*$D20/30)) -> 0 | M20: =IF(AND($D20="",L20=""),0,L20*$E20) -> 0 | O20: =IF(AND($D20="",N20=""),0,N20*$E20) -> 0 | Q20: =IF(AND($D20="",P20=""),0,P20*$E20) -> 0 | S20: =IF(AND($D20="",R20=""),0,R20*$E20) -> 0 | U20: =IF(AND($D20="",T20=""),0,T20*$E20) -> 0 | W20: =IF(AND($D20="",V20=""),0,V20*$E20) -> 0 | Y20: =IF(AND($D20="",X20=""),0,X20*$E20) -> 0 | AH20: =IF(AG20="",0,AF20*AG20) -> 0 | AK20: =IF(AJ20="",0,AI20*AJ20) -> 0 | AO20: =30-AM20-J20-F20-H20 -> 30 | AP20: =E20+M20+O20+Q20+S20+U20+W20+Y20+SUM(Z20:AE20)+AH20+AK20+G20 -> 0
B21: =IF(Empleados!C21="","",Empleados!C21) | C21: =IF(Empleados!E21="","",Empleados!E21) | D21: =Empleados!G21+Empleados!I21+Empleados!K21 -> 0 | E21: =D21*(30-H21-AM21)/30 -> 0 | G21: =IF(F21="",0,IF(ISERROR(F21*D21/30),0,F21*D21/30)) -> 0 | I21: =IF(H21="",0,IF(ISERROR(H21*$D21/30),0,H21*$D21/30)) -> 0 | K21: =IF(J21="",0,IF(ISERROR(J21*$D21/30),0,J21*$D21/30)) -> 0 | M21: =IF(AND($D21="",L21=""),0,L21*$E21) -> 0 | O21: =IF(AND($D21="",N21=""),0,N21*$E21) -> 0 | Q21: =IF(AND($D21="",P21=""),0,P21*$E21) -> 0 | S21: =IF(AND($D21="",R21=""),0,R21*$E21) -> 0 | U21: =IF(AND($D21="",T21=""),0,T21*$E21) -> 0 | W21: =IF(AND($D21="",V21=""),0,V21*$E21) -> 0 | Y21: =IF(AND($D21="",X21=""),0,X21*$E21) -> 0 | AH21: =IF(AG21="",0,AF21*AG21) -> 0 | AK21: =IF(AJ21="",0,AI21*AJ21) -> 0 | AO21: =30-AM21-J21-F21-H21 -> 30 | AP21: =E21+M21+O21+Q21+S21+U21+W21+Y21+SUM(Z21:AE21)+AH21+AK21+G21 -> 0
B22: =IF(Empleados!C22="","",Empleados!C22) | C22: =IF(Empleados!E22="","",Empleados!E22) | D22: =((Empleados!G22+Empleados!I22+Empleados!K22)) -> 0 | E22: =D22*(30-H22-AM22)/30 -> 0 | G22: =IF(F22="",0,IF(ISERROR(F22*D22/30),0,F22*D22/30)) -> 0 | I22: =IF(H22="",0,IF(ISERROR(H22*$D22/30),0,H22*$D22/30)) -> 0 | K22: =IF(J22="",0,IF(ISERROR(J22*$D22/30),0,J22*$D22/30)) -> 0 | M22: =IF(AND($D22="",L22=""),0,L22*$E22) -> 0 | O22: =IF(AND($D22="",N22=""),0,N22*$E22) -> 0 | Q22: =IF(AND($D22="",P22=""),0,P22*$E22) -> 0 | S22: =IF(AND($D22="",R22=""),0,R22*$E22) -> 0 | U22: =IF(AND($D22="",T22=""),0,T22*$E22) -> 0 | W22: =IF(AND($D22="",V22=""),0,V22*$E22) -> 0 | Y22: =IF(AND($D22="",X22=""),0,X22*$E22) -> 0 | AH22: =IF(AG22="",0,AF22*AG22) -> 0 | AK22: =IF(AJ22="",0,AI22*AJ22) -> 0 | AO22: =30-AM22-J22-F22-H22 -> 30 | AP22: =E22+M22+O22+Q22+S22+U22+W22+Y22+SUM(Z22:AE22)+AH22+AK22+G22 -> 0
B23: =IF(Empleados!C23="","",Empleados!C23) | C23: =IF(Empleados!E23="","",Empleados!E23) | D23: =Empleados!G23+Empleados!I23+Empleados!K23 -> 0 | E23: =D23*(30-H23-AM23)/30 -> 0 | G23: =IF(F23="",0,IF(ISERROR(F23*D23/30),0,F23*D23/30)) -> 0 | I23: =IF(H23="",0,IF(ISERROR(H23*$D23/30),0,H23*$D23/30)) -> 0 | K23: =IF(J23="",0,IF(ISERROR(J23*$D23/30),0,J23*$D23/30)) -> 0 | M23: =IF(AND($D23="",L23=""),0,L23*$E23) -> 0 | O23: =IF(AND($D23="",N23=""),0,N23*$E23) -> 0 | Q23: =IF(AND($D23="",P23=""),0,P23*$E23) -> 0 | S23: =IF(AND($D23="",R23=""),0,R23*$E23) -> 0 | U23: =IF(AND($D23="",T23=""),0,T23*$E23) -> 0 | W23: =IF(AND($D23="",V23=""),0,V23*$E23) -> 0 | Y23: =IF(AND($D23="",X23=""),0,X23*$E23) -> 0 | AH23: =IF(AG23="",0,AF23*AG23) -> 0 | AK23: =IF(AJ23="",0,AI23*AJ23) -> 0 | AO23: =30-AM23-J23-F23-H23 -> 30 | AP23: =E23+M23+O23+Q23+S23+U23+W23+Y23+SUM(Z23:AE23)+AH23+AK23+G23 -> 0
B24: =IF(Empleados!C24="","",Empleados!C24) | C24: =IF(Empleados!E24="","",Empleados!E24) | D24: =Empleados!G24+Empleados!I24+Empleados!K24 -> 0 | E24: =D24*(30-H24-AM24)/30 -> 0 | G24: =IF(F24="",0,IF(ISERROR(F24*D24/30),0,F24*D24/30)) -> 0 | I24: =IF(H24="",0,IF(ISERROR(H24*$D24/30),0,H24*$D24/30)) -> 0 | K24: =IF(J24="",0,IF(ISERROR(J24*$D24/30),0,J24*$D24/30)) -> 0 | M24: =IF(AND($D24="",L24=""),0,L24*$E24) -> 0 | O24: =IF(AND($D24="",N24=""),0,N24*$E24) -> 0 | Q24: =IF(AND($D24="",P24=""),0,P24*$E24) -> 0 | S24: =IF(AND($D24="",R24=""),0,R24*$E24) -> 0 | U24: =IF(AND($D24="",T24=""),0,T24*$E24) -> 0 | W24: =IF(AND($D24="",V24=""),0,V24*$E24) -> 0 | Y24: =IF(AND($D24="",X24=""),0,X24*$E24) -> 0 | AH24: =IF(AG24="",0,AF24*AG24) -> 0 | AK24: =IF(AJ24="",0,AI24*AJ24) -> 0 | AO24: =30-AM24-J24-F24-H24 -> 30 | AP24: =E24+M24+O24+Q24+S24+U24+W24+Y24+SUM(Z24:AE24)+AH24+AK24+G24 -> 0
B25: =IF(Empleados!C25="","",Empleados!C25) | C25: =IF(Empleados!E25="","",Empleados!E25) | D25: =Empleados!G25+Empleados!I25+Empleados!K25 -> 0 | E25: =D25*(30-H25-AM25)/30 -> 0 | G25: =IF(F25="",0,IF(ISERROR(F25*D25/30),0,F25*D25/30)) -> 0 | I25: =IF(H25="",0,IF(ISERROR(H25*$D25/30),0,H25*$D25/30)) -> 0 | K25: =IF(J25="",0,IF(ISERROR(J25*$D25/30),0,J25*$D25/30)) -> 0 | M25: =IF(AND($D25="",L25=""),0,L25*$E25) -> 0 | O25: =IF(AND($D25="",N25=""),0,N25*$E25) -> 0 | Q25: =IF(AND($D25="",P25=""),0,P25*$E25) -> 0 | S25: =IF(AND($D25="",R25=""),0,R25*$E25) -> 0 | U25: =IF(AND($D25="",T25=""),0,T25*$E25) -> 0 | W25: =IF(AND($D25="",V25=""),0,V25*$E25) -> 0 | Y25: =IF(AND($D25="",X25=""),0,X25*$E25) -> 0 | AH25: =IF(AG25="",0,AF25*AG25) -> 0 | AK25: =IF(AJ25="",0,AI25*AJ25) -> 0 | AO25: =30-AM25-J25-F25-H25 -> 30 | AP25: =E25+M25+O25+Q25+S25+U25+W25+Y25+SUM(Z25:AE25)+AH25+AK25 -> 0
B26: =IF(Empleados!C26="","",Empleados!C26) | C26: =IF(Empleados!E26="","",Empleados!E26) | D26: =Empleados!G26+Empleados!I26+Empleados!K26 -> 0 | E26: =D26*(30-H26-AM26)/30 -> 0 | G26: =IF(F26="",0,IF(ISERROR(F26*D26/30),0,F26*D26/30)) -> 0 | I26: =IF(H26="",0,IF(ISERROR(H26*$D26/30),0,H26*$D26/30)) -> 0 | K26: =IF(J26="",0,IF(ISERROR(J26*$D26/30),0,J26*$D26/30)) -> 0 | M26: =IF(AND($D26="",L26=""),0,L26*$E26) -> 0 | O26: =IF(AND($D26="",N26=""),0,N26*$E26) -> 0 | Q26: =IF(AND($D26="",P26=""),0,P26*$E26) -> 0 | S26: =IF(AND($D26="",R26=""),0,R26*$E26) -> 0 | U26: =IF(AND($D26="",T26=""),0,T26*$E26) -> 0 | W26: =IF(AND($D26="",V26=""),0,V26*$E26) -> 0 | Y26: =IF(AND($D26="",X26=""),0,X26*$E26) -> 0 | AH26: =IF(AG26="",0,AF26*AG26) -> 0 | AK26: =IF(AJ26="",0,AI26*AJ26) -> 0 | AO26: =30-AM26-J26-F26-H26 -> 30 | AP26: =E26+M26+O26+Q26+S26+U26+W26+Y26+SUM(Z26:AE26)+AH26+AK26 -> 0
B27: =IF(Empleados!C27="","",Empleados!C27) | C27: =IF(Empleados!E27="","",Empleados!E27) | D27: =Empleados!G27+Empleados!I27+Empleados!K27 -> 0 | E27: =D27*(30-H27-AM27)/30 -> 0 | G27: =IF(F27="",0,IF(ISERROR(F27*D27/30),0,F27*D27/30)) -> 0 | I27: =IF(H27="",0,IF(ISERROR(H27*$D27/30),0,H27*$D27/30)) -> 0 | K27: =IF(J27="",0,IF(ISERROR(J27*$D27/30),0,J27*$D27/30)) -> 0 | M27: =IF(AND($D27="",L27=""),0,L27*$E27) -> 0 | O27: =IF(AND($D27="",N27=""),0,N27*$E27) -> 0 | Q27: =IF(AND($D27="",P27=""),0,P27*$E27) -> 0 | S27: =IF(AND($D27="",R27=""),0,R27*$E27) -> 0 | U27: =IF(AND($D27="",T27=""),0,T27*$E27) -> 0 | W27: =IF(AND($D27="",V27=""),0,V27*$E27) -> 0 | Y27: =IF(AND($D27="",X27=""),0,X27*$E27) -> 0 | AH27: =IF(AG27="",0,AF27*AG27) -> 0 | AK27: =IF(AJ27="",0,AI27*AJ27) -> 0 | AO27: =30-AM27-J27-F27-H27 -> 30 | AP27: =E27+M27+O27+Q27+S27+U27+W27+Y27+SUM(Z27:AE27)+AH27+AK27 -> 0
B28: =IF(Empleados!C28="","",Empleados!C28) | C28: =IF(Empleados!E28="","",Empleados!E28) | D28: =Empleados!G28+Empleados!I28+Empleados!K28 -> 0 | E28: =D28*(30-H28-AM28)/30 -> 0 | G28: =IF(F28="",0,IF(ISERROR(F28*D28/30),0,F28*D28/30)) -> 0 | I28: =IF(H28="",0,IF(ISERROR(H28*$D28/30),0,H28*$D28/30)) -> 0 | K28: =IF(J28="",0,IF(ISERROR(J28*$D28/30),0,J28*$D28/30)) -> 0 | M28: =IF(AND($D28="",L28=""),0,L28*$E28) -> 0 | O28: =IF(AND($D28="",N28=""),0,N28*$E28) -> 0 | Q28: =IF(AND($D28="",P28=""),0,P28*$E28) -> 0 | S28: =IF(AND($D28="",R28=""),0,R28*$E28) -> 0 | U28: =IF(AND($D28="",T28=""),0,T28*$E28) -> 0 | W28: =IF(AND($D28="",V28=""),0,V28*$E28) -> 0 | Y28: =IF(AND($D28="",X28=""),0,X28*$E28) -> 0 | AH28: =IF(AG28="",0,AF28*AG28) -> 0 | AK28: =IF(AJ28="",0,AI28*AJ28) -> 0 | AO28: =30-AM28-J28-F28-H28 -> 30 | AP28: =E28+M28+O28+Q28+S28+U28+W28+Y28+SUM(Z28:AE28)+AH28+AK28 -> 0
B29: =IF(Empleados!C29="","",Empleados!C29) | C29: =IF(Empleados!E29="","",Empleados!E29) | D29: =Empleados!G29+Empleados!I29+Empleados!K29 -> 0 | E29: =D29*(30-H29-AM29)/30 -> 0 | G29: =IF(F29="",0,IF(ISERROR(F29*D29/30),0,F29*D29/30)) -> 0 | I29: =IF(H29="",0,IF(ISERROR(H29*$D29/30),0,H29*$D29/30)) -> 0 | K29: =IF(J29="",0,IF(ISERROR(J29*$D29/30),0,J29*$D29/30)) -> 0 | M29: =IF(AND($D29="",L29=""),0,L29*$E29) -> 0 | O29: =IF(AND($D29="",N29=""),0,N29*$E29) -> 0 | Q29: =IF(AND($D29="",P29=""),0,P29*$E29) -> 0 | S29: =IF(AND($D29="",R29=""),0,R29*$E29) -> 0 | U29: =IF(AND($D29="",T29=""),0,T29*$E29) -> 0 | W29: =IF(AND($D29="",V29=""),0,V29*$E29) -> 0 | Y29: =IF(AND($D29="",X29=""),0,X29*$E29) -> 0 | AH29: =IF(AG29="",0,AF29*AG29) -> 0 | AK29: =IF(AJ29="",0,AI29*AJ29) -> 0 | AO29: =30-AM29-J29-F29-H29 -> 30 | AP29: =E29+M29+O29+Q29+S29+U29+W29+Y29+SUM(Z29:AE29)+AH29+AK29 -> 0
B30: =IF(Empleados!C30="","",Empleados!C30) | C30: =IF(Empleados!E30="","",Empleados!E30) | D30: =Empleados!G30+Empleados!I30+Empleados!K30 -> 0 | E30: =D30*(30-H30-AM30)/30 -> 0 | G30: =IF(F30="",0,IF(ISERROR(F30*D30/30),0,F30*D30/30)) -> 0 | I30: =IF(H30="",0,IF(ISERROR(H30*$D30/30),0,H30*$D30/30)) -> 0 | K30: =IF(J30="",0,IF(ISERROR(J30*$D30/30),0,J30*$D30/30)) -> 0 | M30: =IF(AND($D30="",L30=""),0,L30*$E30) -> 0 | O30: =IF(AND($D30="",N30=""),0,N30*$E30) -> 0 | Q30: =IF(AND($D30="",P30=""),0,P30*$E30) -> 0 | S30: =IF(AND($D30="",R30=""),0,R30*$E30) -> 0 | U30: =IF(AND($D30="",T30=""),0,T30*$E30) -> 0 | W30: =IF(AND($D30="",V30=""),0,V30*$E30) -> 0 | Y30: =IF(AND($D30="",X30=""),0,X30*$E30) -> 0 | AH30: =IF(AG30="",0,AF30*AG30) -> 0 | AK30: =IF(AJ30="",0,AI30*AJ30) -> 0 | AO30: =30-AM30-J30-F30-H30 -> 30 | AP30: =E30+M30+O30+Q30+S30+U30+W30+Y30+SUM(Z30:AE30)+AH30+AK30 -> 0
B31: =IF(Empleados!C31="","",Empleados!C31) | C31: =IF(Empleados!E31="","",Empleados!E31) | D31: =Empleados!G31+Empleados!I31+Empleados!K31 -> 0 | E31: =D31*(30-H31-AM31)/30 -> 0 | G31: =IF(F31="",0,IF(ISERROR(F31*D31/30),0,F31*D31/30)) -> 0 | I31: =IF(H31="",0,IF(ISERROR(H31*$D31/30),0,H31*$D31/30)) -> 0 | K31: =IF(J31="",0,IF(ISERROR(J31*$D31/30),0,J31*$D31/30)) -> 0 | M31: =IF(AND($D31="",L31=""),0,L31*$E31) -> 0 | O31: =IF(AND($D31="",N31=""),0,N31*$E31) -> 0 | Q31: =IF(AND($D31="",P31=""),0,P31*$E31) -> 0 | S31: =IF(AND($D31="",R31=""),0,R31*$E31) -> 0 | U31: =IF(AND($D31="",T31=""),0,T31*$E31) -> 0 | W31: =IF(AND($D31="",V31=""),0,V31*$E31) -> 0 | Y31: =IF(AND($D31="",X31=""),0,X31*$E31) -> 0 | AH31: =IF(AG31="",0,AF31*AG31) -> 0 | AK31: =IF(AJ31="",0,AI31*AJ31) -> 0 | AO31: =30-AM31-J31-F31-H31 -> 30 | AP31: =E31+M31+O31+Q31+S31+U31+W31+Y31+SUM(Z31:AE31)+AH31+AK31 -> 0
B32: =IF(Empleados!C32="","",Empleados!C32) | C32: =IF(Empleados!E32="","",Empleados!E32) | D32: =Empleados!G32+Empleados!I32+Empleados!K32 -> 0 | E32: =D32*(30-H32-AM32)/30 -> 0 | G32: =IF(F32="",0,IF(ISERROR(F32*D32/30),0,F32*D32/30)) -> 0 | I32: =IF(H32="",0,IF(ISERROR(H32*$D32/30),0,H32*$D32/30)) -> 0 | K32: =IF(J32="",0,IF(ISERROR(J32*$D32/30),0,J32*$D32/30)) -> 0 | M32: =IF(AND($D32="",L32=""),0,L32*$E32) -> 0 | O32: =IF(AND($D32="",N32=""),0,N32*$E32) -> 0 | Q32: =IF(AND($D32="",P32=""),0,P32*$E32) -> 0 | S32: =IF(AND($D32="",R32=""),0,R32*$E32) -> 0 | U32: =IF(AND($D32="",T32=""),0,T32*$E32) -> 0 | W32: =IF(AND($D32="",V32=""),0,V32*$E32) -> 0 | Y32: =IF(AND($D32="",X32=""),0,X32*$E32) -> 0 | AH32: =IF(AG32="",0,AF32*AG32) -> 0 | AK32: =IF(AJ32="",0,AI32*AJ32) -> 0 | AO32: =30-AM32-J32-F32-H32 -> 30 | AP32: =E32+M32+O32+Q32+S32+U32+W32+Y32+SUM(Z32:AE32)+AH32+AK32 -> 0
B33: =IF(Empleados!C33="","",Empleados!C33) | C33: =IF(Empleados!E33="","",Empleados!E33) | D33: =Empleados!G33+Empleados!I33+Empleados!K33 -> 0 | E33: =D33*(30-H33-AM33)/30 -> 0 | G33: =IF(F33="",0,IF(ISERROR(F33*D33/30),0,F33*D33/30)) -> 0 | I33: =IF(H33="",0,IF(ISERROR(H33*$D33/30),0,H33*$D33/30)) -> 0 | K33: =IF(J33="",0,IF(ISERROR(J33*$D33/30),0,J33*$D33/30)) -> 0 | M33: =IF(AND($D33="",L33=""),0,L33*$E33) -> 0 | O33: =IF(AND($D33="",N33=""),0,N33*$E33) -> 0 | Q33: =IF(AND($D33="",P33=""),0,P33*$E33) -> 0 | S33: =IF(AND($D33="",R33=""),0,R33*$E33) -> 0 | U33: =IF(AND($D33="",T33=""),0,T33*$E33) -> 0 | W33: =IF(AND($D33="",V33=""),0,V33*$E33) -> 0 | Y33: =IF(AND($D33="",X33=""),0,X33*$E33) -> 0 | AH33: =IF(AG33="",0,AF33*AG33) -> 0 | AK33: =IF(AJ33="",0,AI33*AJ33) -> 0 | AO33: =30-AM33-J33-F33-H33 -> 30 | AP33: =E33+M33+O33+Q33+S33+U33+W33+Y33+SUM(Z33:AE33)+AH33+AK33 -> 0
B34: =IF(Empleados!C34="","",Empleados!C34) | C34: =IF(Empleados!E34="","",Empleados!E34) | D34: =Empleados!G34+Empleados!I34+Empleados!K34 -> 0 | E34: =D34*(30-H34-AM34)/30 -> 0 | G34: =IF(F34="",0,IF(ISERROR(F34*D34/30),0,F34*D34/30)) -> 0 | I34: =IF(H34="",0,IF(ISERROR(H34*$D34/30),0,H34*$D34/30)) -> 0 | K34: =IF(J34="",0,IF(ISERROR(J34*$D34/30),0,J34*$D34/30)) -> 0 | M34: =IF(AND($D34="",L34=""),0,L34*$E34) -> 0 | O34: =IF(AND($D34="",N34=""),0,N34*$E34) -> 0 | Q34: =IF(AND($D34="",P34=""),0,P34*$E34) -> 0 | S34: =IF(AND($D34="",R34=""),0,R34*$E34) -> 0 | U34: =IF(AND($D34="",T34=""),0,T34*$E34) -> 0 | W34: =IF(AND($D34="",V34=""),0,V34*$E34) -> 0 | Y34: =IF(AND($D34="",X34=""),0,X34*$E34) -> 0 | AH34: =IF(AG34="",0,AF34*AG34) -> 0 | AK34: =IF(AJ34="",0,AI34*AJ34) -> 0 | AO34: =30-AM34-J34-F34-H34 -> 30 | AP34: =E34+M34+O34+Q34+S34+U34+W34+Y34+SUM(Z34:AE34)+AH34+AK34 -> 0
B35: =IF(Empleados!C35="","",Empleados!C35) | C35: =IF(Empleados!E35="","",Empleados!E35) | D35: =Empleados!G35+Empleados!I35+Empleados!K35 -> 0 | E35: =D35*(30-H35-AM35)/30 -> 0 | G35: =IF(F35="",0,IF(ISERROR(F35*D35/30),0,F35*D35/30)) -> 0 | I35: =IF(H35="",0,IF(ISERROR(H35*$D35/30),0,H35*$D35/30)) -> 0 | K35: =IF(J35="",0,IF(ISERROR(J35*$D35/30),0,J35*$D35/30)) -> 0 | M35: =IF(AND($D35="",L35=""),0,L35*$E35) -> 0 | O35: =IF(AND($D35="",N35=""),0,N35*$E35) -> 0 | Q35: =IF(AND($D35="",P35=""),0,P35*$E35) -> 0 | S35: =IF(AND($D35="",R35=""),0,R35*$E35) -> 0 | U35: =IF(AND($D35="",T35=""),0,T35*$E35) -> 0 | W35: =IF(AND($D35="",V35=""),0,V35*$E35) -> 0 | Y35: =IF(AND($D35="",X35=""),0,X35*$E35) -> 0 | AH35: =IF(AG35="",0,AF35*AG35) -> 0 | AK35: =IF(AJ35="",0,AI35*AJ35) -> 0 | AO35: =30-AM35-J35-F35-H35 -> 30 | AP35: =E35+M35+O35+Q35+S35+U35+W35+Y35+SUM(Z35:AE35)+AH35+AK35 -> 0
B36: =IF(Empleados!C36="","",Empleados!C36) | C36: =IF(Empleados!E36="","",Empleados!E36) | D36: =Empleados!G36+Empleados!I36+Empleados!K36 -> 0 | E36: =D36*(30-H36-AM36)/30 -> 0 | G36: =IF(F36="",0,IF(ISERROR(F36*D36/30),0,F36*D36/30)) -> 0 | I36: =IF(H36="",0,IF(ISERROR(H36*$D36/30),0,H36*$D36/30)) -> 0 | K36: =IF(J36="",0,IF(ISERROR(J36*$D36/30),0,J36*$D36/30)) -> 0 | M36: =IF(AND($D36="",L36=""),0,L36*$E36) -> 0 | O36: =IF(AND($D36="",N36=""),0,N36*$E36) -> 0 | Q36: =IF(AND($D36="",P36=""),0,P36*$E36) -> 0 | S36: =IF(AND($D36="",R36=""),0,R36*$E36) -> 0 | U36: =IF(AND($D36="",T36=""),0,T36*$E36) -> 0 | W36: =IF(AND($D36="",V36=""),0,V36*$E36) -> 0 | Y36: =IF(AND($D36="",X36=""),0,X36*$E36) -> 0 | AH36: =IF(AG36="",0,AF36*AG36) -> 0 | AK36: =IF(AJ36="",0,AI36*AJ36) -> 0 | AO36: =30-AM36-J36-F36-H36 -> 30 | AP36: =E36+M36+O36+Q36+S36+U36+W36+Y36+SUM(Z36:AE36)+AH36+AK36 -> 0
... B56: =IF(Empleados!C56="","",Empleados!C56) | C56: =IF(Empleados!E56="","",Empleados!E56) | D56: =Empleados!G56+Empleados!I56+Empleados!K56 -> 0 | E56: =D56*(30-H56-AM56)/30 -> 0 | G56: =IF(F56="",0,IF(ISERROR(F56*D56/30),0,F56*D56/30)) -> 0 | I56: =IF(H56="",0,IF(ISERROR(H56*$D56/30),0,H56*$D56/30)) -> 0 | K56: =IF(J56="",0,IF(ISERROR(J56*$D56/30),0,J56*$D56/30)) -> 0 | M56: =IF(AND($D56="",L56=""),0,L56*$E56) -> 0 | O56: =IF(AND($D56="",N56=""),0,N56*$E56) -> 0 | Q56: =IF(AND($D56="",P56=""),0,P56*$E56) -> 0 | S56: =IF(AND($D56="",R56=""),0,R56*$E56) -> 0 | U56: =IF(AND($D56="",T56=""),0,T56*$E56) -> 0 | W56: =IF(AND($D56="",V56=""),0,V56*$E56) -> 0 | Y56: =IF(AND($D56="",X56=""),0,X56*$E56) -> 0 | AH56: =IF(AG56="",0,AF56*AG56) -> 0 | AK56: =IF(AJ56="",0,AI56*AJ56) -> 0 | AO56: =30-AM56-J56-F56-H56 -> 30 | AP56: =E56+M56+O56+Q56+S56+U56+W56+Y56+SUM(Z56:AE56)+AH56+AK56 -> 0
AP57: =SUM(AP8:AP25) -> #VALUE!
B58: =IF(Empleados!C57="","",Empleados!C57) | C58: =IF(Empleados!E57="","",Empleados!E57) | D58: =Empleados!G57+Empleados!I57+Empleados!K57 -> 0 | E58: =D58*(30-H58-AM58)/30 -> 0 | G58: =IF(F58="",0,IF(ISERROR(F58*D58/30),0,F58*D58/30)) -> 0 | I58: =IF(H58="",0,IF(ISERROR(H58*$D58/30),0,H58*$D58/30)) -> 0 | K58: =IF(J58="",0,IF(ISERROR(J58*$D58/30),0,J58*$D58/30)) -> 0 | M58: =IF(AND($D58="",L58=""),0,L58*$E58) -> 0 | O58: =IF(AND($D58="",N58=""),0,N58*$E58) -> 0 | Q58: =IF(AND($D58="",P58=""),0,P58*$E58) -> 0 | S58: =IF(AND($D58="",R58=""),0,R58*$E58) -> 0 | U58: =IF(AND($D58="",T58=""),0,T58*$E58) -> 0 | W58: =IF(AND($D58="",V58=""),0,V58*$E58) -> 0 | Y58: =IF(AND($D58="",X58=""),0,X58*$E58) -> 0 | AH58: =IF(AG58="",0,AF58*AG58) -> 0 | AK58: =IF(AJ58="",0,AI58*AJ58) -> 0 | AO58: =30-AM58-J58-F58-H58 -> 30 | AP58: =E58+M58+O58+Q58+S58+U58+W58+Y58+SUM(Z58:AE58)+AH58+AK58 -> 0

Sheet Ret. y no Rem.
E2: Retenciones y no Remunerativos
D5: Jubilación | F5: Ley 19032 | H5: Obra Social | J5: Adherente Os | L5: Sindicato UEC | N5: Ret. ANR s/ O.S. | P5: Ret. ANR s/ SIND. UEC | R5: FAECyS | T5: Ret. ANR FAECyS | V5: S | X5: Ret. Fija 4 | AD5: Asignaciones no remunerativas
B6: Leg. | C6: Nombre Competo | D6: % | E6: Importe | F6: % | G6: Importe | H6: % | I6: Importe | J6: % | K6: Importe | L6: % | M6: Importe | N6: % | O6: Importe | P6: % | Q6: Importe | R6: % | S6: Importe | T6: % | U6: Importe | V6: % | W6: Importe | X6: % | Y6: Importe | Z6: Anticipos | AA6: Anticipo SAC 2º SEM. | AB6: Obra Social Acuerd. Jun./11 | AC6: Subtotal Descuentos | AD6: Acuerdos Junio 2011 | AE6: Inc. Al basico | AF6: Presentismo Acuerdos No Rem. | AG6: Presentismo Acuerdos No Rem. | AH6: Vacaciones no Gozadas | AI6: SAC S/ VNG | AJ6: Acuerdo Junio 2010 | AK6: Adic. No Rem 6 | AL6: Redondeo | AM6: Subtotal no Rem. | AN6: Sueldo Neto Total exacto | AO6: Sueldo Neto Total
B7: =+Remuneración!B8 -> 1 | C7: =+Remuneración!C8 -> ARANIBAR CLAUDIA CRISTINA | D7: 0.11 | E7: =IF(D7="",0,IF(ISERROR(D7*Remuneración!$AP8),"",D7*Remuneración!$AP8)) | F7: 0.03 | G7: =IF(F7="",0,IF(ISERROR(F7*Remuneración!$AP8),"",F7*Remuneración!$AP8)) | H7: 0.03 | I7: =IF(H7="",0,IF(ISERROR(H7*Remuneración!$AP8),"",H7*Remuneración!$AP8)) | K7: =IF(J7="",0,IF(ISERROR(J7*Remuneración!$AP8),"",J7*Remuneración!$AP8)) -> 0 | M7: =IF(L7="",0,IF(ISERROR(L7*Remuneración!$AP8),"",L7*Remuneración!$AP8)) -> 0 | N7: 0.03 | O7: =IF(N7="",0,IF(ISERROR(N7*($AE7+$AD7+$AF7+$AJ7)),"",N7*($AE7+$AD7+$AF7+$AJ7))) -> 0 | Q7: =IF(P7="",0,IF(ISERROR(P7*($AE7+$AD7+$AF7+$AJ7)),"",P7*($AE7+$AD7+$AF7+$AJ7))) -> 0 | R7: 0.005 | S7: =IF(R7="",0,IF(ISERROR(R7*Remuneración!$AP8),"",R7*Remuneración!$AP8)) | U7: =IF(T7="",0,IF(ISERROR(T7*($AE7+$AD7+$AF7+$AJ7)),"",T7*($AE7+$AD7+$AF7+$AJ7))) -> 0 | W7: =IF(V7="",0,IF(ISERROR(V7*Remuneración!$AP8),"",V7*Remuneración!$AP8)) -> 0 | Y7: =IF(X7="",0,IF(ISERROR(X7*Remuneración!$AP8),"",X7*Remuneración!$AP8)) -> 0 | AB7: 0 | AC7: =+E7+G7+I7+K7+M7+O7+Q7+W7+Y7+S7+U7+SUM(Z7:AB7) -> #VALUE! | AF7: =+(AD7+AJ7)*0.0833 -> 0 | AI7: =AH7/12 -> 0 | AL7: =ROUNDUP(AN7,0)-AN7 -> #VALUE! | AM7: =IF(SUM(AD7:AK7)=0,0,SUM(AD7:AK7)) -> 0 | AN7: =+AM7-AC7+Remuneración!AP8 -> #VALUE! | AO7: =+AN7+AL7 -> #VALUE!
B8: 2 | C8: =+Remuneración!C9 -> QUIROGA VANINA LEONELA | D8: 0.11 | E8: =IF(D8="",0,IF(ISERROR(D8*Remuneración!$AP9),"",D8*Remuneración!$AP9)) -> 243.51197 | F8: 0.03 | G8: =IF(F8="",0,IF(ISERROR(F8*Remuneración!$AP9),"",F8*Remuneración!$AP9)) -> 66.412356 | H8: 0.03 | I8: =IF(H8="",0,IF(ISERROR(H8*Remuneración!$AP9),"",H8*Remuneración!$AP9)) -> 66.412356 | K8: =IF(J8="",0,IF(ISERROR(J8*Remuneración!$AP9),"",J8*Remuneración!$AP9)) -> 0 | M8: =IF(L8="",0,IF(ISERROR(L8*Remuneración!$AP9),"",L8*Remuneración!$AP9)) -> 0 | O8: =IF(N8="",0,IF(ISERROR(N8*($AE8+$AD8+$AF8+$AJ8)),"",N8*($AE8+$AD8+$AF8+$AJ8))) -> 0 | Q8: =IF(P8="",0,IF(ISERROR(P8*$AE8),"",P8*$AE8)) -> 0 | S8: =IF(R8="",0,IF(ISERROR(R8*Remuneración!$AP9),"",R8*Remuneración!$AP9)) -> 0 | U8: =IF(T8="",0,IF(ISERROR(T8*Remuneración!$AP9),"",T8*Remuneración!$AP9)) -> 0 | W8: =IF(V8="",0,IF(ISERROR(V8*Remuneración!$AP9),"",V8*Remuneración!$AP9)) -> 0 | Y8: =IF(X8="",0,IF(ISERROR(X8*Remuneración!$AP9),"",X8*Remuneración!$AP9)) -> 0 | AC8: =+E8+G8+I8+K8+M8+O8+Q8+W8+Y8+S8+U8+SUM(Z8:AB8) -> 376.33669 | AL8: =ROUNDUP(AN8,0)-AN8 -> 0.59147072 | AM8: =IF(SUM(AD8:AK8)=0,0,SUM(AD8:AK8)) -> 0 | AN8: =+AM8-AC8+Remuneración!AP9 -> 1837.4085 | AO8: =+AN8+AL8 -> 1838
C9: =+Remuneración!C10 | E9: =IF(D9="",0,IF(ISERROR(D9*Remuneración!$AP10),"",D9*Remuneración!$AP10)) -> 0 | G9: =IF(F9="",0,IF(ISERROR(F9*Remuneración!$AP10),"",F9*Remuneración!$AP10)) -> 0 | I9: =IF(H9="",0,IF(ISERROR(H9*Remuneración!$AP10),"",H9*Remuneración!$AP10)) -> 0 | K9: =IF(J9="",0,IF(ISERROR(J9*Remuneración!$AP10),"",J9*Remuneración!$AP10)) -> 0 | M9: =IF(L9="",0,IF(ISERROR(L9*Remuneración!$AP10),"",L9*Remuneración!$AP10)) -> 0 | O9: =IF(N9="",0,IF(ISERROR(N9*$AE9),"",N9*$AE9)) -> 0 | Q9: =IF(P9="",0,IF(ISERROR(P9*$AE9),"",P9*$AE9)) -> 0 | S9: =IF(R9="",0,IF(ISERROR(R9*Remuneración!$AP10),"",R9*Remuneración!$AP10)) -> 0 | U9: =IF(T9="",0,IF(ISERROR(T9*Remuneración!$AP10),"",T9*Remuneración!$AP10)) -> 0 | W9: =IF(V9="",0,IF(ISERROR(V9*Remuneración!$AP10),"",V9*Remuneración!$AP10)) -> 0 | Y9: =IF(X9="",0,IF(ISERROR(X9*Remuneración!$AP10),"",X9*Remuneración!$AP10)) -> 0 | AC9: =+E9+G9+I9+K9+M9+O9+Q9+W9+Y9+S9+U9+SUM(Z9:AB9) -> 0 | AL9: =ROUNDUP(AN9,0)-AN9 -> 0 | AM9: =IF(SUM(AD9:AK9)=0,0,SUM(AD9:AK9)) -> 0 | AN9: =+AM9-AC9+Remuneración!AP10 -> 0 | AO9: =+AN9+AL9 -> 0
C10: =+Remuneración!C11 | E10: =IF(D10="",0,IF(ISERROR(D10*Remuneración!$AP11),"",D10*Remuneración!$AP11)) -> 0 | G10: =IF(F10="",0,IF(ISERROR(F10*Remuneración!$AP11),"",F10*Remuneración!$AP11)) -> 0 | I10: =IF(H10="",0,IF(ISERROR(H10*Remuneración!$AP11),"",H10*Remuneración!$AP11)) -> 0 | K10: =IF(J10="",0,IF(ISERROR(J10*Remuneración!$AP11),"",J10*Remuneración!$AP11)) -> 0 | M10: =IF(L10="",0,IF(ISERROR(L10*Remuneración!$AP11),"",L10*Remuneración!$AP11)) -> 0 | O10: =IF(N10="",0,IF(ISERROR(N10*$AE10),"",N10*$AE10)) -> 0 | Q10: =IF(P10="",0,IF(ISERROR(P10*$AE10),"",P10*$AE10)) -> 0 | S10: =IF(R10="",0,IF(ISERROR(R10*Remuneración!$AP11),"",R10*Remuneración!$AP11)) -> 0 | U10: =IF(T10="",0,IF(ISERROR(T10*Remuneración!$AP11),"",T10*Remuneración!$AP11)) -> 0 | W10: =IF(V10="",0,IF(ISERROR(V10*Remuneración!$AP11),"",V10*Remuneración!$AP11)) -> 0 | Y10: =IF(X10="",0,IF(ISERROR(X10*Remuneración!$AP11),"",X10*Remuneración!$AP11)) -> 0 | AC10: =+E10+G10+I10+K10+M10+O10+Q10+W10+Y10+S10+U10+SUM(Z10:AB10) -> 0 | AL10: =ROUNDUP(AN10,0)-AN10 -> 0 | AM10: =IF(SUM(AD10:AK10)=0,0,SUM(AD10:AK10)) -> 0 | AN10: =+AM10-AC10+Remuneración!AP11 -> 0 | AO10: =+AN10+AL10 -> 0
C11: =+Remuneración!C12 | E11: =IF(D11="",0,IF(ISERROR(D11*Remuneración!$AP12),"",D11*Remuneración!$AP12)) -> 0 | G11: =IF(F11="",0,IF(ISERROR(F11*Remuneración!$AP12),"",F11*Remuneración!$AP12)) -> 0 | I11: =IF(H11="",0,IF(ISERROR(H11*Remuneración!$AP12),"",H11*Remuneración!$AP12)) -> 0 | K11: =IF(J11="",0,IF(ISERROR(J11*Remuneración!$AP12),"",J11*Remuneración!$AP12)) -> 0 | M11: =IF(L11="",0,IF(ISERROR(L11*Remuneración!$AP12),"",L11*Remuneración!$AP12)) -> 0 | O11: =IF(N11="",0,IF(ISERROR(N11*$AE11),"",N11*$AE11)) -> 0 | Q11: =IF(P11="",0,IF(ISERROR(P11*$AE11),"",P11*$AE11)) -> 0 | S11: =IF(R11="",0,IF(ISERROR(R11*Remuneración!$AP12),"",R11*Remuneración!$AP12)) -> 0 | U11: =IF(T11="",0,IF(ISERROR(T11*Remuneración!$AP12),"",T11*Remuneración!$AP12)) -> 0 | W11: =IF(V11="",0,IF(ISERROR(V11*Remuneración!$AP12),"",V11*Remuneración!$AP12)) -> 0 | Y11: =IF(X11="",0,IF(ISERROR(X11*Remuneración!$AP12),"",X11*Remuneración!$AP12)) -> 0 | AC11: =+E11+G11+I11+K11+M11+O11+Q11+W11+Y11+S11+U11+SUM(Z11:AB11) -> 0 | AL11: =ROUNDUP(AN11,0)-AN11 -> 0 | AM11: =IF(SUM(AD11:AK11)=0,0,SUM(AD11:AK11)) -> 0 | AN11: =+AM11-AC11+Remuneración!AP12 -> 0 | AO11: =+AN11+AL11 -> 0
C12: =+Remuneración!C13 | E12: =IF(D12="",0,IF(ISERROR(D12*Remuneración!$AP13),"",D12*Remuneración!$AP13)) -> 0 | G12: =IF(F12="",0,IF(ISERROR(F12*Remuneración!$AP13),"",F12*Remuneración!$AP13)) -> 0 | I12: =IF(H12="",0,IF(ISERROR(H12*Remuneración!$AP13),"",H12*Remuneración!$AP13)) -> 0 | K12: =IF(J12="",0,IF(ISERROR(J12*Remuneración!$AP13),"",J12*Remuneración!$AP13)) -> 0 | M12: =IF(L12="",0,IF(ISERROR(L12*Remuneración!$AP13),"",L12*Remuneración!$AP13)) -> 0 | O12: =IF(N12="",0,IF(ISERROR(N12*$AE12),"",N12*$AE12)) -> 0 | Q12: =IF(P12="",0,IF(ISERROR(P12*$AE12),"",P12*$AE12)) -> 0 | S12: =IF(R12="",0,IF(ISERROR(R12*Remuneración!$AP13),"",R12*Remuneración!$AP13)) -> 0 | U12: =IF(T12="",0,IF(ISERROR(T12*Remuneración!$AP13),"",T12*Remuneración!$AP13)) -> 0 | W12: =IF(V12="",0,IF(ISERROR(V12*Remuneración!$AP13),"",V12*Remuneración!$AP13)) -> 0 | Y12: =IF(X12="",0,IF(ISERROR(X12*Remuneración!$AP13),"",X12*Remuneración!$AP13)) -> 0 | AC12: =+E12+G12+I12+K12+M12+O12+Q12+W12+Y12+S12+U12+SUM(Z12:AB12) -> 0 | AL12: =ROUNDUP(AN12,0)-AN12 -> 0 | AM12: =IF(SUM(AD12:AK12)=0,0,SUM(AD12:AK12)) -> 0 | AN12: =+AM12-AC12+Remuneración!AP13 -> 0 | AO12: =+AN12+AL12 -> 0
C13: =+Remuneración!C14 | E13: =IF(D13="",0,IF(ISERROR(D13*Remuneración!$AP14),"",D13*Remuneración!$AP14)) -> 0 | G13: =IF(F13="",0,IF(ISERROR(F13*Remuneración!$AP14),"",F13*Remuneración!$AP14)) -> 0 | I13: =IF(H13="",0,IF(ISERROR(H13*Remuneración!$AP14),"",H13*Remuneración!$AP14)) -> 0 | K13: =IF(J13="",0,IF(ISERROR(J13*Remuneración!$AP14),"",J13*Remuneración!$AP14)) -> 0 | M13: =IF(L13="",0,IF(ISERROR(L13*Remuneración!$AP14),"",L13*Remuneración!$AP14)) -> 0 | O13: =IF(N13="",0,IF(ISERROR(N13*$AE13),"",N13*$AE13)) -> 0 | Q13: =IF(P13="",0,IF(ISERROR(P13*$AE13),"",P13*$AE13)) -> 0 | S13: =IF(R13="",0,IF(ISERROR(R13*Remuneración!$AP14),"",R13*Remuneración!$AP14)) -> 0 | U13: =IF(T13="",0,IF(ISERROR(T13*Remuneración!$AP14),"",T13*Remuneración!$AP14)) -> 0 | W13: =IF(V13="",0,IF(ISERROR(V13*Remuneración!$AP14),"",V13*Remuneración!$AP14)) -> 0 | Y13: =IF(X13="",0,IF(ISERROR(X13*Remuneración!$AP14),"",X13*Remuneración!$AP14)) -> 0 | AC13: =+E13+G13+I13+K13+M13+O13+Q13+W13+Y13+S13+U13+SUM(Z13:AB13) -> 0 | AL13: =ROUNDUP(AN13,0)-AN13 -> 0 | AM13: =IF(SUM(AD13:AK13)=0,0,SUM(AD13:AK13)) -> 0 | AN13: =+AM13-AC13+Remuneración!AP14 -> 0 | AO13: =+AN13+AL13 -> 0
C14: =+Remuneración!C15 | E14: =IF(D14="",0,IF(ISERROR(D14*Remuneración!$AP15),"",D14*Remuneración!$AP15)) -> 0 | G14: =IF(F14="",0,IF(ISERROR(F14*Remuneración!$AP15),"",F14*Remuneración!$AP15)) -> 0 | I14: =IF(H14="",0,IF(ISERROR(H14*Remuneración!$AP15),"",H14*Remuneración!$AP15)) -> 0 | K14: =IF(J14="",0,IF(ISERROR(J14*Remuneración!$AP15),"",J14*Remuneración!$AP15)) -> 0 | M14: =IF(L14="",0,IF(ISERROR(L14*Remuneración!$AP15),"",L14*Remuneración!$AP15)) -> 0 | O14: =IF(N14="",0,IF(ISERROR(N14*$AE14),"",N14*$AE14)) -> 0 | Q14: =IF(P14="",0,IF(ISERROR(P14*$AE14),"",P14*$AE14)) -> 0 | S14: =IF(R14="",0,IF(ISERROR(R14*Remuneración!$AP15),"",R14*Remuneración!$AP15)) -> 0 | U14: =IF(T14="",0,IF(ISERROR(T14*Remuneración!$AP15),"",T14*Remuneración!$AP15)) -> 0 | W14: =IF(V14="",0,IF(ISERROR(V14*Remuneración!$AP15),"",V14*Remuneración!$AP15)) -> 0 | Y14: =IF(X14="",0,IF(ISERROR(X14*Remuneración!$AP15),"",X14*Remuneración!$AP15)) -> 0 | AC14: =+E14+G14+I14+K14+M14+O14+Q14+W14+Y14+S14+U14+SUM(Z14:AB14) -> 0 | AL14: =ROUNDUP(AN14,0)-AN14 -> 0 | AM14: =IF(SUM(AD14:AK14)=0,0,SUM(AD14:AK14)) -> 0 | AN14: =+AM14-AC14+Remuneración!AP15 -> 0 | AO14: =+AN14+AL14 -> 0
C15: =+Remuneración!C16 | E15: =IF(D15="",0,IF(ISERROR(D15*Remuneración!$AP16),"",D15*Remuneración!$AP16)) -> 0 | G15: =IF(F15="",0,IF(ISERROR(F15*Remuneración!$AP16),"",F15*Remuneración!$AP16)) -> 0 | I15: =IF(H15="",0,IF(ISERROR(H15*Remuneración!$AP16),"",H15*Remuneración!$AP16)) -> 0 | K15: =IF(J15="",0,IF(ISERROR(J15*Remuneración!$AP16),"",J15*Remuneración!$AP16)) -> 0 | M15: =IF(L15="",0,IF(ISERROR(L15*Remuneración!$AP16),"",L15*Remuneración!$AP16)) -> 0 | O15: =IF(N15="",0,IF(ISERROR(N15*$AE15),"",N15*$AE15)) -> 0 | Q15: =IF(P15="",0,IF(ISERROR(P15*$AE15),"",P15*$AE15)) -> 0 | S15: =IF(R15="",0,IF(ISERROR(R15*Remuneración!$AP16),"",R15*Remuneración!$AP16)) -> 0 | U15: =IF(T15="",0,IF(ISERROR(T15*Remuneración!$AP16),"",T15*Remuneración!$AP16)) -> 0 | W15: =IF(V15="",0,IF(ISERROR(V15*Remuneración!$AP16),"",V15*Remuneración!$AP16)) -> 0 | Y15: =IF(X15="",0,IF(ISERROR(X15*Remuneración!$AP16),"",X15*Remuneración!$AP16)) -> 0 | AC15: =+E15+G15+I15+K15+M15+O15+Q15+W15+Y15+S15+U15+SUM(Z15:AB15) -> 0 | AL15: =ROUNDUP(AN15,0)-AN15 -> 0 | AM15: =IF(SUM(AD15:AK15)=0,0,SUM(AD15:AK15)) -> 0 | AN15: =+AM15-AC15+Remuneración!AP16 -> 0 | AO15: =+AN15+AL15 -> 0
C16: =+Remuneración!C17 | E16: =IF(D16="",0,IF(ISERROR(D16*Remuneración!$AP17),"",D16*Remuneración!$AP17)) -> 0 | G16: =IF(F16="",0,IF(ISERROR(F16*Remuneración!$AP17),"",F16*Remuneración!$AP17)) -> 0 | I16: =IF(H16="",0,IF(ISERROR(H16*Remuneración!$AP17),"",H16*Remuneración!$AP17)) -> 0 | K16: =IF(J16="",0,IF(ISERROR(J16*Remuneración!$AP17),"",J16*Remuneración!$AP17)) -> 0 | M16: =IF(L16="",0,IF(ISERROR(L16*Remuneración!$AP17),"",L16*Remuneración!$AP17)) -> 0 | O16: =IF(N16="",0,IF(ISERROR(N16*$AE16),"",N16*$AE16)) -> 0 | Q16: =IF(P16="",0,IF(ISERROR(P16*$AE16),"",P16*$AE16)) -> 0 | S16: =IF(R16="",0,IF(ISERROR(R16*Remuneración!$AP17),"",R16*Remuneración!$AP17)) -> 0 | U16: =IF(T16="",0,IF(ISERROR(T16*Remuneración!$AP17),"",T16*Remuneración!$AP17)) -> 0 | W16: =IF(V16="",0,IF(ISERROR(V16*Remuneración!$AP17),"",V16*Remuneración!$AP17)) -> 0 | Y16: =IF(X16="",0,IF(ISERROR(X16*Remuneración!$AP17),"",X16*Remuneración!$AP17)) -> 0 | AC16: =+E16+G16+I16+K16+M16+O16+Q16+W16+Y16+S16+U16+SUM(Z16:AB16) -> 0 | AL16: =ROUNDUP(AN16,0)-AN16 -> 0 | AM16: =IF(SUM(AD16:AK16)=0,0,SUM(AD16:AK16)) -> 0 | AN16: =+AM16-AC16+Remuneración!AP17 -> 0 | AO16: =+AN16+AL16 -> 0
C17: =+Remuneración!C18 | E17: =IF(D17="",0,IF(ISERROR(D17*Remuneración!$AP18),"",D17*Remuneración!$AP18)) -> 0 | G17: =IF(F17="",0,IF(ISERROR(F17*Remuneración!$AP18),"",F17*Remuneración!$AP18)) -> 0 | I17: =IF(H17="",0,IF(ISERROR(H17*Remuneración!$AP18),"",H17*Remuneración!$AP18)) -> 0 | K17: =IF(J17="",0,IF(ISERROR(J17*Remuneración!$AP18),"",J17*Remuneración!$AP18)) -> 0 | M17: =IF(L17="",0,IF(ISERROR(L17*Remuneración!$AP18),"",L17*Remuneración!$AP18)) -> 0 | O17: =IF(N17="",0,IF(ISERROR(N17*$AE17),"",N17*$AE17)) -> 0 | Q17: =IF(P17="",0,IF(ISERROR(P17*$AE17),"",P17*$AE17)) -> 0 | S17: =IF(R17="",0,IF(ISERROR(R17*Remuneración!$AP18),"",R17*Remuneración!$AP18)) -> 0 | U17: =IF(T17="",0,IF(ISERROR(T17*Remuneración!$AP18),"",T17*Remuneración!$AP18)) -> 0 | W17: =IF(V17="",0,IF(ISERROR(V17*Remuneración!$AP18),"",V17*Remuneración!$AP18)) -> 0 | Y17: =IF(X17="",0,IF(ISERROR(X17*Remuneración!$AP18),"",X17*Remuneración!$AP18)) -> 0 | AC17: =+E17+G17+I17+K17+M17+O17+Q17+W17+Y17+S17+U17+SUM(Z17:AB17) -> 0 | AL17: =ROUNDUP(AN17,0)-AN17 -> 0 | AM17: =IF(SUM(AD17:AK17)=0,0,SUM(AD17:AK17)) -> 0 | AN17: =+AM17-AC17+Remuneración!AP18 -> 0 | AO17: =+AN17+AL17 -> 0
C18: =+Remuneración!C19 | E18: =IF(D18="",0,IF(ISERROR(D18*Remuneración!$AP19),"",D18*Remuneración!$AP19)) -> 0 | G18: =IF(F18="",0,IF(ISERROR(F18*Remuneración!$AP19),"",F18*Remuneración!$AP19)) -> 0 | I18: =IF(H18="",0,IF(ISERROR(H18*Remuneración!$AP19),"",H18*Remuneración!$AP19)) -> 0 | K18: =IF(J18="",0,IF(ISERROR(J18*Remuneración!$AP19),"",J18*Remuneración!$AP19)) -> 0 | M18: =IF(L18="",0,IF(ISERROR(L18*Remuneración!$AP19),"",L18*Remuneración!$AP19)) -> 0 | O18: =IF(N18="",0,IF(ISERROR(N18*$AE18),"",N18*$AE18)) -> 0 | Q18: =IF(P18="",0,IF(ISERROR(P18*$AE18),"",P18*$AE18)) -> 0 | S18: =IF(R18="",0,IF(ISERROR(R18*Remuneración!$AP19),"",R18*Remuneración!$AP19)) -> 0 | U18: =IF(T18="",0,IF(ISERROR(T18*Remuneración!$AP19),"",T18*Remuneración!$AP19)) -> 0 | W18: =IF(V18="",0,IF(ISERROR(V18*Remuneración!$AP19),"",V18*Remuneración!$AP19)) -> 0 | Y18: =IF(X18="",0,IF(ISERROR(X18*Remuneración!$AP19),"",X18*Remuneración!$AP19)) -> 0 | AC18: =+E18+G18+I18+K18+M18+O18+Q18+W18+Y18+S18+U18+SUM(Z18:AB18) -> 0 | AL18: =ROUNDUP(AN18,0)-AN18 -> 0 | AN18: =+AM18-AC18+Remuneración!AP19 -> 0 | AO18: =+AN18+AL18 -> 0
C19: =+Remuneración!C20 | E19: =IF(D19="",0,IF(ISERROR(D19*Remuneración!$AP20),"",D19*Remuneración!$AP20)) -> 0 | G19: =IF(F19="",0,IF(ISERROR(F19*Remuneración!$AP20),"",F19*Remuneración!$AP20)) -> 0 | I19: =IF(H19="",0,IF(ISERROR(H19*Remuneración!$AP20),"",H19*Remuneración!$AP20)) -> 0 | K19: =IF(J19="",0,IF(ISERROR(J19*Remuneración!$AP20),"",J19*Remuneración!$AP20)) -> 0 | M19: =IF(L19="",0,IF(ISERROR(L19*Remuneración!$AP20),"",L19*Remuneración!$AP20)) -> 0 | O19: =IF(N19="",0,IF(ISERROR(N19*$AE19),"",N19*$AE19)) -> 0 | Q19: =IF(P19="",0,IF(ISERROR(P19*$AE19),"",P19*$AE19)) -> 0 | S19: =IF(R19="",0,IF(ISERROR(R19*Remuneración!$AP20),"",R19*Remuneración!$AP20)) -> 0 | U19: =IF(T19="",0,IF(ISERROR(T19*Remuneración!$AP20),"",T19*Remuneración!$AP20)) -> 0 | W19: =IF(V19="",0,IF(ISERROR(V19*Remuneración!$AP20),"",V19*Remuneración!$AP20)) -> 0 | Y19: =IF(X19="",0,IF(ISERROR(X19*Remuneración!$AP20),"",X19*Remuneración!$AP20)) -> 0 | AC19: =+E19+G19+I19+K19+M19+O19+Q19+W19+Y19+S19+U19+SUM(Z19:AB19) -> 0 | AL19: =ROUNDUP(AN19,0)-AN19 -> 0 | AM19: =IF(SUM(AD19:AK19)=0,0,SUM(AD19:AK19)) -> 0 | AN19: =+AM19-AC19+Remuneración!AP20 -> 0 | AO19: =+AN19+AL19 -> 0
C20: =+Remuneración!C21 | E20: =IF(D20="",0,IF(ISERROR(D20*Remuneración!$AP21),"",D20*Remuneración!$AP21)) -> 0 | G20: =IF(F20="",0,IF(ISERROR(F20*Remuneración!$AP21),"",F20*Remuneración!$AP21)) -> 0 | I20: =IF(H20="",0,IF(ISERROR(H20*Remuneración!$AP21),"",H20*Remuneración!$AP21)) -> 0 | K20: =IF(J20="",0,IF(ISERROR(J20*Remuneración!$AP21),"",J20*Remuneración!$AP21)) -> 0 | M20: =IF(L20="",0,IF(ISERROR(L20*Remuneración!$AP21),"",L20*Remuneración!$AP21)) -> 0 | O20: =IF(N20="",0,IF(ISERROR(N20*$AE20),"",N20*$AE20)) -> 0 | Q20: =IF(P20="",0,IF(ISERROR(P20*$AE20),"",P20*$AE20)) -> 0 | S20: =IF(R20="",0,IF(ISERROR(R20*Remuneración!$AP21),"",R20*Remuneración!$AP21)) -> 0 | U20: =IF(T20="",0,IF(ISERROR(T20*Remuneración!$AP21),"",T20*Remuneración!$AP21)) -> 0 | W20: =IF(V20="",0,IF(ISERROR(V20*Remuneración!$AP21),"",V20*Remuneración!$AP21)) -> 0 | Y20: =IF(X20="",0,IF(ISERROR(X20*Remuneración!$AP21),"",X20*Remuneración!$AP21)) -> 0 | AC20: =+E20+G20+I20+K20+M20+O20+Q20+W20+Y20+S20+U20+SUM(Z20:AB20) -> 0 | AL20: =ROUNDUP(AN20,0)-AN20 -> 0 | AM20: =IF(SUM(AD20:AK20)=0,0,SUM(AD20:AK20)) -> 0 | AN20: =+AM20-AC20+Remuneración!AP21 -> 0 | AO20: =+AN20+AL20 -> 0
C21: =+Remuneración!C22 | E21: =IF(D21="",0,IF(ISERROR(D21*Remuneración!$AP22),"",D21*Remuneración!$AP22)) -> 0 | G21: =IF(F21="",0,IF(ISERROR(F21*Remuneración!$AP22),"",F21*Remuneración!$AP22)) -> 0 | I21: =IF(H21="",0,IF(ISERROR(H21*Remuneración!$AP22),"",H21*Remuneración!$AP22)) -> 0 | K21: =IF(J21="",0,IF(ISERROR(J21*Remuneración!$AP22),"",J21*Remuneración!$AP22)) -> 0 | M21: =IF(L21="",0,IF(ISERROR(L21*Remuneración!$AP22),"",L21*Remuneración!$AP22)) -> 0 | O21: =IF(N21="",0,IF(ISERROR(N21*$AE21),"",N21*$AE21)) -> 0 | Q21: =IF(P21="",0,IF(ISERROR(P21*$AE21),"",P21*$AE21)) -> 0 | S21: =IF(R21="",0,IF(ISERROR(R21*Remuneración!$AP22),"",R21*Remuneración!$AP22)) -> 0 | U21: =IF(T21="",0,IF(ISERROR(T21*Remuneración!$AP22),"",T21*Remuneración!$AP22)) -> 0 | W21: =IF(V21="",0,IF(ISERROR(V21*Remuneración!$AP22),"",V21*Remuneración!$AP22)) -> 0 | Y21: =IF(X21="",0,IF(ISERROR(X21*Remuneración!$AP22),"",X21*Remuneración!$AP22)) -> 0 | AC21: =+E21+G21+I21+K21+M21+O21+Q21+W21+Y21+S21+U21+SUM(Z21:AB21) -> 0 | AL21: =ROUNDUP(AN21,0)-AN21 -> 0 | AM21: =IF(SUM(AD21:AK21)=0,0,SUM(AD21:AK21)) -> 0 | AN21: =+AM21-AC21+Remuneración!AP22 -> 0 | AO21: =+AN21+AL21 -> 0
C22: =+Remuneración!C23 | E22: =IF(D22="",0,IF(ISERROR(D22*Remuneración!$AP23),"",D22*Remuneración!$AP23)) -> 0 | G22: =IF(F22="",0,IF(ISERROR(F22*Remuneración!$AP23),"",F22*Remuneración!$AP23)) -> 0 | I22: =IF(H22="",0,IF(ISERROR(H22*Remuneración!$AP23),"",H22*Remuneración!$AP23)) -> 0 | K22: =IF(J22="",0,IF(ISERROR(J22*Remuneración!$AP23),"",J22*Remuneración!$AP23)) -> 0 | M22: =IF(L22="",0,IF(ISERROR(L22*Remuneración!$AP23),"",L22*Remuneración!$AP23)) -> 0 | O22: =IF(N22="",0,IF(ISERROR(N22*$AE22),"",N22*$AE22)) -> 0 | Q22: =IF(P22="",0,IF(ISERROR(P22*$AE22),"",P22*$AE22)) -> 0 | S22: =IF(R22="",0,IF(ISERROR(R22*Remuneración!$AP23),"",R22*Remuneración!$AP23)) -> 0 | U22: =IF(T22="",0,IF(ISERROR(T22*Remuneración!$AP23),"",T22*Remuneración!$AP23)) -> 0 | W22: =IF(V22="",0,IF(ISERROR(V22*Remuneración!$AP23),"",V22*Remuneración!$AP23)) -> 0 | Y22: =IF(X22="",0,IF(ISERROR(X22*Remuneración!$AP23),"",X22*Remuneración!$AP23)) -> 0 | AC22: =+E22+G22+I22+K22+M22+O22+Q22+W22+Y22+S22+U22+SUM(Z22:AB22) -> 0 | AL22: =ROUNDUP(AN22,0)-AN22 -> 0 | AM22: =IF(SUM(AD22:AK22)=0,0,SUM(AD22:AK22)) -> 0 | AN22: =+AM22-AC22+Remuneración!AP23 -> 0 | AO22: =+AN22+AL22 -> 0
C23: =+Remuneración!C24 | E23: =IF(D23="",0,IF(ISERROR(D23*Remuneración!$AP24),"",D23*Remuneración!$AP24)) -> 0 | G23: =IF(F23="",0,IF(ISERROR(F23*Remuneración!$AP24),"",F23*Remuneración!$AP24)) -> 0 | I23: =IF(H23="",0,IF(ISERROR(H23*Remuneración!$AP24),"",H23*Remuneración!$AP24)) -> 0 | K23: =IF(J23="",0,IF(ISERROR(J23*Remuneración!$AP24),"",J23*Remuneración!$AP24)) -> 0 | M23: =IF(L23="",0,IF(ISERROR(L23*Remuneración!$AP24),"",L23*Remuneración!$AP24)) -> 0 | O23: =IF(N23="",0,IF(ISERROR(N23*$AE23),"",N23*$AE23)) -> 0 | Q23: =IF(P23="",0,IF(ISERROR(P23*$AE23),"",P23*$AE23)) -> 0 | S23: =IF(R23="",0,IF(ISERROR(R23*Remuneración!$AP24),"",R23*Remuneración!$AP24)) -> 0 | U23: =IF(T23="",0,IF(ISERROR(T23*Remuneración!$AP24),"",T23*Remuneración!$AP24)) -> 0 | W23: =IF(V23="",0,IF(ISERROR(V23*Remuneración!$AP24),"",V23*Remuneración!$AP24)) -> 0 | Y23: =IF(X23="",0,IF(ISERROR(X23*Remuneración!$AP24),"",X23*Remuneración!$AP24)) -> 0 | AC23: =+E23+G23+I23+K23+M23+O23+Q23+W23+Y23+S23+U23+SUM(Z23:AB23) -> 0 | AL23: =ROUNDUP(AN23,0)-AN23 -> 0 | AM23: =IF(SUM(AD23:AK23)=0,0,SUM(AD23:AK23)) -> 0 | AN23: =+AM23-AC23+Remuneración!AP24 -> 0 | AO23: =+AN23+AL23 -> 0
B24: =+Remuneración!B25 | C24: =+Remuneración!C25 | E24: =IF(D24="",0,IF(ISERROR(D24*Remuneración!$AP25),"",D24*Remuneración!$AP25)) -> 0 | G24: =IF(F24="",0,IF(ISERROR(F24*Remuneración!$AP25),"",F24*Remuneración!$AP25)) -> 0 | I24: =IF(H24="",0,IF(ISERROR(H24*Remuneración!$AP25),"",H24*Remuneración!$AP25)) -> 0 | K24: =IF(J24="",0,IF(ISERROR(J24*Remuneración!$AP25),"",J24*Remuneración!$AP25)) -> 0 | M24: =IF(L24="",0,IF(ISERROR(L24*Remuneración!$AP25),"",L24*Remuneración!$AP25)) -> 0 | O24: =IF(N24="",0,IF(ISERROR(N24*$AE24),"",N24*$AE24)) -> 0 | Q24: =IF(P24="",0,IF(ISERROR(P24*$AE24),"",P24*$AE24)) -> 0 | S24: =IF(R24="",0,IF(ISERROR(R24*Remuneración!$AP25),"",R24*Remuneración!$AP25)) -> 0 | U24: =IF(T24="",0,IF(ISERROR(T24*Remuneración!$AP25),"",T24*Remuneración!$AP25)) -> 0 | W24: =IF(V24="",0,IF(ISERROR(V24*Remuneración!$AP25),"",V24*Remuneración!$AP25)) -> 0 | Y24: =IF(X24="",0,IF(ISERROR(X24*Remuneración!$AP25),"",X24*Remuneración!$AP25)) -> 0 | AC24: =+E24+G24+I24+K24+M24+O24+Q24+W24+Y24+S24+U24+SUM(Z24:AB24) -> 0 | AL24: =ROUNDUP(AN24,0)-AN24 -> 0 | AM24: =IF(SUM(AD24:AK24)=0,0,SUM(AD24:AK24)) -> 0 | AN24: =+AM24-AC24+Remuneración!AP25 -> 0 | AO24: =+AN24+AL24 -> 0
B25: =+Remuneración!B26 | C25: =+Remuneración!C26 | E25: =IF(D25="",0,IF(ISERROR(D25*Remuneración!$AP26),"",D25*Remuneración!$AP26)) -> 0 | G25: =IF(F25="",0,IF(ISERROR(F25*Remuneración!$AP26),"",F25*Remuneración!$AP26)) -> 0 | I25: =IF(H25="",0,IF(ISERROR(H25*Remuneración!$AP26),"",H25*Remuneración!$AP26)) -> 0 | K25: =IF(J25="",0,IF(ISERROR(J25*Remuneración!$AP26),"",J25*Remuneración!$AP26)) -> 0 | M25: =IF(L25="",0,IF(ISERROR(L25*Remuneración!$AP26),"",L25*Remuneración!$AP26)) -> 0 | O25: =IF(N25="",0,IF(ISERROR(N25*$AE25),"",N25*$AE25)) -> 0 | Q25: =IF(P25="",0,IF(ISERROR(P25*$AE25),"",P25*$AE25)) -> 0 | S25: =IF(R25="",0,IF(ISERROR(R25*Remuneración!$AP26),"",R25*Remuneración!$AP26)) -> 0 | U25: =IF(T25="",0,IF(ISERROR(T25*Remuneración!$AP26),"",T25*Remuneración!$AP26)) -> 0 | W25: =IF(V25="",0,IF(ISERROR(V25*Remuneración!$AP26),"",V25*Remuneración!$AP26)) -> 0 | Y25: =IF(X25="",0,IF(ISERROR(X25*Remuneración!$AP26),"",X25*Remuneración!$AP26)) -> 0 | AC25: =+E25+G25+I25+K25+M25+O25+Q25+W25+Y25+S25+U25+SUM(Z25:AB25) -> 0 | AL25: =ROUNDUP(AN25,0)-AN25 -> 0 | AM25: =IF(SUM(AD25:AK25)=0,0,SUM(AD25:AK25)) -> 0 | AN25: =+AM25-AC25+Remuneración!AP26 -> 0 | AO25: =+AN25+AL25 -> 0
B26: =+Remuneración!B27 | C26: =+Remuneración!C27 | E26: =IF(D26="",0,IF(ISERROR(D26*Remuneración!$AP27),"",D26*Remuneración!$AP27)) -> 0 | G26: =IF(F26="",0,IF(ISERROR(F26*Remuneración!$AP27),"",F26*Remuneración!$AP27)) -> 0 | I26: =IF(H26="",0,IF(ISERROR(H26*Remuneración!$AP27),"",H26*Remuneración!$AP27)) -> 0 | K26: =IF(J26="",0,IF(ISERROR(J26*Remuneración!$AP27),"",J26*Remuneración!$AP27)) -> 0 | M26: =IF(L26="",0,IF(ISERROR(L26*Remuneración!$AP27),"",L26*Remuneración!$AP27)) -> 0 | O26: =IF(N26="",0,IF(ISERROR(N26*$AE26),"",N26*$AE26)) -> 0 | Q26: =IF(P26="",0,IF(ISERROR(P26*$AE26),"",P26*$AE26)) -> 0 | S26: =IF(R26="",0,IF(ISERROR(R26*Remuneración!$AP27),"",R26*Remuneración!$AP27)) -> 0 | U26: =IF(T26="",0,IF(ISERROR(T26*Remuneración!$AP27),"",T26*Remuneración!$AP27)) -> 0 | W26: =IF(V26="",0,IF(ISERROR(V26*Remuneración!$AP27),"",V26*Remuneración!$AP27)) -> 0 | Y26: =IF(X26="",0,IF(ISERROR(X26*Remuneración!$AP27),"",X26*Remuneración!$AP27)) -> 0 | AC26: =+E26+G26+I26+K26+M26+O26+Q26+W26+Y26+S26+U26+SUM(Z26:AB26) -> 0 | AL26: =ROUNDUP(AN26,0)-AN26 -> 0 | AM26: =IF(SUM(AD26:AK26)=0,0,SUM(AD26:AK26)) -> 0 | AN26: =+AM26-AC26+Remuneración!AP27 -> 0 | AO26: =+AN26+AL26 -> 0
B27: =+Remuneración!B28 | C27: =+Remuneración!C28 | E27: =IF(D27="",0,IF(ISERROR(D27*Remuneración!$AP28),"",D27*Remuneración!$AP28)) -> 0 | G27: =IF(F27="",0,IF(ISERROR(F27*Remuneración!$AP28),"",F27*Remuneración!$AP28)) -> 0 | K27: =IF(J27="",0,IF(ISERROR(J27*Remuneración!$AP28),"",J27*Remuneración!$AP28)) -> 0 | M27: =IF(L27="",0,IF(ISERROR(L27*Remuneración!$AP28),"",L27*Remuneración!$AP28)) -> 0 | O27: =IF(N27="",0,IF(ISERROR(N27*$AE27),"",N27*$AE27)) -> 0 | Q27: =IF(P27="",0,IF(ISERROR(P27*$AE27),"",P27*$AE27)) -> 0 | S27: =IF(R27="",0,IF(ISERROR(R27*Remuneración!$AP28),"",R27*Remuneración!$AP28)) -> 0 | U27: =IF(T27="",0,IF(ISERROR(T27*Remuneración!$AP28),"",T27*Remuneración!$AP28)) -> 0 | W27: =IF(V27="",0,IF(ISERROR(V27*Remuneración!$AP28),"",V27*Remuneración!$AP28)) -> 0 | Y27: =IF(X27="",0,IF(ISERROR(X27*Remuneración!$AP28),"",X27*Remuneración!$AP28)) -> 0 | AC27: =+E27+G27+I27+K27+M27+O27+Q27+W27+Y27+S27+U27+SUM(Z27:AB27) -> 0 | AL27: =ROUNDUP(AN27,0)-AN27 -> 0 | AM27: =IF(SUM(AD27:AK27)=0,0,SUM(AD27:AK27)) -> 0 | AN27: =+AM27-AC27+Remuneración!AP28 -> 0 | AO27: =+AN27+AL27 -> 0
B28: =+Remuneración!B29 | C28: =+Remuneración!C29 | E28: =IF(D28="",0,IF(ISERROR(D28*Remuneración!$AP29),"",D28*Remuneración!$AP29)) -> 0 | G28: =IF(F28="",0,IF(ISERROR(F28*Remuneración!$AP29),"",F28*Remuneración!$AP29)) -> 0 | I28: =IF(H28="",0,IF(ISERROR(H28*Remuneración!$AP29),"",H28*Remuneración!$AP29)) -> 0 | K28: =IF(J28="",0,IF(ISERROR(J28*Remuneración!$AP29),"",J28*Remuneración!$AP29)) -> 0 | M28: =IF(L28="",0,IF(ISERROR(L28*Remuneración!$AP29),"",L28*Remuneración!$AP29)) -> 0 | O28: =IF(N28="",0,IF(ISERROR(N28*$AE28),"",N28*$AE28)) -> 0 | Q28: =IF(P28="",0,IF(ISERROR(P28*$AE28),"",P28*$AE28)) -> 0 | S28: =IF(R28="",0,IF(ISERROR(R28*Remuneración!$AP29),"",R28*Remuneración!$AP29)) -> 0 | U28: =IF(T28="",0,IF(ISERROR(T28*Remuneración!$AP29),"",T28*Remuneración!$AP29)) -> 0 | W28: =IF(V28="",0,IF(ISERROR(V28*Remuneración!$AP29),"",V28*Remuneración!$AP29)) -> 0 | Y28: =IF(X28="",0,IF(ISERROR(X28*Remuneración!$AP29),"",X28*Remuneración!$AP29)) -> 0 | AC28: =+E28+G28+I28+K28+M28+O28+Q28+W28+Y28+S28+U28+SUM(Z28:AB28) -> 0 | AL28: =ROUNDUP(AN28,0)-AN28 -> 0 | AM28: =IF(SUM(AD28:AK28)=0,0,SUM(AD28:AK28)) -> 0 | AN28: =+AM28-AC28+Remuneración!AP29 -> 0 | AO28: =+AN28+AL28 -> 0
B29: =+Remuneración!B30 | C29: =+Remuneración!C30 | E29: =IF(D29="",0,IF(ISERROR(D29*Remuneración!$AP30),"",D29*Remuneración!$AP30)) -> 0 | G29: =IF(F29="",0,IF(ISERROR(F29*Remuneración!$AP30),"",F29*Remuneración!$AP30)) -> 0 | I29: =IF(H29="",0,IF(ISERROR(H29*Remuneración!$AP30),"",H29*Remuneración!$AP30)) -> 0 | K29: =IF(J29="",0,IF(ISERROR(J29*Remuneración!$AP30),"",J29*Remuneración!$AP30)) -> 0 | M29: =IF(L29="",0,IF(ISERROR(L29*Remuneración!$AP30),"",L29*Remuneración!$AP30)) -> 0 | O29: =IF(N29="",0,IF(ISERROR(N29*$AE29),"",N29*$AE29)) -> 0 | Q29: =IF(P29="",0,IF(ISERROR(P29*$AE29),"",P29*$AE29)) -> 0 | S29: =IF(R29="",0,IF(ISERROR(R29*Remuneración!$AP30),"",R29*Remuneración!$AP30)) -> 0 | U29: =IF(T29="",0,IF(ISERROR(T29*Remuneración!$AP30),"",T29*Remuneración!$AP30)) -> 0 | W29: =IF(V29="",0,IF(ISERROR(V29*Remuneración!$AP30),"",V29*Remuneración!$AP30)) -> 0 | Y29: =IF(X29="",0,IF(ISERROR(X29*Remuneración!$AP30),"",X29*Remuneración!$AP30)) -> 0 | AC29: =+E29+G29+I29+K29+M29+O29+Q29+W29+Y29+S29+U29+SUM(Z29:AB29) -> 0 | AL29: =ROUNDUP(AN29,0)-AN29 -> 0 | AM29: =IF(SUM(AD29:AK29)=0,0,SUM(AD29:AK29)) -> 0 | AN29: =+AM29-AC29+Remuneración!AP30 -> 0 | AO29: =+AN29+AL29 -> 0
B30: =+Remuneración!B31 | C30: =+Remuneración!C31 | E30: =IF(D30="",0,IF(ISERROR(D30*Remuneración!$AP31),"",D30*Remuneración!$AP31)) -> 0 | G30: =IF(F30="",0,IF(ISERROR(F30*Remuneración!$AP31),"",F30*Remuneración!$AP31)) -> 0 | I30: =IF(H30="",0,IF(ISERROR(H30*Remuneración!$AP31),"",H30*Remuneración!$AP31)) -> 0 | K30: =IF(J30="",0,IF(ISERROR(J30*Remuneración!$AP31),"",J30*Remuneración!$AP31)) -> 0 | M30: =IF(L30="",0,IF(ISERROR(L30*Remuneración!$AP31),"",L30*Remuneración!$AP31)) -> 0 | O30: =IF(N30="",0,IF(ISERROR(N30*$AE30),"",N30*$AE30)) -> 0 | Q30: =IF(P30="",0,IF(ISERROR(P30*$AE30),"",P30*$AE30)) -> 0 | S30: =IF(R30="",0,IF(ISERROR(R30*Remuneración!$AP31),"",R30*Remuneración!$AP31)) -> 0 | U30: =IF(T30="",0,IF(ISERROR(T30*Remuneración!$AP31),"",T30*Remuneración!$AP31)) -> 0 | W30: =IF(V30="",0,IF(ISERROR(V30*Remuneración!$AP31),"",V30*Remuneración!$AP31)) -> 0 | Y30: =IF(X30="",0,IF(ISERROR(X30*Remuneración!$AP31),"",X30*Remuneración!$AP31)) -> 0 | AC30: =+E30+G30+I30+K30+M30+O30+Q30+W30+Y30+S30+U30+SUM(Z30:AB30) -> 0 | AL30: =ROUNDUP(AN30,0)-AN30 -> 0 | AM30: =IF(SUM(AD30:AK30)=0,0,SUM(AD30:AK30)) -> 0 | AN30: =+AM30-AC30+Remuneración!AP31 -> 0 | AO30: =+AN30+AL30 -> 0
B31: =+Remuneración!B32 | C31: =+Remuneración!C32 | E31: =IF(D31="",0,IF(ISERROR(D31*Remuneración!$AP32),"",D31*Remuneración!$AP32)) -> 0 | G31: =IF(F31="",0,IF(ISERROR(F31*Remuneración!$AP32),"",F31*Remuneración!$AP32)) -> 0 | I31: =IF(H31="",0,IF(ISERROR(H31*Remuneración!$AP32),"",H31*Remuneración!$AP32)) -> 0 | K31: =IF(J31="",0,IF(ISERROR(J31*Remuneración!$AP32),"",J31*Remuneración!$AP32)) -> 0 | M31: =IF(L31="",0,IF(ISERROR(L31*Remuneración!$AP32),"",L31*Remuneración!$AP32)) -> 0 | O31: =IF(N31="",0,IF(ISERROR(N31*$AE31),"",N31*$AE31)) -> 0 | Q31: =IF(P31="",0,IF(ISERROR(P31*$AE31),"",P31*$AE31)) -> 0 | S31: =IF(R31="",0,IF(ISERROR(R31*Remuneración!$AP32),"",R31*Remuneración!$AP32)) -> 0 | U31: =IF(T31="",0,IF(ISERROR(T31*Remuneración!$AP32),"",T31*Remuneración!$AP32)) -> 0 | W31: =IF(V31="",0,IF(ISERROR(V31*Remuneración!$AP32),"",V31*Remuneración!$AP32)) -> 0 | Y31: =IF(X31="",0,IF(ISERROR(X31*Remuneración!$AP32),"",X31*Remuneración!$AP32)) -> 0 | AC31: =+E31+G31+I31+K31+M31+O31+Q31+W31+Y31+S31+U31+SUM(Z31:AB31) -> 0 | AL31: =ROUNDUP(AN31,0)-AN31 -> 0 | AM31: =IF(SUM(AD31:AK31)=0,0,SUM(AD31:AK31)) -> 0 | AN31: =+AM31-AC31+Remuneración!AP32 -> 0 | AO31: =+AN31+AL31 -> 0
B32: =+Remuneración!B33 | C32: =+Remuneración!C33 | E32: =IF(D32="",0,IF(ISERROR(D32*Remuneración!$AP33),"",D32*Remuneración!$AP33)) -> 0 | G32: =IF(F32="",0,IF(ISERROR(F32*Remuneración!$AP33),"",F32*Remuneración!$AP33)) -> 0 | I32: =IF(H32="",0,IF(ISERROR(H32*Remuneración!$AP33),"",H32*Remuneración!$AP33)) -> 0 | K32: =IF(J32="",0,IF(ISERROR(J32*Remuneración!$AP33),"",J32*Remuneración!$AP33)) -> 0 | M32: =IF(L32="",0,IF(ISERROR(L32*Remuneración!$AP33),"",L32*Remuneración!$AP33)) -> 0 | O32: =IF(N32="",0,IF(ISERROR(N32*$AE32),"",N32*$AE32)) -> 0 | Q32: =IF(P32="",0,IF(ISERROR(P32*$AE32),"",P32*$AE32)) -> 0 | S32: =IF(R32="",0,IF(ISERROR(R32*Remuneración!$AP33),"",R32*Remuneración!$AP33)) -> 0 | U32: =IF(T32="",0,IF(ISERROR(T32*Remuneración!$AP33),"",T32*Remuneración!$AP33)) -> 0 | W32: =IF(V32="",0,IF(ISERROR(V32*Remuneración!$AP33),"",V32*Remuneración!$AP33)) -> 0 | Y32: =IF(X32="",0,IF(ISERROR(X32*Remuneración!$AP33),"",X32*Remuneración!$AP33)) -> 0 | AC32: =+E32+G32+I32+K32+M32+O32+Q32+W32+Y32+S32+U32+SUM(Z32:AB32) -> 0 | AL32: =ROUNDUP(AN32,0)-AN32 -> 0 | AM32: =IF(SUM(AD32:AK32)=0,0,SUM(AD32:AK32)) -> 0 | AN32: =+AM32-AC32+Remuneración!AP33 -> 0 | AO32: =+AN32+AL32 -> 0
B33: =+Remuneración!B34 | C33: =+Remuneración!C34 | E33: =IF(D33="",0,IF(ISERROR(D33*Remuneración!$AP34),"",D33*Remuneración!$AP34)) -> 0 | G33: =IF(F33="",0,IF(ISERROR(F33*Remuneración!$AP34),"",F33*Remuneración!$AP34)) -> 0 | I33: =IF(H33="",0,IF(ISERROR(H33*Remuneración!$AP34),"",H33*Remuneración!$AP34)) -> 0 | K33: =IF(J33="",0,IF(ISERROR(J33*Remuneración!$AP34),"",J33*Remuneración!$AP34)) -> 0 | M33: =IF(L33="",0,IF(ISERROR(L33*Remuneración!$AP34),"",L33*Remuneración!$AP34)) -> 0 | O33: =IF(N33="",0,IF(ISERROR(N33*$AE33),"",N33*$AE33)) -> 0 | Q33: =IF(P33="",0,IF(ISERROR(P33*$AE33),"",P33*$AE33)) -> 0 | S33: =IF(R33="",0,IF(ISERROR(R33*Remuneración!$AP34),"",R33*Remuneración!$AP34)) -> 0 | U33: =IF(T33="",0,IF(ISERROR(T33*Remuneración!$AP34),"",T33*Remuneración!$AP34)) -> 0 | W33: =IF(V33="",0,IF(ISERROR(V33*Remuneración!$AP34),"",V33*Remuneración!$AP34)) -> 0 | Y33: =IF(X33="",0,IF(ISERROR(X33*Remuneración!$AP34),"",X33*Remuneración!$AP34)) -> 0 | AC33: =+E33+G33+I33+K33+M33+O33+Q33+W33+Y33+S33+U33+SUM(Z33:AB33) -> 0 | AL33: =ROUNDUP(AN33,0)-AN33 -> 0 | AM33: =IF(SUM(AD33:AK33)=0,0,SUM(AD33:AK33)) -> 0 | AN33: =+AM33-AC33+Remuneración!AP34 -> 0 | AO33: =+AN33+AL33 -> 0
B34: =+Remuneración!B35 | C34: =+Remuneración!C35 | E34: =IF(D34="",0,IF(ISERROR(D34*Remuneración!$AP35),"",D34*Remuneración!$AP35)) -> 0 | G34: =IF(F34="",0,IF(ISERROR(F34*Remuneración!$AP35),"",F34*Remuneración!$AP35)) -> 0 | I34: =IF(H34="",0,IF(ISERROR(H34*Remuneración!$AP35),"",H34*Remuneración!$AP35)) -> 0 | K34: =IF(J34="",0,IF(ISERROR(J34*Remuneración!$AP35),"",J34*Remuneración!$AP35)) -> 0 | M34: =IF(L34="",0,IF(ISERROR(L34*Remuneración!$AP35),"",L34*Remuneración!$AP35)) -> 0 | O34: =IF(N34="",0,IF(ISERROR(N34*$AE34),"",N34*$AE34)) -> 0 | Q34: =IF(P34="",0,IF(ISERROR(P34*$AE34),"",P34*$AE34)) -> 0 | S34: =IF(R34="",0,IF(ISERROR(R34*Remuneración!$AP35),"",R34*Remuneración!$AP35)) -> 0 | U34: =IF(T34="",0,IF(ISERROR(T34*Remuneración!$AP35),"",T34*Remuneración!$AP35)) -> 0 | W34: =IF(V34="",0,IF(ISERROR(V34*Remuneración!$AP35),"",V34*Remuneración!$AP35)) -> 0 | Y34: =IF(X34="",0,IF(ISERROR(X34*Remuneración!$AP35),"",X34*Remuneración!$AP35)) -> 0 | AC34: =+E34+G34+I34+K34+M34+O34+Q34+W34+Y34+S34+U34+SUM(Z34:AB34) -> 0 | AL34: =ROUNDUP(AN34,0)-AN34 -> 0 | AM34: =IF(SUM(AD34:AK34)=0,0,SUM(AD34:AK34)) -> 0 | AN34: =+AM34-AC34+Remuneración!AP35 -> 0 | AO34: =+AN34+AL34 -> 0
B35: =+Remuneración!B36 | C35: =+Remuneración!C36 | E35: =IF(D35="",0,IF(ISERROR(D35*Remuneración!$AP36),"",D35*Remuneración!$AP36)) -> 0 | G35: =IF(F35="",0,IF(ISERROR(F35*Remuneración!$AP36),"",F35*Remuneración!$AP36)) -> 0 | I35: =IF(H35="",0,IF(ISERROR(H35*Remuneración!$AP36),"",H35*Remuneración!$AP36)) -> 0 | K35: =IF(J35="",0,IF(ISERROR(J35*Remuneración!$AP36),"",J35*Remuneración!$AP36)) -> 0 | M35: =IF(L35="",0,IF(ISERROR(L35*Remuneración!$AP36),"",L35*Remuneración!$AP36)) -> 0 | O35: =IF(N35="",0,IF(ISERROR(N35*$AE35),"",N35*$AE35)) -> 0 | Q35: =IF(P35="",0,IF(ISERROR(P35*$AE35),"",P35*$AE35)) -> 0 | S35: =IF(R35="",0,IF(ISERROR(R35*Remuneración!$AP36),"",R35*Remuneración!$AP36)) -> 0 | U35: =IF(T35="",0,IF(ISERROR(T35*Remuneración!$AP36),"",T35*Remuneración!$AP36)) -> 0 | W35: =IF(V35="",0,IF(ISERROR(V35*Remuneración!$AP36),"",V35*Remuneración!$AP36)) -> 0 | Y35: =IF(X35="",0,IF(ISERROR(X35*Remuneración!$AP36),"",X35*Remuneración!$AP36)) -> 0 | AC35: =+E35+G35+I35+K35+M35+O35+Q35+W35+Y35+S35+U35+SUM(Z35:AB35) -> 0 | AL35: =ROUNDUP(AN35,0)-AN35 -> 0 | AM35: =IF(SUM(AD35:AK35)=0,0,SUM(AD35:AK35)) -> 0 | AN35: =+AM35-AC35+Remuneración!AP36 -> 0 | AO35: =+AN35+AL35 -> 0
B36: =+Remuneración!B37 | C36: =+Remuneración!C37 | E36: =IF(D36="",0,IF(ISERROR(D36*Remuneración!$AP37),"",D36*Remuneración!$AP37)) -> 0 | G36: =IF(F36="",0,IF(ISERROR(F36*Remuneración!$AP37),"",F36*Remuneración!$AP37)) -> 0 | I36: =IF(H36="",0,IF(ISERROR(H36*Remuneración!$AP37),"",H36*Remuneración!$AP37)) -> 0 | K36: =IF(J36="",0,IF(ISERROR(J36*Remuneración!$AP37),"",J36*Remuneración!$AP37)) -> 0 | M36: =IF(L36="",0,IF(ISERROR(L36*Remuneración!$AP37),"",L36*Remuneración!$AP37)) -> 0 | O36: =IF(N36="",0,IF(ISERROR(N36*$AE36),"",N36*$AE36)) -> 0 | Q36: =IF(P36="",0,IF(ISERROR(P36*$AE36),"",P36*$AE36)) -> 0 | S36: =IF(R36="",0,IF(ISERROR(R36*Remuneración!$AP37),"",R36*Remuneración!$AP37)) -> 0 | U36: =IF(T36="",0,IF(ISERROR(T36*Remuneración!$AP37),"",T36*Remuneración!$AP37)) -> 0 | W36: =IF(V36="",0,IF(ISERROR(V36*Remuneración!$AP37),"",V36*Remuneración!$AP37)) -> 0 | Y36: =IF(X36="",0,IF(ISERROR(X36*Remuneración!$AP37),"",X36*Remuneración!$AP37)) -> 0 | AC36: =+E36+G36+I36+K36+M36+O36+Q36+W36+Y36+S36+U36+SUM(Z36:AB36) -> 0 | AL36: =ROUNDUP(AN36,0)-AN36 -> 0 | AM36: =IF(SUM(AD36:AK36)=0,0,SUM(AD36:AK36)) -> 0 | AN36: =+AM36-AC36+Remuneración!AP37 -> 0 | AO36: =+AN36+AL36 -> 0
B37: =+Remuneración!B38 | C37: =+Remuneración!C38 | E37: =IF(D37="",0,IF(ISERROR(D37*Remuneración!$AP38),"",D37*Remuneración!$AP38)) -> 0 | G37: =IF(F37="",0,IF(ISERROR(F37*Remuneración!$AP38),"",F37*Remuneración!$AP38)) -> 0 | I37: =IF(H37="",0,IF(ISERROR(H37*Remuneración!$AP38),"",H37*Remuneración!$AP38)) -> 0 | K37: =IF(J37="",0,IF(ISERROR(J37*Remuneración!$AP38),"",J37*Remuneración!$AP38)) -> 0 | M37: =IF(L37="",0,IF(ISERROR(L37*Remuneración!$AP38),"",L37*Remuneración!$AP38)) -> 0 | O37: =IF(N37="",0,IF(ISERROR(N37*$AE37),"",N37*$AE37)) -> 0 | Q37: =IF(P37="",0,IF(ISERROR(P37*$AE37),"",P37*$AE37)) -> 0 | S37: =IF(R37="",0,IF(ISERROR(R37*Remuneración!$AP38),"",R37*Remuneración!$AP38)) -> 0 | U37: =IF(T37="",0,IF(ISERROR(T37*Remuneración!$AP38),"",T37*Remuneración!$AP38)) -> 0 | W37: =IF(V37="",0,IF(ISERROR(V37*Remuneración!$AP38),"",V37*Remuneración!$AP38)) -> 0 | Y37: =IF(X37="",0,IF(ISERROR(X37*Remuneración!$AP38),"",X37*Remuneración!$AP38)) -> 0 | AC37: =+E37+G37+I37+K37+M37+O37+Q37+W37+Y37+S37+U37+SUM(Z37:AB37) -> 0 | AL37: =ROUNDUP(AN37,0)-AN37 -> 0 | AM37: =IF(SUM(AD37:AK37)=0,0,SUM(AD37:AK37)) -> 0 | AN37: =+AM37-AC37+Remuneración!AP38 -> 0 | AO37: =+AN37+AL37 -> 0
B38: =+Remuneración!B39 | C38: =+Remuneración!C39 | E38: =IF(D38="",0,IF(ISERROR(D38*Remuneración!$AP39),"",D38*Remuneración!$AP39)) -> 0 | G38: =IF(F38="",0,IF(ISERROR(F38*Remuneración!$AP39),"",F38*Remuneración!$AP39)) -> 0 | I38: =IF(H38="",0,IF(ISERROR(H38*Remuneración!$AP39),"",H38*Remuneración!$AP39)) -> 0 | K38: =IF(J38="",0,IF(ISERROR(J38*Remuneración!$AP39),"",J38*Remuneración!$AP39)) -> 0 | M38: =IF(L38="",0,IF(ISERROR(L38*Remuneración!$AP39),"",L38*Remuneración!$AP39)) -> 0 | O38: =IF(N38="",0,IF(ISERROR(N38*$AE38),"",N38*$AE38)) -> 0 | Q38: =IF(P38="",0,IF(ISERROR(P38*$AE38),"",P38*$AE38)) -> 0 | S38: =IF(R38="",0,IF(ISERROR(R38*Remuneración!$AP39),"",R38*Remuneración!$AP39)) -> 0 | U38: =IF(T38="",0,IF(ISERROR(T38*Remuneración!$AP39),"",T38*Remuneración!$AP39)) -> 0 | W38: =IF(V38="",0,IF(ISERROR(V38*Remuneración!$AP39),"",V38*Remuneración!$AP39)) -> 0 | Y38: =IF(X38="",0,IF(ISERROR(X38*Remuneración!$AP39),"",X38*Remuneración!$AP39)) -> 0 | AC38: =+E38+G38+I38+K38+M38+O38+Q38+W38+Y38+S38+U38+SUM(Z38:AB38) -> 0 | AL38: =ROUNDUP(AN38,0)-AN38 -> 0 | AM38: =IF(SUM(AD38:AK38)=0,0,SUM(AD38:AK38)) -> 0 | AN38: =+AM38-AC38+Remuneración!AP39 -> 0 | AO38: =+AN38+AL38 -> 0
B39: =+Remuneración!B40 | C39: =+Remuneración!C40 | E39: =IF(D39="",0,IF(ISERROR(D39*Remuneración!$AP40),"",D39*Remuneración!$AP40)) -> 0 | G39: =IF(F39="",0,IF(ISERROR(F39*Remuneración!$AP40),"",F39*Remuneración!$AP40)) -> 0 | I39: =IF(H39="",0,IF(ISERROR(H39*Remuneración!$AP40),"",H39*Remuneración!$AP40)) -> 0 | K39: =IF(J39="",0,IF(ISERROR(J39*Remuneración!$AP40),"",J39*Remuneración!$AP40)) -> 0 | M39: =IF(L39="",0,IF(ISERROR(L39*Remuneración!$AP40),"",L39*Remuneración!$AP40)) -> 0 | O39: =IF(N39="",0,IF(ISERROR(N39*$AE39),"",N39*$AE39)) -> 0 | Q39: =IF(P39="",0,IF(ISERROR(P39*$AE39),"",P39*$AE39)) -> 0 | S39: =IF(R39="",0,IF(ISERROR(R39*Remuneración!$AP40),"",R39*Remuneración!$AP40)) -> 0 | U39: =IF(T39="",0,IF(ISERROR(T39*Remuneración!$AP40),"",T39*Remuneración!$AP40)) -> 0 | W39: =IF(V39="",0,IF(ISERROR(V39*Remuneración!$AP40),"",V39*Remuneración!$AP40)) -> 0 | Y39: =IF(X39="",0,IF(ISERROR(X39*Remuneración!$AP40),"",X39*Remuneración!$AP40)) -> 0 | AC39: =+E39+G39+I39+K39+M39+O39+Q39+W39+Y39+S39+U39+SUM(Z39:AB39) -> 0 | AL39: =ROUNDUP(AN39,0)-AN39 -> 0 | AM39: =IF(SUM(AD39:AK39)=0,0,SUM(AD39:AK39)) -> 0 | AN39: =+AM39-AC39+Remuneración!AP40 -> 0 | AO39: =+AN39+AL39 -> 0
... B55: =+Remuneración!B56 | C55: =+Remuneración!C56 | E55: =IF(D55="",0,IF(ISERROR(D55*Remuneración!$AP56),"",D55*Remuneración!$AP56)) -> 0 | G55: =IF(F55="",0,IF(ISERROR(F55*Remuneración!$AP56),"",F55*Remuneración!$AP56)) -> 0 | I55: =IF(H55="",0,IF(ISERROR(H55*Remuneración!$AP56),"",H55*Remuneración!$AP56)) -> 0 | K55: =IF(J55="",0,IF(ISERROR(J55*Remuneración!$AP56),"",J55*Remuneración!$AP56)) -> 0 | M55: =IF(L55="",0,IF(ISERROR(L55*Remuneración!$AP56),"",L55*Remuneración!$AP56)) -> 0 | O55: =IF(N55="",0,IF(ISERROR(N55*$AE55),"",N55*$AE55)) -> 0 | Q55: =IF(P55="",0,IF(ISERROR(P55*$AE55),"",P55*$AE55)) -> 0 | S55: =IF(R55="",0,IF(ISERROR(R55*Remuneración!$AP56),"",R55*Remuneración!$AP56)) -> 0 | U55: =IF(T55="",0,IF(ISERROR(T55*Remuneración!$AP56),"",T55*Remuneración!$AP56)) -> 0 | W55: =IF(V55="",0,IF(ISERROR(V55*Remuneración!$AP56),"",V55*Remuneración!$AP56)) -> 0 | Y55: =IF(X55="",0,IF(ISERROR(X55*Remuneración!$AP56),"",X55*Remuneración!$AP56)) -> 0 | AC55: =+E55+G55+I55+K55+M55+O55+Q55+W55+Y55+S55+U55+SUM(Z55:AB55) -> 0 | AL55: =ROUNDUP(AN55,0)-AN55 -> 0 | AM55: =IF(SUM(AD55:AK55)=0,0,SUM(AD55:AK55)) -> 0 | AN55: =+AM55-AC55+Remuneración!AP56 -> 0 | AO55: =+AN55+AL55 -> 0
B56: =+Remuneración!B58 | C56: =+Remuneración!C58 | E56: =IF(D56="",0,IF(ISERROR(D56*Remuneración!$AP58),"",D56*Remuneración!$AP58)) -> 0 | G56: =IF(F56="",0,IF(ISERROR(F56*Remuneración!$AP58),"",F56*Remuneración!$AP58)) -> 0 | I56: =IF(H56="",0,IF(ISERROR(H56*Remuneración!$AP58),"",H56*Remuneración!$AP58)) -> 0 | K56: =IF(J56="",0,IF(ISERROR(J56*Remuneración!$AP58),"",J56*Remuneración!$AP58)) -> 0 | M56: =IF(L56="",0,IF(ISERROR(L56*Remuneración!$AP58),"",L56*Remuneración!$AP58)) -> 0 | O56: =IF(N56="",0,IF(ISERROR(N56*$AE56),"",N56*$AE56)) -> 0 | Q56: =IF(P56="",0,IF(ISERROR(P56*$AE56),"",P56*$AE56)) -> 0 | S56: =IF(R56="",0,IF(ISERROR(R56*Remuneración!$AP58),"",R56*Remuneración!$AP58)) -> 0 | U56: =IF(T56="",0,IF(ISERROR(T56*Remuneración!$AP58),"",T56*Remuneración!$AP58)) -> 0 | W56: =IF(V56="",0,IF(ISERROR(V56*Remuneración!$AP58),"",V56*Remuneración!$AP58)) -> 0 | Y56: =IF(X56="",0,IF(ISERROR(X56*Remuneración!$AP58),"",X56*Remuneración!$AP58)) -> 0 | AC56: =+E56+G56+I56+K56+M56+O56+Q56+W56+Y56+S56+U56+SUM(Z56:AB56) -> 0 | AL56: =ROUNDUP(AN56,0)-AN56 -> 0 | AM56: =IF(SUM(AD56:AK56)=0,0,SUM(AD56:AK56)) -> 0 | AN56: =+AM56-AC56+Remuneración!AP58 -> 0 | AO56: =+AN56+AL56 -> 0

Sheet Ret. VAV y SAC
E2: Retenciones y no Remunerativos
B3: 1 | C3: 2 | D3: 3 | E3: 4 | F3: 5 | G3: 6 | H3: 7 | I3: 8 | J3: 9 | K3: 10 | L3: 11 | M3: 12 | N3: 17 | O3: 18 | P3: 19 | Q3: 20 | R3: 21 | S3: 22 | T3: 23 | U3: 24 | V3: 25
D5: Jubilación | F5: Ley 19032 | H5: Obra Social | J5: Adherente Os | L5: Sindicato | N5: a1 | P5: a2 | R5: a3 | T5: a4
B6: Leg. | C6: Nombre Competo | D6: % | E6: Importe | F6: % | G6: Importe | H6: % | I6: Importe | J6: % | K6: Importe | L6: % | M6: Importe | N6: % | O6: Importe | P6: % | Q6: Importe | R6: % | S6: Importe | T6: % | U6: Importe | V6: Subtotal Descuentos | W6: Sueldo Total
B7: =+Remuneración!B8 -> 1 | C7: =+Remuneración!C8 -> ARANIBAR CLAUDIA CRISTINA | D7: =+'Ret. y no Rem.'!D7 -> 0.11 | E7: =D7*(Remuneración!$AL8+Remuneración!$AN8) -> 0 | F7: =+'Ret. y no Rem.'!F7 -> 0.03 | G7: =F7*(Remuneración!$AL8+Remuneración!$AN8) -> 0 | H7: =+'Ret. y no Rem.'!H7 -> 0.03 | I7: =H7*(Remuneración!$AL8+Remuneración!$AN8) -> 0 | J7: =+'Ret. y no Rem.'!J7 -> 0 | K7: =J7*(Remuneración!$AL8+Remuneración!$AN8) -> 0 | L7: =+'Ret. y no Rem.'!L7 -> 0 | M7: =L7*(Remuneración!$AL8+Remuneración!$AN8) -> 0 | N7: ='Ret. y no Rem.'!R7 -> 0.005 | O7: =N7*(Remuneración!$AL8+Remuneración!$AN8) -> 0 | P7: ='Ret. y no Rem.'!T7 -> 0 | Q7: =P7*(Remuneración!$AL8+Remuneración!$AN8) -> 0 | R7: ='Ret. y no Rem.'!V7 -> 0 | S7: =R7*(Remuneración!$AL8+Remuneración!$AN8) -> 0 | T7: ='Ret. y no Rem.'!X7 -> 0 | U7: =T7*(Remuneración!$AL8+Remuneración!$AN8) -> 0 | V7: =+E7+G7+I7+K7+M7+S7+U7+O7+Q7 -> 0 | W7: =+#REF!-V7+Remuneración!AP8 -> #REF!
B8: =+Remuneración!B9 -> 2 | C8: =+Remuneración!C9 -> QUIROGA VANINA LEONELA | D8: =+'Ret. y no Rem.'!D8 -> 0.11 | E8: =D8*(Remuneración!$AL9+Remuneración!$AN9) -> 0 | F8: =+'Ret. y no Rem.'!F8 -> 0.03 | G8: =F8*(Remuneración!$AL9+Remuneración!$AN9) -> 0 | H8: =+'Ret. y no Rem.'!H8 -> 0.03 | I8: =H8*(Remuneración!$AL9+Remuneración!$AN9) -> 0 | J8: =+'Ret. y no Rem.'!J8 -> 0 | K8: =J8*(Remuneración!$AL9+Remuneración!$AN9) -> 0 | L8: =+'Ret. y no Rem.'!L8 -> 0 | M8: =L8*(Remuneración!$AL9+Remuneración!$AN9) -> 0 | N8: ='Ret. y no Rem.'!R8 -> 0 | O8: =N8*(Remuneración!$AL9+Remuneración!$AN9) -> 0 | P8: ='Ret. y no Rem.'!T8 -> 0 | Q8: =P8*(Remuneración!$AL9+Remuneración!$AN9) -> 0 | R8: ='Ret. y no Rem.'!V8 -> 0 | S8: =R8*(Remuneración!$AL9+Remuneración!$AN9) -> 0 | T8: ='Ret. y no Rem.'!X8 -> 0 | U8: =T8*(Remuneración!$AL9+Remuneración!$AN9) -> 0 | V8: =+E8+G8+I8+K8+M8+S8+U8+O8+Q8 -> 0 | W8: =+#REF!-V8+Remuneración!AP9 -> #REF!
B9: =+Remuneración!B10 | C9: =+Remuneración!C10 | D9: =+'Ret. y no Rem.'!D9 -> 0 | E9: =D9*(Remuneración!$AL10+Remuneración!$AN10) -> 0 | F9: =+'Ret. y no Rem.'!F9 -> 0 | G9: =F9*(Remuneración!$AL10+Remuneración!$AN10) -> 0 | H9: =+'Ret. y no Rem.'!H9 -> 0 | I9: =H9*(Remuneración!$AL10+Remuneración!$AN10) -> 0 | J9: =+'Ret. y no Rem.'!J9 -> 0 | K9: =J9*(Remuneración!$AL10+Remuneración!$AN10) -> 0 | L9: =+'Ret. y no Rem.'!L9 -> 0 | M9: =L9*(Remuneración!$AL10+Remuneración!$AN10) -> 0 | N9: ='Ret. y no Rem.'!R9 -> 0 | O9: =N9*(Remuneración!$AL10+Remuneración!$AN10) -> 0 | P9: ='Ret. y no Rem.'!T9 -> 0 | Q9: =P9*(Remuneración!$AL10+Remuneración!$AN10) -> 0 | R9: ='Ret. y no Rem.'!V9 -> 0 | S9: =R9*(Remuneración!$AL10+Remuneración!$AN10) -> 0 | T9: ='Ret. y no Rem.'!X9 -> 0 | U9: =T9*(Remuneración!$AL10+Remuneración!$AN10) -> 0 | V9: =+E9+G9+I9+K9+M9+S9+U9+O9+Q9 -> 0 | W9: =+#REF!-V9+Remuneración!AP10 -> #REF!
B10: =+Remuneración!B11 | C10: =+Remuneración!C11 | D10: =+'Ret. y no Rem.'!D10 -> 0 | E10: =D10*(Remuneración!$AL11+Remuneración!$AN11) -> 0 | F10: =+'Ret. y no Rem.'!F10 -> 0 | G10: =F10*(Remuneración!$AL11+Remuneración!$AN11) -> 0 | H10: =+'Ret. y no Rem.'!H10 -> 0 | I10: =H10*(Remuneración!$AL11+Remuneración!$AN11) -> 0 | J10: =+'Ret. y no Rem.'!J10 -> 0 | K10: =J10*(Remuneración!$AL11+Remuneración!$AN11) -> 0 | L10: =+'Ret. y no Rem.'!L10 -> 0 | M10: =L10*(Remuneración!$AL11+Remuneración!$AN11) -> 0 | N10: ='Ret. y no Rem.'!R10 -> 0 | O10: =N10*(Remuneración!$AL11+Remuneración!$AN11) -> 0 | P10: ='Ret. y no Rem.'!T10 -> 0 | Q10: =P10*(Remuneración!$AL11+Remuneración!$AN11) -> 0 | R10: ='Ret. y no Rem.'!V10 -> 0 | S10: =R10*(Remuneración!$AL11+Remuneración!$AN11) -> 0 | T10: ='Ret. y no Rem.'!X10 -> 0 | U10: =T10*(Remuneración!$AL11+Remuneración!$AN11) -> 0 | V10: =+E10+G10+I10+K10+M10+S10+U10+O10+Q10 -> 0 | W10: =+#REF!-V10+Remuneración!AP11 -> #REF!
B11: =+Remuneración!B12 | C11: =+Remuneración!C12 | D11: =+'Ret. y no Rem.'!D11 -> 0 | E11: =D11*(Remuneración!$AL12+Remuneración!$AN12) -> 0 | F11: =+'Ret. y no Rem.'!F11 -> 0 | G11: =F11*(Remuneración!$AL12+Remuneración!$AN12) -> 0 | H11: =+'Ret. y no Rem.'!H11 -> 0 | I11: =H11*(Remuneración!$AL12+Remuneración!$AN12) -> 0 | J11: =+'Ret. y no Rem.'!J11 -> 0 | K11: =J11*(Remuneración!$AL12+Remuneración!$AN12) -> 0 | L11: =+'Ret. y no Rem.'!L11 -> 0 | M11: =L11*(Remuneración!$AL12+Remuneración!$AN12) -> 0 | N11: ='Ret. y no Rem.'!R11 -> 0 | O11: =N11*(Remuneración!$AL12+Remuneración!$AN12) -> 0 | P11: ='Ret. y no Rem.'!T11 -> 0 | Q11: =P11*(Remuneración!$AL12+Remuneración!$AN12) -> 0 | R11: ='Ret. y no Rem.'!V11 -> 0 | S11: =R11*(Remuneración!$AL12+Remuneración!$AN12) -> 0 | T11: ='Ret. y no Rem.'!X11 -> 0 | U11: =T11*(Remuneración!$AL12+Remuneración!$AN12) -> 0 | V11: =+E11+G11+I11+K11+M11+S11+U11+O11+Q11 -> 0 | W11: =+#REF!-V11+Remuneración!AP12 -> #REF!
B12: =+Remuneración!B13 | C12: =+Remuneración!C13 | D12: =+'Ret. y no Rem.'!D12 -> 0 | E12: =D12*(Remuneración!$AL13+Remuneración!$AN13) -> 0 | F12: =+'Ret. y no Rem.'!F12 -> 0 | G12: =F12*(Remuneración!$AL13+Remuneración!$AN13) -> 0 | H12: =+'Ret. y no Rem.'!H12 -> 0 | I12: =H12*(Remuneración!$AL13+Remuneración!$AN13) -> 0 | J12: =+'Ret. y no Rem.'!J12 -> 0 | K12: =J12*(Remuneración!$AL13+Remuneración!$AN13) -> 0 | L12: =+'Ret. y no Rem.'!L12 -> 0 | M12: =L12*(Remuneración!$AL13+Remuneración!$AN13) -> 0 | N12: ='Ret. y no Rem.'!R12 -> 0 | O12: =N12*(Remuneración!$AL13+Remuneración!$AN13) -> 0 | P12: ='Ret. y no Rem.'!T12 -> 0 | Q12: =P12*(Remuneración!$AL13+Remuneración!$AN13) -> 0 | R12: ='Ret. y no Rem.'!V12 -> 0 | S12: =R12*(Remuneración!$AL13+Remuneración!$AN13) -> 0 | T12: ='Ret. y no Rem.'!X12 -> 0 | U12: =T12*(Remuneración!$AL13+Remuneración!$AN13) -> 0 | V12: =+E12+G12+I12+K12+M12+S12+U12+O12+Q12 -> 0 | W12: =+#REF!-V12+Remuneración!AP13 -> #REF!
B13: =+Remuneración!B14 | C13: =+Remuneración!C14 | D13: =+'Ret. y no Rem.'!D13 -> 0 | E13: =D13*(Remuneración!$AL14+Remuneración!$AN14) -> 0 | F13: =+'Ret. y no Rem.'!F13 -> 0 | G13: =F13*(Remuneración!$AL14+Remuneración!$AN14) -> 0 | H13: =+'Ret. y no Rem.'!H13 -> 0 | I13: =H13*(Remuneración!$AL14+Remuneración!$AN14) -> 0 | J13: =+'Ret. y no Rem.'!J13 -> 0 | K13: =J13*(Remuneración!$AL14+Remuneración!$AN14) -> 0 | L13: =+'Ret. y no Rem.'!L13 -> 0 | M13: =L13*(Remuneración!$AL14+Remuneración!$AN14) -> 0 | N13: ='Ret. y no Rem.'!R13 -> 0 | O13: =N13*(Remuneración!$AL14+Remuneración!$AN14) -> 0 | P13: ='Ret. y no Rem.'!T13 -> 0 | Q13: =P13*(Remuneración!$AL14+Remuneración!$AN14) -> 0 | R13: ='Ret. y no Rem.'!V13 -> 0 | S13: =R13*(Remuneración!$AL14+Remuneración!$AN14) -> 0 | T13: ='Ret. y no Rem.'!X13 -> 0 | U13: =T13*(Remuneración!$AL14+Remuneración!$AN14) -> 0 | V13: =+E13+G13+I13+K13+M13+S13+U13+O13+Q13 -> 0 | W13: =+#REF!-V13+Remuneración!AP14 -> #REF!
B14: =+Remuneración!B15 | C14: =+Remuneración!C15 | D14: =+'Ret. y no Rem.'!D14 -> 0 | E14: =D14*(Remuneración!$AL15+Remuneración!$AN15) -> 0 | F14: =+'Ret. y no Rem.'!F14 -> 0 | G14: =F14*(Remuneración!$AL15+Remuneración!$AN15) -> 0 | H14: =+'Ret. y no Rem.'!H14 -> 0 | I14: =H14*(Remuneración!$AL15+Remuneración!$AN15) -> 0 | J14: =+'Ret. y no Rem.'!J14 -> 0 | K14: =J14*(Remuneración!$AL15+Remuneración!$AN15) -> 0 | L14: =+'Ret. y no Rem.'!L14 -> 0 | M14: =L14*(Remuneración!$AL15+Remuneración!$AN15) -> 0 | N14: ='Ret. y no Rem.'!R14 -> 0 | O14: =N14*(Remuneración!$AL15+Remuneración!$AN15) -> 0 | P14: ='Ret. y no Rem.'!T14 -> 0 | Q14: =P14*(Remuneración!$AL15+Remuneración!$AN15) -> 0 | R14: ='Ret. y no Rem.'!V14 -> 0 | S14: =R14*(Remuneración!$AL15+Remuneración!$AN15) -> 0 | T14: ='Ret. y no Rem.'!X14 -> 0 | U14: =T14*(Remuneración!$AL15+Remuneración!$AN15) -> 0 | V14: =+E14+G14+I14+K14+M14+S14+U14+O14+Q14 -> 0 | W14: =+#REF!-V14+Remuneración!AP15 -> #REF!
B15: =+Remuneración!B16 | C15: =+Remuneración!C16 | D15: =+'Ret. y no Rem.'!D15 -> 0 | E15: =D15*(Remuneración!$AL16+Remuneración!$AN16) -> 0 | F15: =+'Ret. y no Rem.'!F15 -> 0 | G15: =F15*(Remuneración!$AL16+Remuneración!$AN16) -> 0 | H15: =+'Ret. y no Rem.'!H15 -> 0 | I15: =H15*(Remuneración!$AL16+Remuneración!$AN16) -> 0 | J15: =+'Ret. y no Rem.'!J15 -> 0 | K15: =J15*(Remuneración!$AL16+Remuneración!$AN16) -> 0 | L15: =+'Ret. y no Rem.'!L15 -> 0 | M15: =L15*(Remuneración!$AL16+Remuneración!$AN16) -> 0 | N15: ='Ret. y no Rem.'!R15 -> 0 | O15: =N15*(Remuneración!$AL16+Remuneración!$AN16) -> 0 | P15: ='Ret. y no Rem.'!T15 -> 0 | Q15: =P15*(Remuneración!$AL16+Remuneración!$AN16) -> 0 | R15: ='Ret. y no Rem.'!V15 -> 0 | S15: =R15*(Remuneración!$AL16+Remuneración!$AN16) -> 0 | T15: ='Ret. y no Rem.'!X15 -> 0 | U15: =T15*(Remuneración!$AL16+Remuneración!$AN16) -> 0 | V15: =+E15+G15+I15+K15+M15+S15+U15+O15+Q15 -> 0 | W15: =+#REF!-V15+Remuneración!AP16 -> #REF!
B16: =+Remuneración!B17 | C16: =+Remuneración!C17 | D16: =+'Ret. y no Rem.'!D16 -> 0 | E16: =D16*(Remuneración!$AL17+Remuneración!$AN17) -> 0 | F16: =+'Ret. y no Rem.'!F16 -> 0 | G16: =F16*(Remuneración!$AL17+Remuneración!$AN17) -> 0 | H16: =+'Ret. y no Rem.'!H16 -> 0 | I16: =H16*(Remuneración!$AL17+Remuneración!$AN17) -> 0 | J16: =+'Ret. y no Rem.'!J16 -> 0 | K16: =J16*(Remuneración!$AL17+Remuneración!$AN17) -> 0 | L16: =+'Ret. y no Rem.'!L16 -> 0 | M16: =L16*(Remuneración!$AL17+Remuneración!$AN17) -> 0 | N16: ='Ret. y no Rem.'!R16 -> 0 | O16: =N16*(Remuneración!$AL17+Remuneración!$AN17) -> 0 | P16: ='Ret. y no Rem.'!T16 -> 0 | Q16: =P16*(Remuneración!$AL17+Remuneración!$AN17) -> 0 | R16: ='Ret. y no Rem.'!V16 -> 0 | S16: =R16*(Remuneración!$AL17+Remuneración!$AN17) -> 0 | T16: ='Ret. y no Rem.'!X16 -> 0 | U16: =T16*(Remuneración!$AL17+Remuneración!$AN17) -> 0 | V16: =+E16+G16+I16+K16+M16+S16+U16+O16+Q16 -> 0 | W16: =+#REF!-V16+Remuneración!AP17 -> #REF!
B17: =+Remuneración!B18 | C17: =+Remuneración!C18 | D17: =+'Ret. y no Rem.'!D17 -> 0 | E17: =D17*(Remuneración!$AL18+Remuneración!$AN18) -> 0 | F17: =+'Ret. y no Rem.'!F17 -> 0 | G17: =F17*(Remuneración!$AL18+Remuneración!$AN18) -> 0 | H17: =+'Ret. y no Rem.'!H17 -> 0 | I17: =H17*(Remuneración!$AL18+Remuneración!$AN18) -> 0 | J17: =+'Ret. y no Rem.'!J17 -> 0 | K17: =J17*(Remuneración!$AL18+Remuneración!$AN18) -> 0 | L17: =+'Ret. y no Rem.'!L17 -> 0 | M17: =L17*(Remuneración!$AL18+Remuneración!$AN18) -> 0 | N17: ='Ret. y no Rem.'!R17 -> 0 | O17: =N17*(Remuneración!$AL18+Remuneración!$AN18) -> 0 | P17: ='Ret. y no Rem.'!T17 -> 0 | Q17: =P17*(Remuneración!$AL18+Remuneración!$AN18) -> 0 | R17: ='Ret. y no Rem.'!V17 -> 0 | S17: =R17*(Remuneración!$AL18+Remuneración!$AN18) -> 0 | T17: ='Ret. y no Rem.'!X17 -> 0 | U17: =T17*(Remuneración!$AL18+Remuneración!$AN18) -> 0 | V17: =+E17+G17+I17+K17+M17+S17+U17+O17+Q17 -> 0 | W17: =+#REF!-V17+Remuneración!AP18 -> #REF!
B18: =+Remuneración!B19 | C18: =+Remuneración!C19 | D18: =+'Ret. y no Rem.'!D18 -> 0 | E18: =D18*(Remuneración!$AL19+Remuneración!$AN19) -> 0 | F18: =+'Ret. y no Rem.'!F18 -> 0 | G18: =F18*(Remuneración!$AL19+Remuneración!$AN19) -> 0 | H18: =+'Ret. y no Rem.'!H18 -> 0 | I18: =H18*(Remuneración!$AL19+Remuneración!$AN19) -> 0 | J18: =+'Ret. y no Rem.'!J18 -> 0 | K18: =J18*(Remuneración!$AL19+Remuneración!$AN19) -> 0 | L18: =+'Ret. y no Rem.'!L18 -> 0 | M18: =L18*(Remuneración!$AL19+Remuneración!$AN19) -> 0 | N18: ='Ret. y no Rem.'!R18 -> 0 | O18: =N18*(Remuneración!$AL19+Remuneración!$AN19) -> 0 | P18: ='Ret. y no Rem.'!T18 -> 0 | Q18: =P18*(Remuneración!$AL19+Remuneración!$AN19) -> 0 | R18: ='Ret. y no Rem.'!V18 -> 0 | S18: =R18*(Remuneración!$AL19+Remuneración!$AN19) -> 0 | T18: ='Ret. y no Rem.'!X18 -> 0 | U18: =T18*(Remuneración!$AL19+Remuneración!$AN19) -> 0 | V18: =+E18+G18+I18+K18+M18+S18+U18+O18+Q18 -> 0 | W18: =+#REF!-V18+Remuneración!AP19 -> #REF!
... B55: =+Remuneración!B56 | C55: =+Remuneración!C56 | D55: =+'Ret. y no Rem.'!D55 -> 0 | E55: =D55*(Remuneración!$AL56+Remuneración!$AN56) -> 0 | F55: =+'Ret. y no Rem.'!F55 -> 0 | G55: =F55*(Remuneración!$AL56+Remuneración!$AN56) -> 0 | H55: =+'Ret. y no Rem.'!H55 -> 0 | I55: =H55*(Remuneración!$AL56+Remuneración!$AN56) -> 0 | J55: =+'Ret. y no Rem.'!J55 -> 0 | K55: =J55*(Remuneración!$AL56+Remuneración!$AN56) -> 0 | L55: =+'Ret. y no Rem.'!L55 -> 0 | M55: =L55*(Remuneración!$AL56+Remuneración!$AN56) -> 0 | N55: ='Ret. y no Rem.'!R55 -> 0 | O55: =N55*(Remuneración!$AL56+Remuneración!$AN56) -> 0 | P55: ='Ret. y no Rem.'!T55 -> 0 | Q55: =P55*(Remuneración!$AL56+Remuneración!$AN56) -> 0 | R55: ='Ret. y no Rem.'!V55 -> 0 | S55: =R55*(Remuneración!$AL56+Remuneración!$AN56) -> 0 | T55: ='Ret. y no Rem.'!X55 -> 0 | U55: =T55*(Remuneración!$AL56+Remuneración!$AN56) -> 0 | V55: =+E55+G55+I55+K55+M55+S55+U55+O55+Q55 -> 0 | W55: =+#REF!-V55+Remuneración!AP56 -> #REF!
B56: =+Remuneración!B58 | C56: =+Remuneración!C58 | D56: =+'Ret. y no Rem.'!D56 -> 0 | E56: =D56*(Remuneración!$AL58+Remuneración!$AN58) -> 0 | F56: =+'Ret. y no Rem.'!F56 -> 0 | G56: =F56*(Remuneración!$AL58+Remuneración!$AN58) -> 0 | H56: =+'Ret. y no Rem.'!H56 -> 0 | I56: =H56*(Remuneración!$AL58+Remuneración!$AN58) -> 0 | J56: =+'Ret. y no Rem.'!J56 -> 0 | K56: =J56*(Remuneración!$AL58+Remuneración!$AN58) -> 0 | L56: =+'Ret. y no Rem.'!L56 -> 0 | M56: =L56*(Remuneración!$AL58+Remuneración!$AN58) -> 0 | N56: ='Ret. y no Rem.'!R56 -> 0 | O56: =N56*(Remuneración!$AL58+Remuneración!$AN58) -> 0 | P56: ='Ret. y no Rem.'!T56 -> 0 | Q56: =P56*(Remuneración!$AL58+Remuneración!$AN58) -> 0 | R56: ='Ret. y no Rem.'!V56 -> 0 | S56: =R56*(Remuneración!$AL58+Remuneración!$AN58) -> 0 | T56: ='Ret. y no Rem.'!X56 -> 0 | U56: =T56*(Remuneración!$AL58+Remuneración!$AN58) -> 0 | V56: =+E56+G56+I56+K56+M56+S56+U56+O56+Q56 -> 0 | W56: =+#REF!-V56+Remuneración!AP58 -> #REF!

Sheet Recibo
B2: Recibo de Sueldos
C5: =IF(OR(Empleador!D6="",J6=""),"",Empleador!D6) -> CARETTA MARIA DEL CARMEN | F5: =IF(OR(Empleador!D8="",J6=""),"",Empleador!D8) -> CMTE RODRIGUEZ Nº 147 | I5: Original para el Empleado
C6: =IF(J6="","","CUIT: "&Empleador!D7) -> CUIT: 27202918684 | F6: =IF(OR(Empleador!D9="",Empleador!D10="",J6="")=TRUE,"",Empleador!D9&"; "&Empleador!D10) -> MALARGUE; Mendoza | I6: Legajo N° | J6: 2
C9: Nombre y Apellido | F9: Fecha de Ingreso | G9: CUIL | H9: Caja de Ahorro N° | I9: AFJP | J9: Remuneración Básica
C10: =IF(J6="","",VLOOKUP(J6,TablaEmpleados,3,FALSE)) -> QUIROGA VANINA LEONELA | F10: =IF($J$6="","",VLOOKUP($J$6,TablaEmpleados,2,FALSE)) -> 40910 | G10: =IF($J$6="","",VLOOKUP($J$6,TablaEmpleados,4,FALSE)) -> 27-34642729-4 | H10: =IF($J$6="","",VLOOKUP($J$6,TablaEmpleados,11,FALSE)) -> 0 | I10: =IF($J$6="","",VLOOKUP($J$6,TablaEmpleados,14,FALSE)) -> SIPA | J10: =Empleados!G9 -> 2043.52
C12: Período depositado | D12: Banco de depósito | H12: Fecha de último deposito | I12: Calificación Profesional
C13: 40878 | D13: SEPSA PAGO FACIL | H13: 40931 | I13: =IF($J$6="","",VLOOKUP($J$6,TablaEmpleados,12,FALSE)) -> VENDEDOR
C15: Período Abonado | E15: Domicilio de Pago | H15: Fecha de Pago | I15: Tarea Desempeñada
C16: =IF(J6="","",Remuneración!C4) -> 41000 | E16: =IF(J6="","",Empleador!D12) -> Malargue, Mza | H16: 41035 | I16: =IF($J$6="","",VLOOKUP($J$6,TablaEmpleados,13,FALSE)) -> Categ. B
C18: Descripción de Conceptos | F18: Unidades | G18: % | H18: Remuneraciones | I18: Descuentos | J18: Conceptos no remunerativos
B19: Omicron System S.A. | C19: =IF($J$6="","",IF(VLOOKUP($J$6,TablaEmpleados,5,FALSE)<>"",Empleados!G6,"")) -> Sueldo Básico | F19: 30 | H19: =J10 -> 2043.52
C20: =IF($J$6="","",IF(VLOOKUP($J$6,TablaEmpleados,7,FALSE)<>"",Empleados!I6,"")) | H20: =IF($J$6="",0,IF(C20="",0,VLOOKUP($J$6,TablaEmpleados,8,FALSE))) -> 0
C21: =IF($J$6="","",IF(VLOOKUP($J$6,TablaEmpleados,9,FALSE)<>"",Empleados!K6,"")) | H21: =IF($J$6="",0,IF(C21="",0,VLOOKUP($J$6,TablaEmpleados,10,FALSE))) -> 0
C22: =IF($J$6="","",IF(VLOOKUP($J$6,TablaRemuneracion,5,FALSE)<>"",Remuneración!F6,"")) | F22: =IF(C22="","",VLOOKUP($J$6,TablaRemuneracion,5,FALSE)) | H22: =IF(C22="",0,IF($J$6="",0,VLOOKUP($J$6,TablaRemuneracion,6,FALSE))) -> 0
C23: =IF($J$6="","",IF(VLOOKUP($J$6,TablaRemuneracion,7,FALSE)<>"",Remuneración!H6,"")) | F23: =IF(C23="","",VLOOKUP($J$6,TablaRemuneracion,7,FALSE)) | H23: =IF(C23="",0,-IF($J$6="",0,VLOOKUP($J$6,TablaRemuneracion,8,FALSE))) -> 0
C24: =IF($J$6="","",IF(VLOOKUP($J$6,TablaRemuneracion,9,FALSE)<>"",Remuneración!J6,"")) | F24: =IF(C24="","",VLOOKUP($J$6,TablaRemuneracion,9,FALSE)) | H24: =IF(C24="",0,IF($J$6="",0,VLOOKUP($J$6,TablaRemuneracion,10,FALSE))) -> 0
C25: =IF($J$6="","",IF(VLOOKUP($J$6,TablaRemuneracion,11,FALSE)<>"",Remuneración!L6,"")) | G25: =IF(C25="","",VLOOKUP($J$6,TablaRemuneracion,11,FALSE)) | H25: =IF($J$6="",0,IF(C25="",0,VLOOKUP($J$6,TablaRemuneracion,12,FALSE))) -> 0
C26: =IF($J$6="","",IF(VLOOKUP($J$6,TablaRemuneracion,13,FALSE)<>"",Remuneración!N6,"")) | G26: =IF(C26="","",VLOOKUP($J$6,TablaRemuneracion,13,FALSE)) | H26: =IF($J$6="",0,IF(C26="",0,VLOOKUP($J$6,TablaRemuneracion,14,FALSE))) -> 0
C27: =IF($J$6="","",IF(VLOOKUP($J$6,TablaRemuneracion,15,FALSE)<>"",Remuneración!P6,"")) | G27: =IF(C27="","",VLOOKUP($J$6,TablaRemuneracion,15,FALSE)) | H27: =IF($J$6="",0,IF(C27="",0,VLOOKUP($J$6,TablaRemuneracion,16,FALSE))) -> 0
C28: =IF($J$6="","",IF(VLOOKUP($J$6,TablaRemuneracion,17,FALSE)<>"",Remuneración!R6,"")) -> Presentismo | G28: =IF(C28="","",VLOOKUP($J$6,TablaRemuneracion,17,FALSE)) -> 0.0833 | H28: =IF($J$6="",0,IF(C28="",0,VLOOKUP($J$6,TablaRemuneracion,18,FALSE))) -> 170.22522
C29: =IF($J$6="","",IF(VLOOKUP($J$6,TablaRemuneracion,19,FALSE)<>"",Remuneración!T6,"")) | G29: =IF(C29="","",VLOOKUP($J$6,TablaRemuneracion,19,FALSE)) | H29: =IF($J$6="",0,IF(C29="",0,VLOOKUP($J$6,TablaRemuneracion,20,FALSE))) -> 0
C30: =IF($J$6="","",IF(VLOOKUP($J$6,TablaRemuneracion,21,FALSE)<>"",Remuneración!V6,"")) | G30: =IF(C30="","",VLOOKUP($J$6,TablaRemuneracion,21,FALSE)) | H30: =IF($J$6="",0,IF(C30="",0,VLOOKUP($J$6,TablaRemuneracion,22,FALSE))) -> 0
C31: =IF($J$6="","",IF(VLOOKUP($J$6,TablaRemuneracion,23,FALSE)<>"",Remuneración!X6,"")) | G31: =IF(C31="","",VLOOKUP($J$6,TablaRemuneracion,23,FALSE)) | H31: =IF($J$6="",0,IF(C31="",0,VLOOKUP($J$6,TablaRemuneracion,24,FALSE))) -> 0
C32: =IF($J$6="","",IF(VLOOKUP($J$6,TablaRemuneracion,25,FALSE)<>"",Remuneración!Z7,"")) | H32: =IF(C32="",0,IF($J$6="",0,VLOOKUP($J$6,TablaRemuneracion,25,FALSE))) -> 0
C33: =IF($J$6="","",IF(VLOOKUP($J$6,TablaRemuneracion,26,FALSE)<>"",Remuneración!AA7,"")) | H33: =IF(C33="",0,IF($J$6="",0,VLOOKUP($J$6,TablaRemuneracion,26,FALSE))) -> 0
C34: =IF($J$6="","",IF(VLOOKUP($J$6,TablaRemuneracion,27,FALSE)<>"",Remuneración!AB7,"")) | H34: =IF(C34="",0,IF($J$6="",0,VLOOKUP($J$6,TablaRemuneracion,27,FALSE))) -> 0
C35: =IF($J$6="","",IF(VLOOKUP($J$6,TablaRemuneracion,28,FALSE)<>"",Remuneración!AC7,"")) | H35: =IF(C35="",0,IF($J$6="",0,VLOOKUP($J$6,TablaRemuneracion,28,FALSE))) -> 0
C36: =IF($J$6="","",IF(VLOOKUP($J$6,TablaRemuneracion,29,FALSE)<>"",Remuneración!AD7,"")) | H36: =IF(C36="",0,IF($J$6="",0,VLOOKUP($J$6,TablaRemuneracion,29,FALSE))) -> 0
C37: =IF($J$6="","",IF(VLOOKUP($J$6,TablaRemuneracion,30,FALSE)<>"",Remuneración!AE7,"")) | H37: =IF(C37="",0,IF($J$6="",0,VLOOKUP($J$6,TablaRemuneracion,30,FALSE))) -> 0
C38: =IF($J$6="","",IF(VLOOKUP($J$6,TablaRemuneracion,32,FALSE)<>"",Remuneración!AF6,"")) | F38: =IF(C38="","",VLOOKUP($J$6,TablaRemuneracion,31,FALSE)) | H38: =IF(C38="",0,IF($J$6="",0,VLOOKUP($J$6,TablaRemuneracion,33,FALSE))) -> 0
C39: =IF($J$6="","",IF(VLOOKUP($J$6,TablaRemuneracion,35,FALSE)<>"",Remuneración!AI6,"")) | F39: =IF(C39="","",VLOOKUP($J$6,TablaRemuneracion,34,FALSE)) | H39: =IF(C39="",0,IF($J$6="",0,VLOOKUP($J$6,TablaRemuneracion,36,FALSE))) -> 0
C40: =IF($J$6="","",IF(VLOOKUP($J$6,TablaNoRemunerativo,3,FALSE)<>"",'Ret. y no Rem.'!D5,"")) -> Jubilación | G40: =IF(C40="","",VLOOKUP($J$6,TablaNoRemunerativo,3,FALSE)) -> 0.11 | I40: =IF(C40="",0,IF($J$6="",0,VLOOKUP($J$6,TablaNoRemunerativo,4,FALSE))) -> 243.51197
C41: =IF($J$6="","",IF(VLOOKUP($J$6,TablaNoRemunerativo,5,FALSE)<>"",'Ret. y no Rem.'!F5,"")) -> Ley 19032 | G41: =IF(C41="","",VLOOKUP($J$6,TablaNoRemunerativo,5,FALSE)) -> 0.03 | I41: =IF(C41="",0,IF($J$6="",0,VLOOKUP($J$6,TablaNoRemunerativo,6,FALSE))) -> 66.412356
C42: =IF($J$6="","",IF(VLOOKUP($J$6,TablaNoRemunerativo,7,FALSE)<>"",'Ret. y no Rem.'!H5,"")) -> Obra Social | G42: =IF(C42="","",VLOOKUP($J$6,TablaNoRemunerativo,7,FALSE)) -> 0.03 | I42: =IF(C42="",0,IF($J$6="",0,VLOOKUP($J$6,TablaNoRemunerativo,8,FALSE))) -> 66.412356
C43: =IF($J$6="","",IF(VLOOKUP($J$6,TablaNoRemunerativo,9,FALSE)<>"",'Ret. y no Rem.'!J5,"")) | G43: =IF(C43="","",VLOOKUP($J$6,TablaNoRemunerativo,9,FALSE)) | I43: =IF(C43="",0,IF($J$6="",0,VLOOKUP($J$6,TablaNoRemunerativo,10,FALSE))) -> 0
C44: =IF($J$6="","",IF(VLOOKUP($J$6,TablaNoRemunerativo,11,FALSE)<>"",'Ret. y no Rem.'!L5,"")) | G44: =IF(C44="","",VLOOKUP($J$6,TablaNoRemunerativo,11,FALSE)) | I44: =IF(C44="",0,IF($J$6="",0,VLOOKUP($J$6,TablaNoRemunerativo,12,FALSE))) -> 0
C45: =IF($J$6="","",IF(VLOOKUP($J$6,TablaNoRemunerativo,13,FALSE)<>"",'Ret. y no Rem.'!N5,"")) | G45: =IF(C45="","",VLOOKUP($J$6,TablaNoRemunerativo,13,FALSE)) | I45: =IF(C45="",0,IF($J$6="",0,VLOOKUP($J$6,TablaNoRemunerativo,14,FALSE))) -> 0
C46: =IF($J$6="","",IF(VLOOKUP($J$6,TablaNoRemunerativo,15,FALSE)<>"",'Ret. y no Rem.'!P5,"")) | G46: =IF(C46="","",VLOOKUP($J$6,TablaNoRemunerativo,15,FALSE)) | I46: =IF(C46="",0,IF($J$6="",0,VLOOKUP($J$6,TablaNoRemunerativo,16,FALSE))) -> 0
C47: =IF($J$6="","",IF(VLOOKUP($J$6,TablaNoRemunerativo,17,FALSE)<>"",'Ret. y no Rem.'!R5,"")) | G47: =IF(C47="","",VLOOKUP($J$6,TablaNoRemunerativo,17,FALSE)) | I47: =IF(C47="",0,IF($J$6="",0,VLOOKUP($J$6,TablaNoRemunerativo,18,FALSE))) -> 0
C48: =IF($J$6="","",IF(VLOOKUP($J$6,TablaNoRemunerativo,19,FALSE)<>"",'Ret. y no Rem.'!T5,"")) | G48: =IF(C48="","",VLOOKUP($J$6,TablaNoRemunerativo,19,FALSE)) | I48: =IF(C48="",0,IF($J$6="",0,VLOOKUP($J$6,TablaNoRemunerativo,20,FALSE))) -> 0
C49: =IF($J$6="","",IF(VLOOKUP($J$6,TablaNoRemunerativo,21,FALSE)<>"",'Ret. y no Rem.'!V5,"")) | G49: =IF(C49="","",VLOOKUP($J$6,TablaNoRemunerativo,21,FALSE)) | I49: =IF(C49="",0,IF($J$6="",0,VLOOKUP($J$6,TablaNoRemunerativo,22,FALSE))) -> 0
C50: =IF($J$6="","",IF(VLOOKUP($J$6,TablaNoRemunerativo,23,FALSE)<>"",'Ret. y no Rem.'!X5,"")) | G50: =IF(C50="","",VLOOKUP($J$6,TablaNoRemunerativo,23,FALSE)) | I50: =IF(C50="",0,IF($J$6="",0,VLOOKUP($J$6,TablaNoRemunerativo,24,FALSE))) -> 0
C51: =IF($J$6="","",IF(VLOOKUP($J$6,TablaNoRemunerativo,25,FALSE)<>"",'Ret. y no Rem.'!Z6,"")) | I51: =IF(C51="",0,IF($J$6="",0,VLOOKUP($J$6,TablaNoRemunerativo,25,FALSE))) -> 0
C52: =IF($J$6="","",IF(VLOOKUP($J$6,TablaNoRemunerativo,26,FALSE)<>"",'Ret. y no Rem.'!AA6,"")) | I52: =IF(C52="",0,IF($J$6="",0,VLOOKUP($J$6,TablaNoRemunerativo,26,FALSE))) -> 0
C53: =IF($J$6="","",IF(VLOOKUP($J$6,TablaNoRemunerativo,27,FALSE)<>"",'Ret. y no Rem.'!AB6,"")) | I53: =IF(C53="",0,IF($J$6="",0,VLOOKUP($J$6,TablaNoRemunerativo,27,FALSE))) -> 0
C54: =IF($J$6="","",IF(VLOOKUP($J$6,TablaNoRemunerativo,29,FALSE)<>"",'Ret. y no Rem.'!AD6,"")) | J54: =IF(C54="",0,IF($J$6="",0,VLOOKUP($J$6,TablaNoRemunerativo,29,FALSE))) -> 0
C55: =IF($J$6="","",IF(VLOOKUP($J$6,TablaNoRemunerativo,30,FALSE)<>"",'Ret. y no Rem.'!AE6,"")) | J55: =IF(C55="",0,IF($J$6="",0,VLOOKUP($J$6,TablaNoRemunerativo,30,FALSE))) -> 0
C56: =IF($J$6="","",IF(VLOOKUP($J$6,TablaNoRemunerativo,31,FALSE)<>"",'Ret. y no Rem.'!AF6,"")) | J56: =IF(C56="",0,IF($J$6="",0,VLOOKUP($J$6,TablaNoRemunerativo,31,FALSE))) -> 0
C57: =IF($J$6="","",IF(VLOOKUP($J$6,TablaNoRemunerativo,32,FALSE)<>"",'Ret. y no Rem.'!AG6,"")) | J57: =IF(C57="",0,IF($J$6="",0,VLOOKUP($J$6,TablaNoRemunerativo,32,FALSE))) -> 0
C58: =IF($J$6="","",IF(VLOOKUP($J$6,TablaNoRemunerativo,33,FALSE)<>"",'Ret. y no Rem.'!AH6,"")) | J58: =IF(C58="","",IF($J$6="",0,VLOOKUP($J$6,TablaNoRemunerativo,33,FALSE)))
C59: =IF($J$6="","",IF(VLOOKUP($J$6,TablaNoRemunerativo,34,FALSE)<>"",'Ret. y no Rem.'!AI6,"")) | J59: =IF(C59="",0,IF($J$6="",0,VLOOKUP($J$6,TablaNoRemunerativo,34,FALSE))) -> 0
C60: =IF($J$6="","",IF(VLOOKUP($J$6,TablaNoRemunerativo,35,FALSE)<>"",'Ret. y no Rem.'!AJ6,"")) | J60: =IF(C60="",0,IF($J$6="",0,VLOOKUP($J$6,TablaNoRemunerativo,35,FALSE))) -> 0
C61: =IF($J$6="","",IF(VLOOKUP($J$6,TablaNoRemunerativo,36,FALSE)<>"",'Ret. y no Rem.'!AK6,"")) | J61: =IF(C61="",0,IF($J$6="",0,VLOOKUP($J$6,TablaNoRemunerativo,36,FALSE))) -> 0
C62: =IF($J$6="","",IF(VLOOKUP($J$6,TablaNoRemunerativo,37,FALSE)<>"",'Ret. y no Rem.'!AL6,"")) -> Redondeo | J62: =IF(C62="",0,IF($J$6="",0,VLOOKUP($J$6,TablaNoRemunerativo,37,FALSE))) -> 0.59147072
C63: =IF(C20="",0,"") -> 0
C64: =IF(C21="",0,"") -> 0
C65: =IF(C22="",0,"") -> 0
C66: =IF(C23="",0,"") -> 0
C67: =IF(C25="",0,"") -> 0
C68: =IF(C26="",0,"") -> 0
C69: =IF(C27="",0,"") -> 0
C70: =IF(C28="",0,"")
C71: =IF(C29="",0,"") -> 0
C72: =IF(C30="",0,"") -> 0
C73: =IF(C31="",0,"") -> 0
C74: =IF(C32="",0,"") -> 0
C75: =IF(C33="",0,"") -> 0
C76: =IF(C34="",0,"") -> 0
C77: =IF(C35="",0,"") -> 0
C78: =IF(C36="",0,"") -> 0
... C90: =IF(C48="",0,"") -> 0
C91: =IF(C54="",0,"") -> 0
C92: =IF(C55="",0,"") -> 0
C93: =IF(C56="",0,"") -> 0
C94: =IF(C57="",0,"") -> 0
C95: =IF(C58="",0,"") -> 0
C96: =IF(C59="",0,"") -> 0
C97: =IF(C62="",0,"")
C98: 0
C99: Observación: | D99: Contrato temporada CCT 130/75
C100: 0
C102: =IF(I5="Original para el empleado","Firma Empleador","Firma Empleado") -> Firma Empleador | G102: Subtotal | H102: =SUBTOTAL(9,H19:H62) -> 2213.7452 | I102: =SUBTOTAL(9,I19:I62) -> 376.33669 | J102: =SUBTOTAL(9,J19:J62) -> 0.59147072
I103: Total neto | J103: =ROUNDUP(L103,0) -> 1838 | L103: =+$H$102+$J$102-$I$102 -> 1838
E104: Recibí conforme la suma de Pesos: | H104: Un mil ochocientos treinta y ocho con 0/100
E105: En concepto de mis haberes correspondientes al periodo arriba indicado y según la presente liquidación, dejando constancia de haber recibido un duplicado de este recibo.

Sheet Recibo SAC
B2: Recibo: Salario Anual Complementario
C5: =IF(OR(Empleador!D6="",J6=""),"",Empleador!D6) -> CARETTA MARIA DEL CARMEN | F5: =IF(OR(Empleador!D8="",J6=""),"",Empleador!D8) -> CMTE RODRIGUEZ Nº 147 | I5: Duplicado del Empleador
C6: =IF(J6="","","CUIT: "&Empleador!D7) -> CUIT: 27202918684 | F6: =IF(OR(Empleador!D9="",Empleador!D10="",J6="")=TRUE,"",Empleador!D9&"; "&Empleador!D10) -> MALARGUE; Mendoza | I6: Legajo N° | J6: 1
C9: Nombre y Apellido | F9: Fecha de Ingreso | G9: CUIL | H9: Caja de Ahorro N° | I9: AFJP | J9: Remuneración Básica
C10: =IF(J6="","",VLOOKUP(J6,TablaEmpleados,3,FALSE)) -> ARANIBAR CLAUDIA CRISTINA | F10: =IF($J$6="","",VLOOKUP($J$6,TablaEmpleados,2,FALSE)) -> 40848 | G10: =IF($J$6="","",VLOOKUP($J$6,TablaEmpleados,4,FALSE)) -> 27-23067512-6 | H10: =IF($J$6="","",VLOOKUP($J$6,TablaEmpleados,11,FALSE)) -> 0 | I10: =IF($J$6="","",VLOOKUP($J$6,TablaEmpleados,14,FALSE)) -> SIPA | J10: =IF($J$6="","",VLOOKUP($J$6,TablaRemuneracion,3,FALSE)) -> |
C12: Período depositado | D12: Banco de depósito | H12: Fecha de último deposito | I12: Calificación Profesional
C13: =Recibo!C13 -> 40878 | D13: SEPSA PAGO FACIL | H13: 40931 | I13: =IF($J$6="","",VLOOKUP($J$6,TablaEmpleados,12,FALSE)) -> VENDEDOR
C15: Período Abonado | E15: Domicilio de Pago | H15: Fecha de Pago | I15: Tarea Desempeñada
C16: =IF(J6="","",Remuneración!C4) -> 41000 | E16: =IF(J6="","",Empleador!D12) -> Malargue, Mza | H16: 40945 | I16: =IF($J$6="","",VLOOKUP($J$6,TablaEmpleados,13,FALSE)) -> Categ. B
C18: Descripción de Conceptos | F18: Unidades | G18: % | H18: Remuneraciones | I18: Descuentos | J18: Conceptos no remunerativos
B19: Omicron System S.A. | C19: =IF($J$6="","",IF(VLOOKUP($J$6,TablaRemuneracion,37,FALSE)<>"",Remuneración!AL7,"")) | H19: =IF($J$6="",0,IF(C19="",0,VLOOKUP($J$6,TablaRemuneracion,37,FALSE))) -> 0
C20: =IF($C$19="","",IF(C19="","",IF($J$6="","",IF(VLOOKUP($J$6,TablaNoRemunerativo,3,FALSE)<>"",'Ret. y no Rem.'!D5,"")))) | G20: =IF(C20="","",VLOOKUP($J$6,TablaNoRemunerativo,3,FALSE)) | I20: =IF(C20="",0,VLOOKUP($J$6,TablaNoRemunerativo,3,FALSE)*H19) -> 0
C21: =IF(C19="","",IF(C19="","",IF($J$6="","",IF(VLOOKUP($J$6,TablaNoRemunerativo,5,FALSE)<>"",'Ret. y no Rem.'!F5,"")))) | G21: =IF(C21="","",VLOOKUP($J$6,TablaNoRemunerativo,5,FALSE)) | I21: =IF(C21="",0,VLOOKUP($J$6,TablaNoRemunerativo,5,FALSE)*H19) -> 0
C22: =IF(C19="","",IF(C19="","",IF($J$6="","",IF(VLOOKUP($J$6,TablaNoRemunerativo,7,FALSE)<>"",'Ret. y no Rem.'!H5,"")))) | G22: =IF(C22="","",VLOOKUP($J$6,TablaNoRemunerativo,7,FALSE)) | I22: =IF(C22="",0,VLOOKUP($J$6,TablaNoRemunerativo,7,FALSE)*H19) -> 0
C23: =IF(C19="","",IF(C19="","",IF($J$6="","",IF(VLOOKUP($J$6,TablaNoRemunerativo,9,FALSE)<>"",'Ret. y no Rem.'!J5,"")))) | G23: =IF(C23="","",VLOOKUP($J$6,TablaNoRemunerativo,9,FALSE)) | I23: =IF(C23="",0,VLOOKUP($J$6,TablaNoRemunerativo,9,FALSE)*H19) -> 0
C24: =IF(C19="","",IF(C19="","",IF($J$6="","",IF(VLOOKUP($J$6,TablaNoRemunerativo,11,FALSE)<>"",'Ret. y no Rem.'!L5,"")))) | G24: =IF(C24="","",VLOOKUP($J$6,TablaNoRemunerativo,11,FALSE)) | I24: =IF(C24="",0,VLOOKUP($J$6,TablaNoRemunerativo,11,FALSE)*H19) -> 0
C25: =IF(C19="","",IF(C19="","",IF($J$6="","",IF(VLOOKUP($J$6,TablaNoRemunerativo,17,FALSE)<>"",'Ret. y no Rem.'!R5,"")))) | G25: =IF(C25="","",VLOOKUP($J$6,TablaNoRemunerativo,17,FALSE)) | I25: =IF(C25="",0,VLOOKUP($J$6,TablaNoRemunerativo,17,FALSE)*H19) -> 0
C26: =IF(C19="","",IF(C19="","",IF($J$6="","",IF(VLOOKUP($J$6,TablaNoRemunerativo,21,FALSE)<>"",'Ret. y no Rem.'!V5,"")))) | G26: =IF(C26="","",VLOOKUP($J$6,TablaNoRemunerativo,21,FALSE)) | I26: =IF(C26="",0,VLOOKUP($J$6,TablaNoRemunerativo,21,FALSE)*H19) -> 0
C27: =IF(C19="","",IF(C19="","",IF($J$6="","",IF(VLOOKUP($J$6,TablaNoRemunerativo,23,FALSE)<>"",'Ret. y no Rem.'!X5,"")))) | G27: =IF(C27="","",VLOOKUP($J$6,TablaNoRemunerativo,23,FALSE)) | I27: =IF(C27="",0,VLOOKUP($J$6,TablaNoRemunerativo,23,FALSE)*H19) -> 0
C28: =IF(C19="","",IF(C19="","",IF($J$6="","",IF(VLOOKUP($J$6,TablaNoRemunerativo,37,FALSE)<>"",'Ret. y no Rem.'!AL6,"")))) | J28: =IF(C28="","",ROUNDUP(L52,0)-L52)
C29: =IF(C20="",0,"") -> 0
C30: =IF(C21="",0,"") -> 0
C31: =IF(C22="",0,"") -> 0
C32: =IF(C23="",0,"") -> 0
C33: =IF(C24="",0,"") -> 0
C34: =IF(C25="",0,"") -> 0
C36: =IF(C26="",0,"") -> 0
C37: =IF(C27="",0,"") -> 0
C38: 0
C39: 0
C40: 0
C41: 0
C42: 0
C43: 0
C44: 0
C45: 0
C46: 0
C47: 0
C48: Observación:
C49: 0
C51: Firma Empleador | G51: Subtotal | H51: =SUBTOTAL(9,H19:H28) -> 0 | I51: =SUBTOTAL(9,I19:I28) -> 0 | J51: =SUBTOTAL(9,J19:J28) -> 0 | L51: Exacto
I52: Total neto | J52: =+$H$51+$J$51-$I$51 -> 0 | L52: =SUBTOTAL(9,H19)-SUBTOTAL(9,I20:I27)+SUBTOTAL(9,J19:J27) -> 0
E53: Recibí conforme la suma de Pesos: | H53: Un mil trescientos noventa y nueve con 0/100
E54: En concepto de mis haberes correspondientes al periodo arriba indicado y según la presente liquidación, dejando constancia de haber recibido un duplicado de este recibo.

Sheet Recibo Vacaciones
B2: Recibo: Vacaciones
C5: =IF(OR(Empleador!D6="",J6=""),"",Empleador!D6) -> CARETTA MARIA DEL CARMEN | F5: =IF(OR(Empleador!D8="",J6=""),"",Empleador!D8) -> CMTE RODRIGUEZ Nº 147 | I5: Duplicado del Empleador
C6: =IF(J6="","","CUIT: "&Empleador!D7) -> CUIT: 27202918684 | F6: =IF(OR(Empleador!D9="",Empleador!D10="",J6="")=TRUE,"",Empleador!D9&"; "&Empleador!D10) -> MALARGUE; Mendoza | I6: Legajo N° | J6: 1
C9: Nombre y Apellido | F9: Fecha de Ingreso | G9: CUIL | H9: Caja de Ahorro N° | I9: AFJP | J9: Remuneración Básica
C10: =IF(J6="","",VLOOKUP(J6,TablaEmpleados,3,FALSE)) -> ARANIBAR CLAUDIA CRISTINA | F10: =IF($J$6="","",VLOOKUP($J$6,TablaEmpleados,2,FALSE)) -> 40848 | G10: =IF($J$6="","",VLOOKUP($J$6,TablaEmpleados,4,FALSE)) -> 27-23067512-6 | H10: =IF($J$6="","",VLOOKUP($J$6,TablaEmpleados,11,FALSE)) -> 0 | I10: =IF($J$6="","",VLOOKUP($J$6,TablaEmpleados,14,FALSE)) -> SIPA | J10: =IF($J$6="","",VLOOKUP($J$6,TablaRemuneracion,3,FALSE)) -> |
C12: Período depositado | D12: Banco de depósito | H12: Fecha de último deposito | I12: Calificación Profesional
I13: =IF($J$6="","",VLOOKUP($J$6,TablaEmpleados,12,FALSE)) -> VENDEDOR
C15: Período Abonado | E15: Domicilio de Pago | H15: Fecha de Pago | I15: Tarea Desempeñada
C16: =IF(J6="","",Remuneración!C4) -> 41000 | E16: =IF(J6="","",Empleador!D12) -> Malargue, Mza | H16: 40578 | I16: =IF($J$6="","",VLOOKUP($J$6,TablaEmpleados,13,FALSE)) -> Categ. B
C18: Descripción de Conceptos | F18: Unidades | G18: % | H18: Remuneraciones | I18: Descuentos | J18: Conceptos no remunerativos
B19: Omicron System S.A. | C19: =IF($J$6="","",IF(VLOOKUP($J$6,TablaRemuneracion,39,FALSE)<>"",Remuneración!AN7,"")) | F19: =IF($J$6="",0,IF(C19="",0,VLOOKUP($J$6,TablaRemuneracion,38,FALSE))) -> 0 | H19: =IF($J$6="",0,IF(C19="",0,VLOOKUP($J$6,TablaRemuneracion,39,FALSE))) -> 0
C20: =IF($J$6="","",IF(C19="","",IF(VLOOKUP($J$6,TablaNoRemunerativo,3,FALSE)<>"",'Ret. y no Rem.'!D5,""))) | G20: =IF(C20="","",VLOOKUP($J$6,TablaNoRemunerativo,3,FALSE)) | I20: =IF(C20="",0,VLOOKUP($J$6,TablaNoRemunerativo,3,FALSE)*H19) -> 0
C21: =IF($J$6="","",IF(C19="","",IF(VLOOKUP($J$6,TablaNoRemunerativo,5,FALSE)<>"",'Ret. y no Rem.'!F5,""))) | G21: =IF(C21="","",VLOOKUP($J$6,TablaNoRemunerativo,5,FALSE)) | I21: =IF(C21="",0,VLOOKUP($J$6,TablaNoRemunerativo,5,FALSE)*H19) -> 0
C22: =IF($J$6="","",IF(C19="","",IF(VLOOKUP($J$6,TablaNoRemunerativo,7,FALSE)<>"",'Ret. y no Rem.'!H5,""))) | G22: =IF(C22="","",VLOOKUP($J$6,TablaNoRemunerativo,7,FALSE)) | I22: =IF(C22="",0,VLOOKUP($J$6,TablaNoRemunerativo,7,FALSE)*H19) -> 0
C23: =IF($J$6="","",IF(C19="","",IF(VLOOKUP($J$6,TablaNoRemunerativo,9,FALSE)<>"",'Ret. y no Rem.'!J5,""))) | G23: =IF(C23="","",VLOOKUP($J$6,TablaNoRemunerativo,9,FALSE)) | I23: =IF(C23="",0,VLOOKUP($J$6,TablaNoRemunerativo,9,FALSE)*H19) -> 0
C24: =IF($J$6="","",IF(C19="","",IF(VLOOKUP($J$6,TablaNoRemunerativo,11,FALSE)<>"",'Ret. y no Rem.'!L5,""))) | G24: =IF(C24="","",VLOOKUP($J$6,TablaNoRemunerativo,11,FALSE)) | I24: =IF(C24="",0,VLOOKUP($J$6,TablaNoRemunerativo,11,FALSE)*H19) -> 0
C25: =IF($J$6="","",IF(C19="","",IF(VLOOKUP($J$6,TablaNoRemunerativo,17,FALSE)<>"",'Ret. y no Rem.'!R5,""))) | G25: =IF(C25="","",VLOOKUP($J$6,TablaNoRemunerativo,17,FALSE)) | I25: =IF(C25="",0,VLOOKUP($J$6,TablaNoRemunerativo,17,FALSE)*H19) -> 0
C26: =IF($J$6="","",IF(C19="","",IF(VLOOKUP($J$6,TablaNoRemunerativo,19,FALSE)<>"",'Ret. y no Rem.'!T5,""))) | G26: =IF(C26="","",VLOOKUP($J$6,TablaNoRemunerativo,19,FALSE)) | I26: =IF(C26="",0,VLOOKUP($J$6,TablaNoRemunerativo,19,FALSE)*H19) -> 0
C27: =IF($J$6="","",IF(C19="","",IF(VLOOKUP($J$6,TablaNoRemunerativo,21,FALSE)<>"",'Ret. y no Rem.'!V5,""))) | G27: =IF(C27="","",VLOOKUP($J$6,TablaNoRemunerativo,21,FALSE)) | I27: =IF(C27="",0,VLOOKUP($J$6,TablaNoRemunerativo,21,FALSE)*H19) -> 0
C28: =IF($J$6="","",IF(C19="","",IF(VLOOKUP($J$6,TablaNoRemunerativo,23,FALSE)<>"",'Ret. y no Rem.'!X5,""))) | G28: =IF(C28="","",VLOOKUP($J$6,TablaNoRemunerativo,23,FALSE)) | I28: =IF(C28="",0,VLOOKUP($J$6,TablaNoRemunerativo,23,FALSE)*H19) -> 0
C29: =IF($J$6="","",IF(C19="","",IF(VLOOKUP($J$6,TablaNoRemunerativo,37,FALSE)<>"",'Ret. y no Rem.'!AL6,""))) | J29: =IF(C29="","",ROUNDUP(L56,0)-L56)
C30: =IF(C20="",0,"") -> 0
C31: =IF(C21="",0,"") -> 0
C32: =IF(C22="",0,"") -> 0
C33: =IF(C23="",0,"") -> 0
C34: =IF(C24="",0,"") -> 0
C35: =IF(C25="",0,"") -> 0
C36: =IF(C26="",0,"") -> 0
C37: =IF(C27="",0,"") -> 0
C38: =IF(C28="",0,"") -> 0
C39: 0
C40: 0
C41: 0
C42: 0
C43: 0
C44: 0
C45: 0
C46: 0
C47: 0
C48: 0
C49: 0
C50: 0
C51: 0
C52: Observación:
C53: 0
C55: Firma Empleador | G55: Subtotal | H55: =SUBTOTAL(9,H19:H29) -> 0 | I55: =SUBTOTAL(9,I19:I29) -> 0 | J55: =SUBTOTAL(9,J19:J29) -> 0 | L55: Exacto
I56: Total neto | J56: =+$H$55+$J$55-$I$55 -> 0 | L56: =SUBTOTAL(9,H19)-SUBTOTAL(9,I20:I28)+SUBTOTAL(9,J19:J28) -> 0
E57: Recibí conforme la suma de Pesos: | H57: Novecientos treinta y dos con 0/100
E58: En concepto de mis haberes correspondientes al periodo arriba indicado y según la presente liquidación, dejando constancia de haber recibido un duplicado de este recibo.

Sheet Reporte
B2: Reporte
B4: =IF(Empleador!D6="","",Empleador!D6) -> CARETTA MARIA DEL CARMEN | G4: Período | H4: =IF(Remuneración!C4="","",Remuneración!C4) -> 41000
B6: Apellido y Nombre | C6: N° Legajo | D6: CUIL | E6: N° de Caja de Ahorro | F6: SB + SAC + VAC | G6: Total Descuentos | H6: Total Conc. no Remun. | I6: Sueldo Neto
B7: =IF(Remuneración!C8="","",Remuneración!C8) -> ARANIBAR CLAUDIA CRISTINA | C7: =IF(Remuneración!B8="","",Remuneración!B8) -> 1 | D7: =IF(Empleados!F8="","",Empleados!F8) -> 27-23067512-6 | E7: =IF(Empleados!M8="","",Empleados!M8) | F7: =IF(Remuneración!AP8="","",Remuneración!AP8+Remuneración!AL8+Remuneración!AN8) -> #VALUE! | G7: ='Ret. y no Rem.'!AC7+'Ret. VAV y SAC'!V7 -> #VALUE! | H7: ='Ret. y no Rem.'!AM7+'Ret. y no Rem.'!AL7 -> #VALUE! | I7: =ROUNDUP(IF(ISERROR(H7+F7-G7),"",H7+F7-G7),0) -> #VALUE!
B8: =IF(Remuneración!C9="","",Remuneración!C9) -> QUIROGA VANINA LEONELA | C8: =IF(Remuneración!B9="","",Remuneración!B9) -> 2 | D8: =IF(Empleados!F9="","",Empleados!F9) -> 27-34642729-4 | E8: =IF(Empleados!M9="","",Empleados!M9) | F8: =IF(Remuneración!AP9="","",Remuneración!AP9+Remuneración!AL9+Remuneración!AN9) -> 2213.7452 | G8: =+'Ret. y no Rem.'!AC8+'Ret. VAV y SAC'!V8 -> 376.33669 | H8: ='Ret. y no Rem.'!AM8+'Ret. y no Rem.'!AL8 -> 0.59147072 | I8: =ROUNDUP(IF(ISERROR(H8+F8-G8),"",H8+F8-G8),0) -> 1838
B9: =IF(Remuneración!C10="","",Remuneración!C10) | C9: =IF(Remuneración!B10="","",Remuneración!B10) | D9: =IF(Empleados!F10="","",Empleados!F10) | E9: =IF(Empleados!M10="","",Empleados!M10) | F9: =IF(Remuneración!AP10="","",Remuneración!AP10+Remuneración!AL10+Remuneración!AN10) -> 0 | G9: =+'Ret. y no Rem.'!AC9+'Ret. VAV y SAC'!V9 -> 0 | H9: ='Ret. y no Rem.'!AM9+'Ret. y no Rem.'!AL9 -> 0 | I9: =ROUNDUP(IF(ISERROR(H9+F9-G9),"",H9+F9-G9),0) -> 0
B10: =IF(Remuneración!C11="","",Remuneración!C11) | C10: =IF(Remuneración!B11="","",Remuneración!B11) | D10: =IF(Empleados!F11="","",Empleados!F11) | E10: =IF(Empleados!M11="","",Empleados!M11) | F10: =IF(Remuneración!AP11="","",Remuneración!AP11+Remuneración!AL11+Remuneración!AN11) -> 0 | G10: =+'Ret. y no Rem.'!AC10+'Ret. VAV y SAC'!V10 -> 0 | H10: ='Ret. y no Rem.'!AM10+'Ret. y no Rem.'!AL10 -> 0 | I10: =ROUNDUP(IF(ISERROR(H10+F10-G10),"",H10+F10-G10),0) -> 0
B11: =IF(Remuneración!C12="","",Remuneración!C12) | C11: =IF(Remuneración!B12="","",Remuneración!B12) | D11: =IF(Empleados!F12="","",Empleados!F12) | E11: =IF(Empleados!M12="","",Empleados!M12) | F11: =IF(Remuneración!AP12="","",Remuneración!AP12+Remuneración!AL12+Remuneración!AN12) -> 0 | G11: =+'Ret. y no Rem.'!AC11+'Ret. VAV y SAC'!V11 -> 0 | H11: ='Ret. y no Rem.'!AM11+'Ret. y no Rem.'!AL11 -> 0 | I11: =ROUNDUP(IF(ISERROR(H11+F11-G11),"",H11+F11-G11),0) -> 0
B12: =IF(Remuneración!C13="","",Remuneración!C13) | C12: =IF(Remuneración!B13="","",Remuneración!B13) | D12: =IF(Empleados!F13="","",Empleados!F13) | E12: =IF(Empleados!M13="","",Empleados!M13) | F12: =IF(Remuneración!AP13="","",Remuneración!AP13+Remuneración!AL13+Remuneración!AN13) -> 0 | G12: =+'Ret. y no Rem.'!AC12+'Ret. VAV y SAC'!V12 -> 0 | H12: ='Ret. y no Rem.'!AM12+'Ret. y no Rem.'!AL12 -> 0 | I12: =ROUNDUP(IF(ISERROR(H12+F12-G12),"",H12+F12-G12),0) -> 0
B13: =IF(Remuneración!C14="","",Remuneración!C14) | C13: =IF(Remuneración!B14="","",Remuneración!B14) | D13: =IF(Empleados!F14="","",Empleados!F14) | E13: =IF(Empleados!M14="","",Empleados!M14) | F13: =IF(Remuneración!AP14="","",Remuneración!AP14+Remuneración!AL14+Remuneración!AN14) -> 0 | G13: =+'Ret. y no Rem.'!AC13+'Ret. VAV y SAC'!V13 -> 0 | H13: ='Ret. y no Rem.'!AM13+'Ret. y no Rem.'!AL13 -> 0 | I13: =ROUNDUP(IF(ISERROR(H13+F13-G13),"",H13+F13-G13),0) -> 0
B14: =IF(Remuneración!C15="","",Remuneración!C15) | C14: =IF(Remuneración!B15="","",Remuneración!B15) | D14: =IF(Empleados!F15="","",Empleados!F15) | E14: =IF(Empleados!M15="","",Empleados!M15) | F14: =IF(Remuneración!AP15="","",Remuneración!AP15+Remuneración!AL15+Remuneración!AN15) -> 0 | G14: =+'Ret. y no Rem.'!AC14+'Ret. VAV y SAC'!V14 -> 0 | H14: ='Ret. y no Rem.'!AM14+'Ret. y no Rem.'!AL14 -> 0 | I14: =ROUNDUP(IF(ISERROR(H14+F14-G14),"",H14+F14-G14),0) -> 0
B15: =IF(Remuneración!C16="","",Remuneración!C16) | C15: =IF(Remuneración!B16="","",Remuneración!B16) | D15: =IF(Empleados!F16="","",Empleados!F16) | E15: =IF(Empleados!M16="","",Empleados!M16) | F15: =IF(Remuneración!AP16="","",Remuneración!AP16+Remuneración!AL16+Remuneración!AN16) -> 0 | G15: =+'Ret. y no Rem.'!AC15+'Ret. VAV y SAC'!V15 -> 0 | H15: ='Ret. y no Rem.'!AM15+'Ret. y no Rem.'!AL15 -> 0 | I15: =ROUNDUP(IF(ISERROR(H15+F15-G15),"",H15+F15-G15),0) -> 0
B16: =IF(Remuneración!C17="","",Remuneración!C17) | C16: =IF(Remuneración!B17="","",Remuneración!B17) | D16: =IF(Empleados!F17="","",Empleados!F17) | E16: =IF(Empleados!M17="","",Empleados!M17) | F16: =IF(Remuneración!AP17="","",Remuneración!AP17+Remuneración!AL17+Remuneración!AN17) -> 0 | G16: =+'Ret. y no Rem.'!AC16+'Ret. VAV y SAC'!V16 -> 0 | H16: ='Ret. y no Rem.'!AM16+'Ret. y no Rem.'!AL16 -> 0 | I16: =ROUNDUP(IF(ISERROR(H16+F16-G16),"",H16+F16-G16),0) -> 0
B17: =IF(Remuneración!C18="","",Remuneración!C18) | C17: =IF(Remuneración!B18="","",Remuneración!B18) | D17: =IF(Empleados!F18="","",Empleados!F18) | E17: =IF(Empleados!M18="","",Empleados!M18) | F17: =IF(Remuneración!AP18="","",Remuneración!AP18+Remuneración!AL18+Remuneración!AN18) -> 0 | G17: =+'Ret. y no Rem.'!AC17+'Ret. VAV y SAC'!V17 -> 0 | H17: ='Ret. y no Rem.'!AM17+'Ret. y no Rem.'!AL17 -> 0 | I17: =ROUNDUP(IF(ISERROR(H17+F17-G17),"",H17+F17-G17),0) -> 0
B18: =IF(Remuneración!C19="","",Remuneración!C19) | C18: =IF(Remuneración!B19="","",Remuneración!B19) | D18: =IF(Empleados!F19="","",Empleados!F19) | E18: =IF(Empleados!M19="","",Empleados!M19) | F18: =IF(Remuneración!AP19="","",Remuneración!AP19+Remuneración!AL19+Remuneración!AN19) -> 0 | G18: =+'Ret. y no Rem.'!AC18+'Ret. VAV y SAC'!V18 -> 0 | H18: ='Ret. y no Rem.'!AM18+'Ret. y no Rem.'!AL18 -> 0 | I18: =ROUNDUP(IF(ISERROR(H18+F18-G18),"",H18+F18-G18),0) -> 0
B19: =IF(Remuneración!C20="","",Remuneración!C20) | C19: =IF(Remuneración!B20="","",Remuneración!B20) | D19: =IF(Empleados!F20="","",Empleados!F20) | E19: =IF(Empleados!M20="","",Empleados!M20) | F19: =IF(Remuneración!AP20="","",Remuneración!AP20+Remuneración!AL20+Remuneración!AN20) -> 0 | G19: =+'Ret. y no Rem.'!AC19+'Ret. VAV y SAC'!V19 -> 0 | H19: ='Ret. y no Rem.'!AM19+'Ret. y no Rem.'!AL19 -> 0 | I19: =ROUNDUP(IF(ISERROR(H19+F19-G19),"",H19+F19-G19),0) -> 0
... B55: =IF(Remuneración!C56="","",Remuneración!C56) | C55: =IF(Remuneración!B56="","",Remuneración!B56) | D55: =IF(Empleados!F56="","",Empleados!F56) | E55: =IF(Empleados!M56="","",Empleados!M56) | F55: =IF(Remuneración!AP56="","",Remuneración!AP56+Remuneración!AL56+Remuneración!AN56) -> 0 | G55: =+'Ret. y no Rem.'!AC55+'Ret. VAV y SAC'!V55 -> 0 | H55: ='Ret. y no Rem.'!AM55+'Ret. y no Rem.'!AL55 -> 0 | I55: =ROUNDUP(IF(ISERROR(H55+F55-G55),"",H55+F55-G55),0) -> 0
B56: =IF(Remuneración!C58="","",Remuneración!C58) | C56: =IF(Remuneración!B58="","",Remuneración!B58) | D56: =IF(Empleados!F57="","",Empleados!F57) | E56: =IF(Empleados!M57="","",Empleados!M57) | F56: =IF(Remuneración!AP58="","",Remuneración!AP58+Remuneración!AL58+Remuneración!AN58) -> 0 | G56: =+'Ret. y no Rem.'!AC56+'Ret. VAV y SAC'!V56 -> 0 | H56: ='Ret. y no Rem.'!AM56+'Ret. y no Rem.'!AL56 -> 0 | I56: =ROUNDUP(IF(ISERROR(H56+F56-G56),"",H56+F56-G56),0) -> 0

Sheet Importante
C4: Liquidación de Sueldos Mensuales
